Workbook
Name TblAPIFactory: 'API Raw'!$E$11:$G$32
Name TblAPIHQ: 'API Raw'!$S$11:$AQ$11
Name TblAPIMines: 'API Raw'!$N$30:$AO$51
Name TblAPISpecial: 'API Raw'!$P$11:$Q$24
Name TblAPIWarehouse: 'API Raw'!$J$11:$L$76
Name TblFactoryBasics: Static!$B$4:$E$25
Name TblFactoryInput: Static!$H$4:$J$68
Name TblFactoryUpgrades: Static!$M$4:$O$89
Name TblMarket: Markets!$F$4:$J$61
Name TblMineBasics: Static!$R$4:$Y$17
Name TblRecycleBasics: Static!$AH$23:$AQ$32
Name TblResourcesType: Static!$AB$4:$AE$61
Name TblSpecialBasics: Static!$AH$3:$AO$17
Name TblUserFactories: UserBuildings!$K$5:$L$26
Name TblUserMines: UserBuildings!$B$5:$I$18
Name TblUserWarehouse: UserBuildings!$Y$5:$AA$40

Sheet Supply Chain
B1: Profit Totals | C1: Daily All | D1: Daily Mine | E1: Daily Factory | F1: Hourly All | I1: Hourly Mine | J1: Hourly Factory | K1: Minute All | L1: Second All
B2: Adj For Use | C2: =M57-MAX(UserBuildings!B26:E26) -> #N/A | D2: =E48 -> 4.9211496e+11 | E2: =M56 -> #N/A | F2: =J57-(MAX(UserBuildings!B26:E26)/24) -> #N/A | I2: =C48 -> 1.0342045e+10 | J2: =J56 -> #N/A | K2: =F2/60 -> #N/A | L2: =K2/60 -> #N/A
B4: Biggest shortages - Production
B6: Resource | C6: Avg production/hour | D6: Required/hour | E6: Ratio @100% maint | F6: Daily Purchase Req | G6: WH LV | I6: Product | J6: Produce_Hr | K6: Req_Hr | L6: Ratio @100% Use | M6: Daily Purchase Req | N6: WH LV
B7: Clay | C7: =VLOOKUP(B7,TblUserMines,6,FALSE) -> 35844.48 | D7: =SUMIFS(Calc!$I$4:$I$100,Calc!$H$4:$H$100,B7) -> 427200 | E7: =IFERROR(D7/C7,"BUYALL") -> 11.918153 | F7: =IF(((D7-C7)*24)<0,0,((D7-C7)*24)) -> 9392532.5 | G7: =IF(ROUNDUP(SQRT((D7*24)/5000),0)<ROUNDUP(SQRT((C7*24)/5000),0),ROUNDUP(SQRT((C7*24)/5000),0),ROUNDUP(SQRT((D7*24)/5000),0)) -> 46 | I7: =Calc!C4 -> Bricks | J7: =Calc!D4 -> 284800 | K7: =Calc!M4 -> 0 | L7: =IFERROR(K7/J7,0) -> 0 | M7: =IF(((K7-J7)*24)<0,0,((K7-J7)*24)) -> 0 | N7: =IF(ROUNDUP(SQRT((K7*24)/5000),0)<ROUNDUP(SQRT((J7*24)/5000),0),ROUNDUP(SQRT((J7*24)/5000),0),ROUNDUP(SQRT((K7*24)/5000),0)) -> 37
B8: Limestone | C8: =VLOOKUP(B8,TblUserMines,6,FALSE) -> 3686.76 | D8: =SUMIFS(Calc!$I$4:$I$100,Calc!$H$4:$H$100,B8) -> 129560 | E8: =IFERROR(D8/C8,"BUYALL") -> 35.141967 | F8: =IF(((D8-C8)*24)<0,0,((D8-C8)*24)) -> 3020957.8 | G8: =IF(ROUNDUP(SQRT((D8*24)/5000),0)<ROUNDUP(SQRT((C8*24)/5000),0),ROUNDUP(SQRT((C8*24)/5000),0),ROUNDUP(SQRT((D8*24)/5000),0)) -> 25 | I8: =Calc!C5 -> Concrete | J8: =Calc!D5 -> 327600 | K8: =Calc!M5 -> 0 | L8: =IFERROR(K8/J8,0) -> 0 | M8: =IF(((K8-J8)*24)<0,0,((K8-J8)*24)) -> 0 | N8: =IF(ROUNDUP(SQRT((K8*24)/5000),0)<ROUNDUP(SQRT((J8*24)/5000),0),ROUNDUP(SQRT((J8*24)/5000),0),ROUNDUP(SQRT((K8*24)/5000),0)) -> 40
B9: Gravel | C9: =VLOOKUP(B9,TblUserMines,6,FALSE) -> 0 | D9: =SUMIFS(Calc!$I$4:$I$100,Calc!$H$4:$H$100,B9) -> 70200 | E9: =IFERROR(D9/C9,"BUYALL") -> BUYALL | F9: =IF(((D9-C9)*24)<0,0,((D9-C9)*24)) -> 1684800 | G9: =IF(ROUNDUP(SQRT((D9*24)/5000),0)<ROUNDUP(SQRT((C9*24)/5000),0),ROUNDUP(SQRT((C9*24)/5000),0),ROUNDUP(SQRT((D9*24)/5000),0)) -> 19 | I9: =Calc!C6 -> Fertilizer | J9: =Calc!D6 -> 77440 | K9: =Calc!M6 -> 0 | L9: =IFERROR(K9/J9,0) -> 0 | M9: =IF(((K9-J9)*24)<0,0,((K9-J9)*24)) -> 0 | N9: =IF(ROUNDUP(SQRT((K9*24)/5000),0)<ROUNDUP(SQRT((J9*24)/5000),0),ROUNDUP(SQRT((J9*24)/5000),0),ROUNDUP(SQRT((K9*24)/5000),0)) -> 20
B10: Coal | C10: =VLOOKUP(B10,TblUserMines,6,FALSE) -> 270153.66 | D10: =SUMIFS(Calc!$I$4:$I$100,Calc!$H$4:$H$100,B10) -> 292500 | E10: =IFERROR(D10/C10,"BUYALL") -> 1.0827171 | F10: =IF(((D10-C10)*24)<0,0,((D10-C10)*24)) -> 536312.16 | G10: =IF(ROUNDUP(SQRT((D10*24)/5000),0)<ROUNDUP(SQRT((C10*24)/5000),0),ROUNDUP(SQRT((C10*24)/5000),0),ROUNDUP(SQRT((D10*24)/5000),0)) -> 38 | I10: =Calc!C7 -> Steel | J10: =Calc!D7 -> 29250 | K10: =Calc!M7 -> 2100 | L10: =IFERROR(K10/J10,0) -> 0.071794872 | M10: =IF(((K10-J10)*24)<0,0,((K10-J10)*24)) -> 0 | N10: =IF(ROUNDUP(SQRT((K10*24)/5000),0)<ROUNDUP(SQRT((J10*24)/5000),0),ROUNDUP(SQRT((J10*24)/5000),0),ROUNDUP(SQRT((K10*24)/5000),0)) -> 12
B11: Iron Ore | C11: =VLOOKUP(B11,TblUserMines,6,FALSE) -> 132299.02 | D11: =SUMIFS(Calc!$I$4:$I$100,Calc!$H$4:$H$100,B11) -> 204750 | E11: =IFERROR(D11/C11,"BUYALL") -> 1.5476305 | F11: =IF(((D11-C11)*24)<0,0,((D11-C11)*24)) -> 1738823.5 | G11: =IF(ROUNDUP(SQRT((D11*24)/5000),0)<ROUNDUP(SQRT((C11*24)/5000),0),ROUNDUP(SQRT((C11*24)/5000),0),ROUNDUP(SQRT((D11*24)/5000),0)) -> 32 | I11: =Calc!C8 -> Fossil fuel | J11: =Calc!D8 -> 40320 | K11: =Calc!M8 -> 30080 | L11: =IFERROR(K11/J11,0) -> 0.74603175 | M11: =IF(((K11-J11)*24)<0,0,((K11-J11)*24)) -> 0 | N11: =IF(ROUNDUP(SQRT((K11*24)/5000),0)<ROUNDUP(SQRT((J11*24)/5000),0),ROUNDUP(SQRT((J11*24)/5000),0),ROUNDUP(SQRT((K11*24)/5000),0)) -> 14
B12: Crude Oil | C12: =VLOOKUP(B12,TblUserMines,6,FALSE) -> 6979.56 | D12: =SUMIFS(Calc!$I$4:$I$100,Calc!$H$4:$H$100,B12) -> 47700 | E12: =IFERROR(D12/C12,"BUYALL") -> 6.8342417 | F12: =IF(((D12-C12)*24)<0,0,((D12-C12)*24)) -> 977290.56 | G12: =IF(ROUNDUP(SQRT((D12*24)/5000),0)<ROUNDUP(SQRT((C12*24)/5000),0),ROUNDUP(SQRT((C12*24)/5000),0),ROUNDUP(SQRT((D12*24)/5000),0)) -> 16 | I12: =Calc!C9 -> Glass | J12: =Calc!D9 -> 30080 | K12: =Calc!M9 -> 0 | L12: =IFERROR(K12/J12,0) -> 0 | M12: =IF(((K12-J12)*24)<0,0,((K12-J12)*24)) -> 0 | N12: =IF(ROUNDUP(SQRT((K12*24)/5000),0)<ROUNDUP(SQRT((J12*24)/5000),0),ROUNDUP(SQRT((J12*24)/5000),0),ROUNDUP(SQRT((K12*24)/5000),0)) -> 13
B13: Quartz Sand | C13: =VLOOKUP(B13,TblUserMines,6,FALSE) -> 0 | D13: =SUMIFS(Calc!$I$4:$I$100,Calc!$H$4:$H$100,B13) -> 22560 | E13: =IFERROR(D13/C13,"BUYALL") -> BUYALL | F13: =IF(((D13-C13)*24)<0,0,((D13-C13)*24)) -> 541440 | G13: =IF(ROUNDUP(SQRT((D13*24)/5000),0)<ROUNDUP(SQRT((C13*24)/5000),0),ROUNDUP(SQRT((C13*24)/5000),0),ROUNDUP(SQRT((D13*24)/5000),0)) -> 11 | I13: =Calc!C10 -> Copper | J13: =Calc!D10 -> 11340 | K13: =Calc!M10 -> 10280 | L13: =IFERROR(K13/J13,0) -> 0.90652557 | M13: =IF(((K13-J13)*24)<0,0,((K13-J13)*24)) -> 0 | N13: =IF(ROUNDUP(SQRT((K13*24)/5000),0)<ROUNDUP(SQRT((J13*24)/5000),0),ROUNDUP(SQRT((J13*24)/5000),0),ROUNDUP(SQRT((K13*24)/5000),0)) -> 8
B14: Chalcopyrite | C14: =VLOOKUP(B14,TblUserMines,6,FALSE) -> 0 | D14: =SUMIFS(Calc!$I$4:$I$100,Calc!$H$4:$H$100,B14) -> 34020 | E14: =IFERROR(D14/C14,"BUYALL") -> BUYALL | F14: =IF(((D14-C14)*24)<0,0,((D14-C14)*24)) -> 816480 | G14: =IF(ROUNDUP(SQRT((D14*24)/5000),0)<ROUNDUP(SQRT((C14*24)/5000),0),ROUNDUP(SQRT((C14*24)/5000),0),ROUNDUP(SQRT((D14*24)/5000),0)) -> 13 | I14: =Calc!C11 -> Insecticides | J14: =Calc!D11 -> 133000 | K14: =Calc!M11 -> 0 | L14: =IFERROR(K14/J14,0) -> 0 | M14: =IF(((K14-J14)*24)<0,0,((K14-J14)*24)) -> 0 | N14: =IF(ROUNDUP(SQRT((K14*24)/5000),0)<ROUNDUP(SQRT((J14*24)/5000),0),ROUNDUP(SQRT((J14*24)/5000),0),ROUNDUP(SQRT((K14*24)/5000),0)) -> 26
B15: Bauxite | C15: =VLOOKUP(B15,TblUserMines,6,FALSE) -> 7239.26 | D15: =SUMIFS(Calc!$I$4:$I$100,Calc!$H$4:$H$100,B15) -> 88320 | E15: =IFERROR(D15/C15,"BUYALL") -> 12.200142 | F15: =IF(((D15-C15)*24)<0,0,((D15-C15)*24)) -> 1945937.8 | G15: =IF(ROUNDUP(SQRT((D15*24)/5000),0)<ROUNDUP(SQRT((C15*24)/5000),0),ROUNDUP(SQRT((C15*24)/5000),0),ROUNDUP(SQRT((D15*24)/5000),0)) -> 21 | I15: =Calc!C12 -> Aluminium | J15: =Calc!D12 -> 14720 | K15: =Calc!M12 -> 10300 | L15: =IFERROR(K15/J15,0) -> 0.69972826 | M15: =IF(((K15-J15)*24)<0,0,((K15-J15)*24)) -> 0 | N15: =IF(ROUNDUP(SQRT((K15*24)/5000),0)<ROUNDUP(SQRT((J15*24)/5000),0),ROUNDUP(SQRT((J15*24)/5000),0),ROUNDUP(SQRT((K15*24)/5000),0)) -> 9
B16: Lithium Ore | C16: =VLOOKUP(B16,TblUserMines,6,FALSE) -> 3194800 | D16: =SUMIFS(Calc!$I$4:$I$100,Calc!$H$4:$H$100,B16) -> 621000 | E16: =IFERROR(D16/C16,"BUYALL") -> 0.19437836 | F16: =IF(((D16-C16)*24)<0,0,((D16-C16)*24)) -> 0 | G16: =IF(ROUNDUP(SQRT((D16*24)/5000),0)<ROUNDUP(SQRT((C16*24)/5000),0),ROUNDUP(SQRT((C16*24)/5000),0),ROUNDUP(SQRT((D16*24)/5000),0)) -> 124 | I16: =Calc!C13 -> Plastics | J16: =Calc!D13 -> 73800 | K16: =Calc!M13 -> 51760 | L16: =IFERROR(K16/J16,0) -> 0.70135501 | M16: =IF(((K16-J16)*24)<0,0,((K16-J16)*24)) -> 0 | N16: =IF(ROUNDUP(SQRT((K16*24)/5000),0)<ROUNDUP(SQRT((J16*24)/5000),0),ROUNDUP(SQRT((J16*24)/5000),0),ROUNDUP(SQRT((K16*24)/5000),0)) -> 19
B17: Ilmenite | C17: =VLOOKUP(B17,TblUserMines,6,FALSE) -> 0 | D17: =SUMIFS(Calc!$I$4:$I$100,Calc!$H$4:$H$100,B17) -> 13440 | E17: =IFERROR(D17/C17,"BUYALL") -> BUYALL | F17: =IF(((D17-C17)*24)<0,0,((D17-C17)*24)) -> 322560 | G17: =IF(ROUNDUP(SQRT((D17*24)/5000),0)<ROUNDUP(SQRT((C17*24)/5000),0),ROUNDUP(SQRT((C17*24)/5000),0),ROUNDUP(SQRT((D17*24)/5000),0)) -> 9 | I17: =Calc!C14 -> Lithium | J17: =Calc!D14 -> 27000 | K17: =Calc!M14 -> 20400 | L17: =IFERROR(K17/J17,0) -> 0.75555556 | M17: =IF(((K17-J17)*24)<0,0,((K17-J17)*24)) -> 0 | N17: =IF(ROUNDUP(SQRT((K17*24)/5000),0)<ROUNDUP(SQRT((J17*24)/5000),0),ROUNDUP(SQRT((J17*24)/5000),0),ROUNDUP(SQRT((K17*24)/5000),0)) -> 12
B18: Silver Ore | C18: =VLOOKUP(B18,TblUserMines,6,FALSE) -> 32797.66 | D18: =SUMIFS(Calc!$I$4:$I$100,Calc!$H$4:$H$100,B18) -> 5760 | E18: =IFERROR(D18/C18,"BUYALL") -> 0.17562229 | F18: =IF(((D18-C18)*24)<0,0,((D18-C18)*24)) -> 0 | G18: =IF(ROUNDUP(SQRT((D18*24)/5000),0)<ROUNDUP(SQRT((C18*24)/5000),0),ROUNDUP(SQRT((C18*24)/5000),0),ROUNDUP(SQRT((D18*24)/5000),0)) -> 13 | I18: =Calc!C15 -> Batteries | J18: =Calc!D15 -> 10200 | K18: =Calc!M15 -> 600 | L18: =IFERROR(K18/J18,0) -> 0.058823529 | M18: =IF(((K18-J18)*24)<0,0,((K18-J18)*24)) -> 0 | N18: =IF(ROUNDUP(SQRT((K18*24)/5000),0)<ROUNDUP(SQRT((J18*24)/5000),0),ROUNDUP(SQRT((J18*24)/5000),0),ROUNDUP(SQRT((K18*24)/5000),0)) -> 7
... B20: Rough Diamonds | C20: =VLOOKUP(B20,TblUserMines,6,FALSE) -> 5174400 | D20: =SUMIFS(Calc!$I$4:$I$100,Calc!$H$4:$H$100,B20) -> 2400000 | E20: =IFERROR(D20/C20,"BUYALL") -> 0.46382189 | F20: =IF(((D20-C20)*24)<0,0,((D20-C20)*24)) -> 0 | G20: =IF(ROUNDUP(SQRT((D20*24)/5000),0)<ROUNDUP(SQRT((C20*24)/5000),0),ROUNDUP(SQRT((C20*24)/5000),0),ROUNDUP(SQRT((D20*24)/5000),0)) -> 158 | I20: =Calc!C17 -> Silicon | J20: =Calc!D17 -> 0 | K20: =Calc!M17 -> 2160 | L20: =IFERROR(K20/J20,0) -> 0 | M20: =IF(((K20-J20)*24)<0,0,((K20-J20)*24)) -> 51840 | N20: =IF(ROUNDUP(SQRT((K20*24)/5000),0)<ROUNDUP(SQRT((J20*24)/5000),0),ROUNDUP(SQRT((J20*24)/5000),0),ROUNDUP(SQRT((K20*24)/5000),0)) -> 4
I21: =Calc!C18 -> Electronics | J21: =Calc!D18 -> 17280 | K21: =Calc!M18 -> 2320 | L21: =IFERROR(K21/J21,0) -> 0.13425926 | M21: =IF(((K21-J21)*24)<0,0,((K21-J21)*24)) -> 0 | N21: =IF(ROUNDUP(SQRT((K21*24)/5000),0)<ROUNDUP(SQRT((J21*24)/5000),0),ROUNDUP(SQRT((J21*24)/5000),0),ROUNDUP(SQRT((K21*24)/5000),0)) -> 10
I22: =Calc!C19 -> Titanium | J22: =Calc!D19 -> 6720 | K22: =Calc!M19 -> 4640 | L22: =IFERROR(K22/J22,0) -> 0.69047619 | M22: =IF(((K22-J22)*24)<0,0,((K22-J22)*24)) -> 0 | N22: =IF(ROUNDUP(SQRT((K22*24)/5000),0)<ROUNDUP(SQRT((J22*24)/5000),0),ROUNDUP(SQRT((J22*24)/5000),0),ROUNDUP(SQRT((K22*24)/5000),0)) -> 6
I23: =Calc!C20 -> Medical technology | J23: =Calc!D20 -> 11600 | K23: =Calc!M20 -> 0 | L23: =IFERROR(K23/J23,0) -> 0 | M23: =IF(((K23-J23)*24)<0,0,((K23-J23)*24)) -> 0 | N23: =IF(ROUNDUP(SQRT((K23*24)/5000),0)<ROUNDUP(SQRT((J23*24)/5000),0),ROUNDUP(SQRT((J23*24)/5000),0),ROUNDUP(SQRT((K23*24)/5000),0)) -> 8
I24: =Calc!C21 -> Silver | J24: =Calc!D21 -> 36000 | K24: =Calc!M21 -> 3400 | L24: =IFERROR(K24/J24,0) -> 0.094444444 | M24: =IF(((K24-J24)*24)<0,0,((K24-J24)*24)) -> 0 | N24: =IF(ROUNDUP(SQRT((K24*24)/5000),0)<ROUNDUP(SQRT((J24*24)/5000),0),ROUNDUP(SQRT((J24*24)/5000),0),ROUNDUP(SQRT((K24*24)/5000),0)) -> 14
I25: =Calc!C22 -> Gold | J25: =Calc!D22 -> 5040 | K25: =Calc!M22 -> 2400 | L25: =IFERROR(K25/J25,0) -> 0.47619048 | M25: =IF(((K25-J25)*24)<0,0,((K25-J25)*24)) -> 0 | N25: =IF(ROUNDUP(SQRT((K25*24)/5000),0)<ROUNDUP(SQRT((J25*24)/5000),0),ROUNDUP(SQRT((J25*24)/5000),0),ROUNDUP(SQRT((K25*24)/5000),0)) -> 5
I26: =Calc!C23 -> Jewellery | J26: =Calc!D23 -> 4800 | K26: =Calc!M23 -> 0 | L26: =IFERROR(K26/J26,0) -> 0 | M26: =IF(((K26-J26)*24)<0,0,((K26-J26)*24)) -> 0 | N26: =IF(ROUNDUP(SQRT((K26*24)/5000),0)<ROUNDUP(SQRT((J26*24)/5000),0),ROUNDUP(SQRT((J26*24)/5000),0),ROUNDUP(SQRT((K26*24)/5000),0)) -> 5
I27: =Calc!C24 -> Scan drones | J27: =Calc!D24 -> 0 | K27: =Calc!M24 -> 0 | L27: =IFERROR(K27/J27,0) -> 0 | M27: =IF(((K27-J27)*24)<0,0,((K27-J27)*24)) -> 0 | N27: =IF(ROUNDUP(SQRT((K27*24)/5000),0)<ROUNDUP(SQRT((J27*24)/5000),0),ROUNDUP(SQRT((J27*24)/5000),0),ROUNDUP(SQRT((K27*24)/5000),0)) -> 0
I28: Trucks | J28: =Calc!D25 -> 1000 | K28: =Calc!M25 -> 0 | L28: =IFERROR(K28/J28,0) -> 0 | M28: =IF(((K28-J28)*24)<0,0,((K28-J28)*24)) -> 0 | N28: =IF(ROUNDUP(SQRT((K28*24)/5000),0)<ROUNDUP(SQRT((J28*24)/5000),0),ROUNDUP(SQRT((J28*24)/5000),0),ROUNDUP(SQRT((K28*24)/5000),0)) -> 3
B30: Profit centers
B32: Value at hand | C32: Adj Value/hr | D32: Value/hr | E32: Individ VL | I32: Product | J32: Adj Value/hr | K32: Value/hr | L32: Individ VL | M32: Profit Ratio | N32: Actual Profit | P32: Profit/hr
B33: Clay | C33: =VLOOKUP($B33,Markets!$F$4:$J$61,5,FALSE)*(C7-D7) -> -136974432 | D33: =VLOOKUP($B33,TblMarket,5,FALSE)*C7 -> 12545568 | E33: =IF(VLOOKUP($B33,Markets!$F$4:$H$61,3,FALSE)=0,VLOOKUP($B33,Markets!$F$4:$H$61,2,FALSE), VLOOKUP($B33,Markets!$F$4:$H$61,3,FALSE)) -> 350 | I33: Bricks | J33: =VLOOKUP($I33,TblMarket,5,FALSE)*(J7-K7) -> #N/A | K33: =VLOOKUP($I33,TblMarket,5,FALSE)*J7 -> #N/A | L33: =VLOOKUP($I33,TblMarket,5,FALSE) -> #N/A | M33: =(L33*2)/(E33*3+10) -> #N/A | N33: =(L33)-(E33*3+10)/2 -> #N/A | P33: =Calc!D4*N33 -> #N/A
B34: Limestone | C34: =VLOOKUP($B34,TblMarket,5,FALSE)*(C8-D8) -> -64447099 | D34: =VLOOKUP($B34,TblMarket,5,FALSE)*C8 -> 1887621.1 | E34: =IF(VLOOKUP($B34,Markets!$F$4:$H$61,3,FALSE)=0,VLOOKUP($B34,Markets!$F$4:$H$61,2,FALSE), VLOOKUP($B34,Markets!$F$4:$H$61,3,FALSE)) -> 512 | I34: Concrete | J34: =VLOOKUP($I34,TblMarket,5,FALSE)*(J8-K8) -> 1695657600 | K34: =VLOOKUP($I34,TblMarket,5,FALSE)*J8 -> 1695657600 | L34: =VLOOKUP($I34,TblMarket,5,FALSE) -> 5176 | M34: =(L34*14)/(E34*2+E35*3+20) -> 29.172303 | N34: =(L34)-(E34*2+E35*3+20)/14 -> 4998.5714 | P34: =Calc!D5*N34 -> 1637532000
B35: Gravel | C35: =VLOOKUP($B35,TblMarket,5,FALSE)*(C9-D9) -> -33696000 | D35: =VLOOKUP($B35,TblMarket,5,FALSE)*C9 -> 0 | E35: =IF(VLOOKUP($B35,Markets!$F$4:$H$61,3,FALSE)=0,VLOOKUP($B35,Markets!$F$4:$H$61,2,FALSE), VLOOKUP($B35,Markets!$F$4:$H$61,3,FALSE)) -> 480 | I35: Fertilizer | J35: =VLOOKUP($I35,TblMarket,5,FALSE)*(J9-K9) -> 168122240 | K35: =VLOOKUP($I35,TblMarket,5,FALSE)*J9 -> 168122240 | L35: =VLOOKUP($I35,TblMarket,5,FALSE) -> 2171 | M35: =(L35*11)/(E34*8+90) -> 5.7049689 | N35: =(L35)-(E34*8+90)/11 -> 1790.4545 | P35: =Calc!D6*N35 -> 138652800
B36: Coal | C36: =VLOOKUP($B36,TblMarket,5,FALSE)*(C10-D10) -> -54301606 | D36: =VLOOKUP($B36,TblMarket,5,FALSE)*C10 -> 6.5647339e+08 | E36: =IF(VLOOKUP($B36,Markets!$F$4:$H$61,3,FALSE)=0,VLOOKUP($B36,Markets!$F$4:$H$61,2,FALSE), VLOOKUP($B36,Markets!$F$4:$H$61,3,FALSE)) -> 2416 | I36: Steel | J36: =VLOOKUP($I36,TblMarket,5,FALSE)*(J10-K10) -> 1341753000 | K36: =VLOOKUP($I36,TblMarket,5,FALSE)*J10 -> 1445535000 | L36: =VLOOKUP($I36,TblMarket,5,FALSE) -> 49420 | M36: =L36/(E36*10+E37*7+350) -> 1.447484 | N36: =L36-(E36*10+E37*7+350) -> 15278 | P36: =Calc!D7*N36 -> 446881500
B37: Iron Ore | C37: =VLOOKUP($B37,TblMarket,5,FALSE)*(C11-D11) -> -99692548 | D37: =VLOOKUP($B37,TblMarket,5,FALSE)*C11 -> 1.8204345e+08 | E37: =IF(VLOOKUP($B37,Markets!$F$4:$H$61,3,FALSE)=0,VLOOKUP($B37,Markets!$F$4:$H$61,2,FALSE), VLOOKUP($B37,Markets!$F$4:$H$61,3,FALSE)) -> 1376 | I37: Fossil fuel | J37: =VLOOKUP($I37,TblMarket,5,FALSE)*(J11-K11) -> 329041920 | K37: =VLOOKUP($I37,TblMarket,5,FALSE)*J11 -> 1295602560 | L37: =VLOOKUP($I37,TblMarket,5,FALSE) -> 32133 | M37: =(L37*4)/(E38*4+150) -> 12.285605 | N37: =(L37)-(E38*4+150)/4 -> 29517.5 | P37: =Calc!D8*N37 -> 1190145600
B38: Crude Oil | C38: =VLOOKUP($B38,TblMarket,5,FALSE)*(C12-D12) -> -1.0497729e+08 | D38: =VLOOKUP($B38,TblMarket,5,FALSE)*C12 -> 17993306 | E38: =IF(VLOOKUP($B38,Markets!$F$4:$H$61,3,FALSE)=0,VLOOKUP($B38,Markets!$F$4:$H$61,2,FALSE), VLOOKUP($B38,Markets!$F$4:$H$61,3,FALSE)) -> 2578 | I38: Glass | J38: =VLOOKUP($I38,TblMarket,5,FALSE)*(J12-K12) -> 1510286720 | K38: =VLOOKUP($I38,TblMarket,5,FALSE)*J12 -> 1510286720 | L38: =VLOOKUP($I38,TblMarket,5,FALSE) -> 50209 | M38: =(L38*8)/(E39*6+L37*8+E34*4+3000) -> 1.5200224 | N38: =(L38)-(E39*6+L37*8+E34*4+3000)/8 -> 17177.25 | P38: =Calc!D9*N38 -> 516691680
B39: Quartz Sand | C39: =VLOOKUP($B39,TblMarket,5,FALSE)*(C13-D13) -> -8053920 | D39: =VLOOKUP($B39,TblMarket,5,FALSE)*C13 -> 0 | E39: =IF(VLOOKUP($B39,Markets!$F$4:$H$61,3,FALSE)=0,VLOOKUP($B39,Markets!$F$4:$H$61,2,FALSE), VLOOKUP($B39,Markets!$F$4:$H$61,3,FALSE)) -> 357 | I39: Copper | J39: =VLOOKUP($I39,TblMarket,5,FALSE)*(J13-K13) -> 92575100 | K39: =VLOOKUP($I39,TblMarket,5,FALSE)*J13 -> 990378900 | L39: =VLOOKUP($I39,TblMarket,5,FALSE) -> 87335 | M39: =(L39*3)/(E40*9+2500) -> 17.807721 | N39: =(L39)-(E40*9+2500)/3 -> 82430.667 | P39: =Calc!D10*N39 -> 934763760
B40: Chalcopyrite | C40: =VLOOKUP($B40,TblMarket,5,FALSE)*(C14-D14) -> -46165140 | D40: =VLOOKUP($B40,TblMarket,5,FALSE)*C14 -> 0 | E40: =IF(VLOOKUP($B40,Markets!$F$4:$H$61,3,FALSE)=0,VLOOKUP($B40,Markets!$F$4:$H$61,2,FALSE), VLOOKUP($B40,Markets!$F$4:$H$61,3,FALSE)) -> 1357 | I40: Insecticides | J40: =VLOOKUP($I40,TblMarket,5,FALSE)*(J14-K14) -> 580146000 | K40: =VLOOKUP($I40,TblMarket,5,FALSE)*J14 -> 580146000 | L40: =VLOOKUP($I40,TblMarket,5,FALSE) -> 4362 | M40: =(L40*35)/(E34*3+L39+2400) -> 1.6727109 | N40: =(L40)-(E34*3+L39+2400)/35 -> 1754.2571 | P40: =Calc!D11*N40 -> 233316200
B41: Bauxite | C41: =VLOOKUP($B41,TblMarket,5,FALSE)*(C15-D15) -> -1.662966e+08 | D41: =VLOOKUP($B41,TblMarket,5,FALSE)*C15 -> 14847722 | E41: =IF(VLOOKUP($B41,Markets!$F$4:$H$61,3,FALSE)=0,VLOOKUP($B41,Markets!$F$4:$H$61,2,FALSE), VLOOKUP($B41,Markets!$F$4:$H$61,3,FALSE)) -> 2050 | I41: Aluminium | J41: =VLOOKUP($I41,TblMarket,5,FALSE)*(J15-K15) -> 426101260 | K41: =VLOOKUP($I41,TblMarket,5,FALSE)*J15 -> 1419052160 | L41: =VLOOKUP($I41,TblMarket,5,FALSE) -> 96403 | M41: =(L41*4)/(E41*24+5000) -> 7.1146125 | N41: =(L41)-(E41*24+5000)/4 -> 82853 | P41: =Calc!D12*N41 -> 1219596160
B42: Lithium Ore | C42: =VLOOKUP($B42,TblMarket,5,FALSE)*(C16-D16) -> 1253440600 | D42: =VLOOKUP($B42,TblMarket,5,FALSE)*C16 -> 1555867600 | E42: =IF(VLOOKUP($B42,Markets!$F$4:$H$61,3,FALSE)=0,VLOOKUP($B42,Markets!$F$4:$H$61,2,FALSE), VLOOKUP($B42,Markets!$F$4:$H$61,3,FALSE)) -> 487 | I42: Plastics | J42: =VLOOKUP($I42,TblMarket,5,FALSE)*(J16-K16) -> 105836080 | K42: =VLOOKUP($I42,TblMarket,5,FALSE)*J16 -> 354387600 | L42: =VLOOKUP($I42,TblMarket,5,FALSE) -> 4802 | M42: =(L42*10)/(E38+400) -> 16.124916 | N42: =(L42)-(E38+400)/10 -> 4504.2 | P42: =Calc!D13*N42 -> 332409960
B43: Ilmenite | C43: =VLOOKUP($B43,TblMarket,5,FALSE)*(C17-D17) -> -4032000 | D43: =VLOOKUP($B43,TblMarket,5,FALSE)*C17 -> 0 | E43: =IF(VLOOKUP($B43,Markets!$F$4:$H$61,3,FALSE)=0,VLOOKUP($B43,Markets!$F$4:$H$61,2,FALSE), VLOOKUP($B43,Markets!$F$4:$H$61,3,FALSE)) -> 300 | I43: Lithium | J43: =VLOOKUP($I43,TblMarket,5,FALSE)*(J17-K17) -> 201234000 | K43: =VLOOKUP($I43,TblMarket,5,FALSE)*J17 -> 823230000 | L43: =VLOOKUP($I43,TblMarket,5,FALSE) -> 30490 | M43: =(L43*5)/(E42*115+5000) -> 2.4989755 | N43: =(L43)-(E42*115+5000)/5 -> 18289 | P43: =Calc!D14*N43 -> 493803000
B44: Silver Ore | C44: =VLOOKUP($B44,TblMarket,5,FALSE)*(C18-D18) -> 40853904 | D44: =VLOOKUP($B44,TblMarket,5,FALSE)*C18 -> 49557264 | E44: =IF(VLOOKUP($B44,Markets!$F$4:$H$61,3,FALSE)=0,VLOOKUP($B44,Markets!$F$4:$H$61,2,FALSE), VLOOKUP($B44,Markets!$F$4:$H$61,3,FALSE)) -> 1511 | I44: Batteries | J44: =VLOOKUP($I44,TblMarket,5,FALSE)*(J18-K18) -> 1983292800 | K44: =VLOOKUP($I44,TblMarket,5,FALSE)*J18 -> 2107248600 | L44: =VLOOKUP($I44,TblMarket,5,FALSE) -> 206593 | M44: =(L44*10)/(L43*20+L42*40+L41*10+75000) -> 1.122233 | N44: =L44-(L43*20+L42*40+L41*10+75000)/10 -> 22502 | P44: =Calc!D15*N44 -> 229520400
B45: Gold Ore | C45: =VLOOKUP($B45,TblMarket,5,FALSE)*(C19-D19) -> 3.0554747e+08 | D45: =VLOOKUP($B45,TblMarket,5,FALSE)*C19 -> 3.3753467e+08 | E45: =IF(VLOOKUP($B45,Markets!$F$4:$H$61,3,FALSE)=0,VLOOKUP($B45,Markets!$F$4:$H$61,2,FALSE), VLOOKUP($B45,Markets!$F$4:$H$61,3,FALSE)) -> 952 | I45: Weapons | J45: =VLOOKUP($I45,TblMarket,5,FALSE)*(J19-K19) -> #N/A | K45: =VLOOKUP($I45,TblMarket,5,FALSE)*J19 -> #N/A | L45: =VLOOKUP($I45,TblMarket,5,FALSE) -> #N/A | M45: =(L45*25)/(L36+L41+L44+250000) -> #N/A | N45: =(L45)-(L36+L41+L44+250000)/25 -> #N/A | P45: =Calc!D16*N45 -> #N/A
B46: Rough Diamonds | C46: =VLOOKUP($B46,TblMarket,5,FALSE)*(C20-D20) -> 9496771200 | D46: =VLOOKUP($B46,TblMarket,5,FALSE)*C20 -> 17711971200 | E46: =IF(VLOOKUP($B46,Markets!$F$4:$H$61,3,FALSE)=0,VLOOKUP($B46,Markets!$F$4:$H$61,2,FALSE), VLOOKUP($B46,Markets!$F$4:$H$61,3,FALSE)) -> 3423 | I46: Silicon | J46: =VLOOKUP($I46,TblMarket,5,FALSE)*(J20-K20) -> -261267120 | K46: =VLOOKUP($I46,TblMarket,5,FALSE)*J20 -> 0 | L46: =VLOOKUP($I46,TblMarket,5,FALSE) -> 120957 | M46: =(L46*2)/(E39*20+E33+L37*5+49500) -> 1.1114562 | N46: =(L46)-(E39*20+E33+L37*5+49500)/2 -> 12129.5 | P46: =Calc!D17*N46 -> 0
B47: Total | C47: Adj Value/hr (+TC) | D47: Value/hr | E47: Value/day | I47: Electronics | J47: =VLOOKUP($I47,TblMarket,5,FALSE)*(J21-K21) -> 951725280 | K47: =VLOOKUP($I47,TblMarket,5,FALSE)*J21 -> 1099319040 | L47: =VLOOKUP($I47,TblMarket,5,FALSE) -> 63618 | M47: =(L47*8)/(L42*4+L39*3+L46+5000) -> 1.2499546 | N47: =(L47)-(L42*4+L39*3+L46+5000)/8 -> 12721.75 | P47: =Calc!D18*N47 -> 219831840
B48: All Mines | C48: =SUM(C33:C46)+C77 -> 1.0342045e+10 | D48: =SUM(D33:D46)+C77 -> 2.050479e+10 | E48: =D48*24 -> 4.9211496e+11 | I48: Titanium | J48: =VLOOKUP($I48,TblMarket,5,FALSE)*(J22-K22) -> 75838880 | K48: =VLOOKUP($I48,TblMarket,5,FALSE)*J22 -> 245017920 | L48: =VLOOKUP($I48,TblMarket,5,FALSE) -> 36461 | M48: =(L48*4)/(E43*8+10000) -> 11.761613 | N48: =(L48)-(E43*8+10000)/4 -> 33361 | P48: =Calc!D19*N48 -> 224185920
I49: Medical technology | J49: =VLOOKUP($I49,TblMarket,5,FALSE)*(J23-K23) -> 2078975200 | K49: =VLOOKUP($I49,TblMarket,5,FALSE)*J23 -> 2078975200 | L49: =VLOOKUP($I49,TblMarket,5,FALSE) -> 179222 | M49: =(L49*10)/(L48*4+L42*2+L47*2+90000) -> 4.8089534 | N49: =(L49)-(L48*4+L42*2+L47*2+90000)/10 -> 141953.6 | P49: =Calc!D20*N49 -> 1646661760
I50: Silver | J50: =VLOOKUP($I50,TblMarket,5,FALSE)*(J24-K24) -> 53007600 | K50: =VLOOKUP($I50,TblMarket,5,FALSE)*J24 -> 58536000 | L50: =VLOOKUP($I50,TblMarket,5,FALSE) -> 1626 | M50: =(L50*50)/(E44*8+10000) -> 3.6807316 | N50: =(L50)-(E44*8+10000)/50 -> 1184.24 | P50: =Calc!D21*N50 -> 42632640
I51: Gold | J51: =VLOOKUP($I51,TblMarket,5,FALSE)*(J25-K25) -> 164857440 | K51: =VLOOKUP($I51,TblMarket,5,FALSE)*J25 -> 314727840 | L51: =VLOOKUP($I51,TblMarket,5,FALSE) -> 62446 | M51: =(L51*3)/(E45*20+20000) -> 4.7986168 | N51: =(L51)-(E45*20+20000)/3 -> 49432.667 | P51: =Calc!D22*N51 -> 249140640
I52: Jewellery | J52: =VLOOKUP($I52,TblMarket,5,FALSE)*(J26-K26) -> 9954864000 | K52: =VLOOKUP($I52,TblMarket,5,FALSE)*J26 -> 9954864000 | L52: =VLOOKUP($I52,TblMarket,5,FALSE) -> 2073930 | M52: =(L52*2)/(E46*1000+L51+L50+50000) -> 1.1726818 | N52: =(L52)-(E46*1000+L51+L50+50000)/2 -> 305394 | P52: =Calc!D23*N52 -> 1465891200
I53: Scan drones | J53: =VLOOKUP($I53,TblMarket,5,FALSE)*(J27-K27) -> 0 | K53: =VLOOKUP($I53,TblMarket,5,FALSE)*J27 -> 0 | L53: =VLOOKUP($I53,TblMarket,5,FALSE) -> 96557042 | M53: =L53/(L47*25+L48*50+L44*250+25000000) -> 1.2060321 | N53: =L53-(L47*25+L48*50+L44*250+25000000) -> 16495292 | P53: =Calc!D24*N53 -> 0
I54: Trucks | J54: =VLOOKUP($I54,TblMarket,5,FALSE)*(J28-K28) -> 299273000 | K54: =VLOOKUP($I54,TblMarket,5,FALSE)*J28 -> 299273000 | L54: =VLOOKUP($I54,TblMarket,5,FALSE) -> 299273 | M54: =(L54*50)/(L36*100+L44*25+L50*50+2500000) -> 1.1793429 | N54: =L54-(L36*100+L44*25+L50*50+2500000)/50 -> 45510.5 | P54: =Calc!D25*N54 -> 45510500
I55: Total | J55: Adj Value/hr | K55: Value/hr | L55: Average VL | M55: Adj Value/day
I56: All Factories | J56: =SUM(P33:P54)+J85 -> #N/A | K56: =SUM(K33:K54) -> #N/A | L56: =AVERAGE(L33:L54) -> #N/A | M56: =J56*24 -> #N/A
I57: Total All | J57: =J56+C48 -> #N/A | M57: =(M56+E48) -> #N/A
B59: Transport costs
B61: Value at hand | C61: Transport cost/hr | I61: Product | J61: Adj Value/hr
B62: Clay | C62: =IF(C33<0,C33*(0.15-(UserBuildings!T$16*0.01)),0) -> -6848721.6 | I62: Bricks | J62: =IF(J33<0,J33*(0.15-(UserBuildings!T$16*0.01)),0) -> #N/A
B63: Limestone | C63: =IF(C34<0,C34*(0.15-(UserBuildings!T$16*0.01)),0) -> -3222354.9 | I63: Concrete | J63: =IF(J34<0,J34*(0.15-(UserBuildings!T$16*0.01)),0) -> 0
B64: Gravel | C64: =IF(C35<0,C35*(0.15-(UserBuildings!T$16*0.01)),0) -> -1684800 | I64: Fertilizer | J64: =IF(J35<0,J35*(0.15-(UserBuildings!T$16*0.01)),0) -> 0
B65: Coal | C65: =IF(C36<0,C36*(0.15-(UserBuildings!T$16*0.01)),0) -> -2715080.3 | I65: Steel | J65: =IF(J36<0,J36*(0.15-(UserBuildings!T$16*0.01)),0) -> 0
B66: Iron Ore | C66: =IF(C37<0,C37*(0.15-(UserBuildings!T$16*0.01)),0) -> -4984627.4 | I66: Fossil fuel | J66: =IF(J37<0,J37*(0.15-(UserBuildings!T$16*0.01)),0) -> 0
B67: Crude Oil | C67: =IF(C38<0,C38*(0.15-(UserBuildings!T$16*0.01)),0) -> -5248864.7 | I67: Glass | J67: =IF(J38<0,J38*(0.15-(UserBuildings!T$16*0.01)),0) -> 0
B68: Quartz Sand | C68: =IF(C39<0,C39*(0.15-(UserBuildings!T$16*0.01)),0) -> -402696 | I68: Copper | J68: =IF(J39<0,J39*(0.15-(UserBuildings!T$16*0.01)),0) -> 0
B69: Chalcopyrite | C69: =IF(C40<0,C40*(0.15-(UserBuildings!T$16*0.01)),0) -> -2308257 | I69: Insecticides | J69: =IF(J40<0,J40*(0.15-(UserBuildings!T$16*0.01)),0) -> 0
B70: Bauxite | C70: =IF(C41<0,C41*(0.15-(UserBuildings!T$16*0.01)),0) -> -8314829.9 | I70: Aluminium | J70: =IF(J41<0,J41*(0.15-(UserBuildings!T$16*0.01)),0) -> 0
B71: Lithium Ore | C71: =IF(C42<0,C42*(0.15-(UserBuildings!T$16*0.01)),0) -> 0 | I71: Plastics | J71: =IF(J42<0,J42*(0.15-(UserBuildings!T$16*0.01)),0) -> 0
B72: Ilmenite | C72: =IF(C43<0,C43*(0.15-(UserBuildings!T$16*0.01)),0) -> -201600 | I72: Lithium | J72: =IF(J43<0,J43*(0.15-(UserBuildings!T$16*0.01)),0) -> 0
B73: Silver Ore | C73: =IF(C44<0,C44*(0.15-(UserBuildings!T$16*0.01)),0) -> 0 | I73: Batteries | J73: =IF(J44<0,J44*(0.15-(UserBuildings!T$16*0.01)),0) -> 0
... B75: Rough Diamonds | C75: =IF(C46<0,C46*(0.15-(UserBuildings!T$16*0.01)),0) -> 0 | I75: Silicon | J75: =IF(J46<0,J46*(0.15-(UserBuildings!T$16*0.01)),0) -> -13063356
B76: Total | C76: Adj Value/hr | I76: Electronics | J76: =IF(J47<0,J47*(0.15-(UserBuildings!T$16*0.01)),0) -> 0
B77: All Mines | C77: =SUM(C62:C75) -> -35931832 | I77: Titanium | J77: =IF(J48<0,J48*(0.15-(UserBuildings!T$16*0.01)),0) -> 0
I78: Medical technology | J78: =IF(J49<0,J49*(0.15-(UserBuildings!T$16*0.01)),0) -> 0
I79: Silver | J79: =IF(J50<0,J50*(0.15-(UserBuildings!T$16*0.01)),0) -> 0
I80: Gold | J80: =IF(J51<0,J51*(0.15-(UserBuildings!T$16*0.01)),0) -> 0
I81: Jewellery | J81: =IF(J52<0,J52*(0.15-(UserBuildings!T$16*0.01)),0) -> 0
I82: Scan drones | J82: =IF(J53<0,J53*(0.15-(UserBuildings!T$16*0.01)),0) -> 0
I83: Trucks | J83: =IF(J54<0,J54*(0.15-(UserBuildings!T$16*0.01)),0) -> 0
I84: Total | J84: Adj Value/hr
I85: All Factories | J85: =SUM(J62:J83) -> #N/A

Sheet UserBuildings
B1: Fill the blue highlighted areas with your current stats. | Y1: Warehouse level is optional. To leave this out of calculations, put it all to zero.
B2: API Toggle: | C2: 0 | D2: API Credits Left: | E2: ='API Raw'!B11 -> 0 | F2: API Key: | G2: d2f7070074a24ff4c55a55a0c0ab3faa699c437a4d87b
B3: Mines | C3: fill from mine overview | K3: Factories | R3: Buildings | W3: HQ | Y3: Warehouse
B4: Resource | C4: Mine name | D4: Number: | E4: Manual | F4: API | G4: Average Produce | H4: Max Production | I4: Max from API | K4: Name | L4: Use Lvl | M4: Actual Lvl | N4: Manual Lvl | O4: API Lvl | P4: Using? | R4: Name | S4: Lvl | T4: Manual Lvl | U4: API Lvl | W4: Level | Y4: Resource | Z4: Level | AA4: Manual Lvl | AB4: API Lvl
B5: Clay | C5: Clay pit | D5: =IF(F5=0,E5,F5) -> 25 | E5: 25 | F5: =IFERROR(VLOOKUP(C5,TblAPIMines,2,FALSE),0) -> 0 | G5: =IF(I5=0,H5*$G$20/100,I5*$G$20/100) -> 35844.48 | H5: 36576 | I5: =IFERROR(VLOOKUP(C5,TblAPIMines,5,FALSE),0) -> 0 | K5: Brick factory | L5: =IF(P5="NO",0,M5) -> 356 | M5: =IF(O5=0,N5,O5) -> 356 | N5: 356 | O5: =IFERROR(VLOOKUP(K5,TblAPIFactory,2,FALSE),0) -> 0 | P5: Yes | R5: Tech center | S5: =IF(U5=0,T5,U5) -> 10 | T5: 10 | U5: =IFERROR(VLOOKUP(R5,TblAPISpecial,2,FALSE),0) -> 0 | W5: =IF(W7=0,W6,W7) -> 9 | Y5: Bauxite | Z5: =IF(AB5=0,AA5,AB5) -> 32 | AA5: 32 | AB5: =IFERROR(VLOOKUP(Y5,TblAPIWarehouse,2,FALSE),0) -> 0
B6: Coal | C6: Coal mine | D6: =IF(F6=0,E6,F6) -> 143 | E6: 143 | F6: =IFERROR(VLOOKUP(C6,TblAPIMines,2,FALSE),0) -> 0 | G6: =IF(I6=0,H6*$G$20/100,I6*$G$20/100) -> 270153.66 | H6: 275667 | I6: =IFERROR(VLOOKUP(C6,TblAPIMines,5,FALSE),0) -> 0 | K6: Concrete factory | L6: =IF(P6="NO",0,M6) -> 156 | M6: =IF(O6=0,N6,O6) -> 156 | N6: 156 | O6: =IFERROR(VLOOKUP(K6,TblAPIFactory,2,FALSE),0) -> 0 | P6: Yes | R6: Casino | S6: =IF(U6=0,T6,U6) -> 10 | T6: 10 | U6: =IFERROR(VLOOKUP(R6,TblAPISpecial,2,FALSE),0) -> 0 | W6: 9 | Y6: Chalcopyrite | Z6: =IF(AB6=0,AA6,AB6) -> 23 | AA6: 23 | AB6: =IFERROR(VLOOKUP(Y6,TblAPIWarehouse,2,FALSE),0) -> 0
B7: Chalcopyrite | C7: Copper mine | D7: =IF(F7=0,E7,F7) -> 0 | E7: 0 | F7: =IFERROR(VLOOKUP(C7,TblAPIMines,2,FALSE),0) -> 0 | G7: =IF(I7=0,H7*$G$20/100,I7*$G$20/100) -> 0 | H7: 0 | I7: =IFERROR(VLOOKUP(C7,TblAPIMines,5,FALSE),0) -> 0 | K7: Fertilizer factory | L7: =IF(P7="NO",0,M7) -> 64 | M7: =IF(O7=0,N7,O7) -> 64 | N7: 64 | O7: =IFERROR(VLOOKUP(K7,TblAPIFactory,2,FALSE),0) -> 0 | P7: Yes | R7: Museum | S7: =IF(U7=0,T7,U7) -> 10 | T7: 10 | U7: =IFERROR(VLOOKUP(R7,TblAPISpecial,2,FALSE),0) -> 0 | W7: ='API Raw'!S11 -> 0 | Y7: Clay | Z7: =IF(AB7=0,AA7,AB7) -> 126 | AA7: 126 | AB7: =IFERROR(VLOOKUP(Y7,TblAPIWarehouse,2,FALSE),0) -> 0
B8: Rough diamonds | C8: Diamond mine | D8: =IF(F8=0,E8,F8) -> 478 | E8: 478 | F8: =IFERROR(VLOOKUP(C8,TblAPIMines,2,FALSE),0) -> 0 | G8: =IF(I8=0,H8*$G$20/100,I8*$G$20/100) -> 5174400 | H8: 5280000 | I8: =IFERROR(VLOOKUP(C8,TblAPIMines,5,FALSE),0) -> 0 | K8: Ironworks | L8: =IF(P8="NO",0,M8) -> 65 | M8: =IF(O8=0,N8,O8) -> 65 | N8: 65 | O8: =IFERROR(VLOOKUP(K8,TblAPIFactory,2,FALSE),0) -> 0 | P8: Yes | R8: Training camp | S8: =IF(U8=0,T8,U8) -> 10 | T8: 10 | U8: =IFERROR(VLOOKUP(R8,TblAPISpecial,2,FALSE),0) -> 0 | Y8: Coal | Z8: =IF(AB8=0,AA8,AB8) -> 50 | AA8: 50 | AB8: =IFERROR(VLOOKUP(Y8,TblAPIWarehouse,2,FALSE),0) -> 0
B9: Gravel | C9: Gravel pit | D9: =IF(F9=0,E9,F9) -> 0 | E9: 0 | F9: =IFERROR(VLOOKUP(C9,TblAPIMines,2,FALSE),0) -> 0 | G9: =IF(I9=0,H9*$G$20/100,I9*$G$20/100) -> 0 | H9: 0 | I9: =IFERROR(VLOOKUP(C9,TblAPIMines,5,FALSE),0) -> 0 | K9: Oil refinery | L9: =IF(P9="NO",0,M9) -> 63 | M9: =IF(O9=0,N9,O9) -> 63 | N9: 63 | O9: =IFERROR(VLOOKUP(K9,TblAPIFactory,2,FALSE),0) -> 0 | P9: Yes | R9: Recycling plant | S9: =IF(U9=0,T9,U9) -> 10 | T9: 10 | U9: =IFERROR(VLOOKUP(R9,TblAPISpecial,2,FALSE),0) -> 0 | Y9: Crude oil | Z9: =IF(AB9=0,AA9,AB9) -> 35 | AA9: 35 | AB9: =IFERROR(VLOOKUP(Y9,TblAPIWarehouse,2,FALSE),0) -> 0
B10: Ilmenite | C10: Ilmenite mine | D10: =IF(F10=0,E10,F10) -> 0 | E10: 0 | F10: =IFERROR(VLOOKUP(C10,TblAPIMines,2,FALSE),0) -> 0 | G10: =IF(I10=0,H10*$G$20/100,I10*$G$20/100) -> 0 | H10: 0 | I10: =IFERROR(VLOOKUP(C10,TblAPIMines,5,FALSE),0) -> 0 | K10: Glazier's workshop | L10: =IF(P10="NO",0,M10) -> 47 | M10: =IF(O10=0,N10,O10) -> 47 | N10: 47 | O10: =IFERROR(VLOOKUP(K10,TblAPIFactory,2,FALSE),0) -> 0 | P10: Yes | R10: Law firm | S10: =IF(U10=0,T10,U10) -> 10 | T10: 10 | U10: =IFERROR(VLOOKUP(R10,TblAPISpecial,2,FALSE),0) -> 0 | Y10: Gold ore | Z10: =IF(AB10=0,AA10,AB10) -> 52 | AA10: 52 | AB10: =IFERROR(VLOOKUP(Y10,TblAPIWarehouse,2,FALSE),0) -> 0
B11: Iron ore | C11: Iron ore mine | D11: =IF(F11=0,E11,F11) -> 141 | E11: 141 | F11: =IFERROR(VLOOKUP(C11,TblAPIMines,2,FALSE),0) -> 0 | G11: =IF(I11=0,H11*$G$20/100,I11*$G$20/100) -> 132299.02 | H11: 134999 | I11: =IFERROR(VLOOKUP(C11,TblAPIMines,5,FALSE),0) -> 0 | K11: Copper refinery | L11: =IF(P11="NO",0,M11) -> 42 | M11: =IF(O11=0,N11,O11) -> 42 | N11: 42 | O11: =IFERROR(VLOOKUP(K11,TblAPIFactory,2,FALSE),0) -> 0 | P11: Yes | R11: Mafia HQ | S11: =IF(U11=0,T11,U11) -> 10 | T11: 10 | U11: =IFERROR(VLOOKUP(R11,TblAPISpecial,2,FALSE),0) -> 0 | Y11: Gravel | Z11: =IF(AB11=0,AA11,AB11) -> 60 | AA11: 60 | AB11: =IFERROR(VLOOKUP(Y11,TblAPIWarehouse,2,FALSE),0) -> 0
B12: Lithium ore | C12: Lithium ore mine | D12: =IF(F12=0,E12,F12) -> 257 | E12: 257 | F12: =IFERROR(VLOOKUP(C12,TblAPIMines,2,FALSE),0) -> 0 | G12: =IF(I12=0,H12*$G$20/100,I12*$G$20/100) -> 3194800 | H12: 3260000 | I12: =IFERROR(VLOOKUP(C12,TblAPIMines,5,FALSE),0) -> 0 | K12: Insecticide factory | L12: =IF(P12="NO",0,M12) -> 38 | M12: =IF(O12=0,N12,O12) -> 38 | N12: 38 | O12: =IFERROR(VLOOKUP(K12,TblAPIFactory,2,FALSE),0) -> 0 | P12: Yes | R12: Hospital | S12: =IF(U12=0,T12,U12) -> 10 | T12: 10 | U12: =IFERROR(VLOOKUP(R12,TblAPISpecial,2,FALSE),0) -> 0 | Y12: Ilmenite | Z12: =IF(AB12=0,AA12,AB12) -> 37 | AA12: 37 | AB12: =IFERROR(VLOOKUP(Y12,TblAPIWarehouse,2,FALSE),0) -> 0
B13: Quartz sand | C13: Sand mine | D13: =IF(F13=0,E13,F13) -> 0 | E13: 0 | F13: =IFERROR(VLOOKUP(C13,TblAPIMines,2,FALSE),0) -> 0 | G13: =IF(I13=0,H13*$G$20/100,I13*$G$20/100) -> 0 | H13: 0 | I13: =IFERROR(VLOOKUP(C13,TblAPIMines,5,FALSE),0) -> 0 | K13: Aluminium factory | L13: =IF(P13="NO",0,M13) -> 46 | M13: =IF(O13=0,N13,O13) -> 46 | N13: 46 | O13: =IFERROR(VLOOKUP(K13,TblAPIFactory,2,FALSE),0) -> 0 | P13: Yes | R13: Drone research | S13: =IF(U13=0,T13,U13) -> 10 | T13: 10 | U13: =IFERROR(VLOOKUP(R13,TblAPISpecial,2,FALSE),0) -> 0 | Y13: Iron ore | Z13: =IF(AB13=0,AA13,AB13) -> 51 | AA13: 51 | AB13: =IFERROR(VLOOKUP(Y13,TblAPIWarehouse,2,FALSE),0) -> 0
B14: Silver ore | C14: Silver mine | D14: =IF(F14=0,E14,F14) -> 13 | E14: 13 | F14: =IFERROR(VLOOKUP(C14,TblAPIMines,2,FALSE),0) -> 0 | G14: =IF(I14=0,H14*$G$20/100,I14*$G$20/100) -> 32797.66 | H14: 33467 | I14: =IFERROR(VLOOKUP(C14,TblAPIMines,5,FALSE),0) -> 0 | K14: Plastic factory | L14: =IF(P14="NO",0,M14) -> 41 | M14: =IF(O14=0,N14,O14) -> 41 | N14: 41 | O14: =IFERROR(VLOOKUP(K14,TblAPIFactory,2,FALSE),0) -> 0 | P14: Yes | R14: Service center | S14: =IF(U14=0,T14,U14) -> 10 | T14: 10 | U14: =IFERROR(VLOOKUP(R14,TblAPISpecial,2,FALSE),0) -> 0 | Y14: Limestone | Z14: =IF(AB14=0,AA14,AB14) -> 64 | AA14: 64 | AB14: =IFERROR(VLOOKUP(Y14,TblAPIWarehouse,2,FALSE),0) -> 0
B15: Bauxite | C15: Bauxite mine | D15: =IF(F15=0,E15,F15) -> 6 | E15: 6 | F15: =IFERROR(VLOOKUP(C15,TblAPIMines,2,FALSE),0) -> 0 | G15: =IF(I15=0,H15*$G$20/100,I15*$G$20/100) -> 7239.26 | H15: 7387 | I15: =IFERROR(VLOOKUP(C15,TblAPIMines,5,FALSE),0) -> 0 | K15: Lithium refinery | L15: =IF(P15="NO",0,M15) -> 36 | M15: =IF(O15=0,N15,O15) -> 36 | N15: 36 | O15: =IFERROR(VLOOKUP(K15,TblAPIFactory,2,FALSE),0) -> 0 | P15: Yes | R15: HR Department | S15: =IF(U15=0,T15,U15) -> 10 | T15: 10 | U15: =IFERROR(VLOOKUP(R15,TblAPISpecial,2,FALSE),0) -> 0 | Y15: Lithium ore | Z15: =IF(AB15=0,AA15,AB15) -> 120 | AA15: 120 | AB15: =IFERROR(VLOOKUP(Y15,TblAPIWarehouse,2,FALSE),0) -> 0
B16: Crude oil | C16: Oil derrick | D16: =IF(F16=0,E16,F16) -> 16 | E16: 16 | F16: =IFERROR(VLOOKUP(C16,TblAPIMines,2,FALSE),0) -> 0 | G16: =IF(I16=0,H16*$G$20/100,I16*$G$20/100) -> 6979.56 | H16: 7122 | I16: =IFERROR(VLOOKUP(C16,TblAPIMines,5,FALSE),0) -> 0 | K16: Battery factory | L16: =IF(P16="NO",0,M16) -> 17 | M16: =IF(O16=0,N16,O16) -> 17 | N16: 17 | O16: =IFERROR(VLOOKUP(K16,TblAPIFactory,2,FALSE),0) -> 0 | P16: Yes | R16: Haulage firm | S16: =IF(U16=0,T16,U16) -> 10 | T16: 10 | U16: =IFERROR(VLOOKUP(R16,TblAPISpecial,2,FALSE),0) -> 0 | Y16: Quartz sand | Z16: =IF(AB16=0,AA16,AB16) -> 38 | AA16: 38 | AB16: =IFERROR(VLOOKUP(Y16,TblAPIWarehouse,2,FALSE),0) -> 0
B17: Gold ore | C17: Gold mine | D17: =IF(F17=0,E17,F17) -> 64 | E17: 64 | F17: =IFERROR(VLOOKUP(C17,TblAPIMines,2,FALSE),0) -> 0 | G17: =IF(I17=0,H17*$G$20/100,I17*$G$20/100) -> 354553.22 | H17: 361789 | I17: =IFERROR(VLOOKUP(C17,TblAPIMines,5,FALSE),0) -> 0 | K17: Arms factory | L17: =IF(P17="NO",0,M17) -> 20 | M17: =IF(O17=0,N17,O17) -> 20 | N17: 20 | O17: =IFERROR(VLOOKUP(K17,TblAPIFactory,2,FALSE),0) -> 0 | P17: Yes | R17: Fire Station | S17: =IF(U17=0,T17,U17) -> 1 | T17: 1 | U17: =IFERROR(VLOOKUP(R17,TblAPISpecial,2,FALSE),0) -> 0 | Y17: Rough diamonds | Z17: =IF(AB17=0,AA17,AB17) -> 152 | AA17: 152 | AB17: =IFERROR(VLOOKUP(Y17,TblAPIWarehouse,2,FALSE),0) -> 0
B18: Limestone | C18: Limestone quarry | D18: =IF(F18=0,E18,F18) -> 4 | E18: 4 | F18: =IFERROR(VLOOKUP(C18,TblAPIMines,2,FALSE),0) -> 0 | G18: =IF(I18=0,H18*$G$20/100,I18*$G$20/100) -> 3686.76 | H18: 3762 | I18: =IFERROR(VLOOKUP(C18,TblAPIMines,5,FALSE),0) -> 0 | K18: Silicon refinery | L18: =IF(P18="NO",0,M18) -> 0 | M18: =IF(O18=0,N18,O18) -> 5 | N18: 5 | O18: =IFERROR(VLOOKUP(K18,TblAPIFactory,2,FALSE),0) -> 0 | P18: No | R18: Seismology Centre | S18: =IF(U18=0,T18,U18) -> 2 | T18: 2 | U18: =IFERROR(VLOOKUP(R18,TblAPISpecial,2,FALSE),0) -> 0 | Y18: Silver ore | Z18: =IF(AB18=0,AA18,AB18) -> 40 | AA18: 40 | AB18: =IFERROR(VLOOKUP(Y18,TblAPIWarehouse,2,FALSE),0) -> 0
K19: Electronics factory | L19: =IF(P19="NO",0,M19) -> 36 | M19: =IF(O19=0,N19,O19) -> 36 | N19: 36 | O19: =IFERROR(VLOOKUP(K19,TblAPIFactory,2,FALSE),0) -> 0 | P19: Yes | Y19: Aluminium | Z19: =IF(AB19=0,AA19,AB19) -> 69 | AA19: 69 | AB19: =IFERROR(VLOOKUP(Y19,TblAPIWarehouse,2,FALSE),0) -> 0
B20: TOTAL | D20: =SUM(D5:D18) -> 1147 | E20: =SUM(E5:E19) -> 1147 | G20: =AVERAGE(100-1/F24*4,100) -> 98 | H20: =SUM(H5:H19) -> 9400769 | I20: =SUM(I5:I19) -> 0 | K20: Titanium refinery | L20: =IF(P20="NO",0,M20) -> 21 | M20: =IF(O20=0,N20,O20) -> 21 | N20: 21 | O20: =IFERROR(VLOOKUP(K20,TblAPIFactory,2,FALSE),0) -> 0 | P20: Yes | Y20: Batteries | Z20: =IF(AB20=0,AA20,AB20) -> 23 | AA20: 23 | AB20: =IFERROR(VLOOKUP(Y20,TblAPIWarehouse,2,FALSE),0) -> 0
K21: Medical technology Inc. | L21: =IF(P21="NO",0,M21) -> 29 | M21: =IF(O21=0,N21,O21) -> 29 | N21: 29 | O21: =IFERROR(VLOOKUP(K21,TblAPIFactory,2,FALSE),0) -> 0 | P21: Yes | Y21: Bricks | Z21: =IF(AB21=0,AA21,AB21) -> 190 | AA21: 190 | AB21: =IFERROR(VLOOKUP(Y21,TblAPIWarehouse,2,FALSE),0) -> 0
B22: Maintenance | C22: fill from mine overview | K22: Silver refinery | L22: =IF(P22="NO",0,M22) -> 12 | M22: =IF(O22=0,N22,O22) -> 12 | N22: 12 | O22: =IFERROR(VLOOKUP(K22,TblAPIFactory,2,FALSE),0) -> 0 | P22: Yes | Y22: Concrete | Z22: =IF(AB22=0,AA22,AB22) -> 156 | AA22: 156 | AB22: =IFERROR(VLOOKUP(Y22,TblAPIWarehouse,2,FALSE),0) -> 0
B23: Expert Cost | C23: MK Cost | D23: Individual | E23: Per Day times. | K23: Gold refinery | L23: =IF(P23="NO",0,M23) -> 21 | M23: =IF(O23=0,N23,O23) -> 21 | N23: 21 | O23: =IFERROR(VLOOKUP(K23,TblAPIFactory,2,FALSE),0) -> 0 | P23: Yes | Y23: Copper | Z23: =IF(AB23=0,AA23,AB23) -> 35 | AA23: 35 | AB23: =IFERROR(VLOOKUP(Y23,TblAPIWarehouse,2,FALSE),0) -> 0
B24: 7570000000 | C24: =E20*VLOOKUP("Maintenance kit",TblMarket,5,FALSE) -> #N/A | D24: =B24/3 -> 2.5233333e+09 | F24: 1 | K24: Goldsmith | L24: =IF(P24="NO",0,M24) -> 48 | M24: =IF(O24=0,N24,O24) -> 48 | N24: 48 | O24: =IFERROR(VLOOKUP(K24,TblAPIFactory,2,FALSE),0) -> 0 | P24: Yes | Y24: Electronics | Z24: =IF(AB24=0,AA24,AB24) -> 50 | AA24: 50 | AB24: =IFERROR(VLOOKUP(Y24,TblAPIWarehouse,2,FALSE),0) -> 0
B25: No | C25: No | D25: No | E25: How many times | K25: Drone shipyard | L25: =IF(P25="NO",0,M25) -> 0 | M25: =IF(O25=0,N25,O25) -> 0 | N25: 0 | O25: =IFERROR(VLOOKUP(K25,TblAPIFactory,2,FALSE),0) -> 0 | P25: Yes | Y25: Fertilizer | Z25: =IF(AB25=0,AA25,AB25) -> 36 | AA25: 36 | AB25: =IFERROR(VLOOKUP(Y25,TblAPIWarehouse,2,FALSE),0) -> 0
B26: =(IF(B25="Yes",B24,0))*$F$24 -> 0 | C26: =(IF(C25="Yes",C24,0))*$F$24 -> 0 | D26: =(IF(D25="Yes",D24,0))*$F$24 -> 0 | E26: per day. | K26: Truck plant | L26: =IF(P26="NO",0,M26) -> 10 | M26: =IF(O26=0,N26,O26) -> 10 | N26: 10 | O26: =IFERROR(VLOOKUP(K26,TblAPIFactory,2,FALSE),0) -> 0 | P26: Yes | Y26: Fossil fuel | Z26: =IF(AB26=0,AA26,AB26) -> 102 | AA26: 102 | AB26: =IFERROR(VLOOKUP(Y26,TblAPIWarehouse,2,FALSE),0) -> 0
E27: Use a fraction if less | Y27: Glass | Z27: =IF(AB27=0,AA27,AB27) -> 84 | AA27: 84 | AB27: =IFERROR(VLOOKUP(Y27,TblAPIWarehouse,2,FALSE),0) -> 0
E28: than once per day | Y28: Gold | Z28: =IF(AB28=0,AA28,AB28) -> 20 | AA28: 20 | AB28: =IFERROR(VLOOKUP(Y28,TblAPIWarehouse,2,FALSE),0) -> 0
E29: i.e. .5 for every other | Y29: Insecticides | Z29: =IF(AB29=0,AA29,AB29) -> 43 | AA29: 43 | AB29: =IFERROR(VLOOKUP(Y29,TblAPIWarehouse,2,FALSE),0) -> 0
E30: List of likely inputs | Y30: Jewellery | Z30: =IF(AB30=0,AA30,AB30) -> 28 | AA30: 28 | AB30: =IFERROR(VLOOKUP(Y30,TblAPIWarehouse,2,FALSE),0) -> 0
E31: 2 = 2x/day | Y31: Lithium | Z31: =IF(AB31=0,AA31,AB31) -> 26 | AA31: 26 | AB31: =IFERROR(VLOOKUP(Y31,TblAPIWarehouse,2,FALSE),0) -> 0
E32: 1 = 1/day | Y32: Medical technology | Z32: =IF(AB32=0,AA32,AB32) -> 17 | AA32: 17 | AB32: =IFERROR(VLOOKUP(Y32,TblAPIWarehouse,2,FALSE),0) -> 0
E33: .5 = every other day | Y33: Plastics | Z33: =IF(AB33=0,AA33,AB33) -> 59 | AA33: 59 | AB33: =IFERROR(VLOOKUP(Y33,TblAPIWarehouse,2,FALSE),0) -> 0
E34: .33 = every third d | Y34: Scan drones | Z34: =IF(AB34=0,AA34,AB34) -> 1 | AA34: 1 | AB34: =IFERROR(VLOOKUP(Y34,TblAPIWarehouse,2,FALSE),0) -> 0
E35: .25 = every fourth d | Y35: Silicon | Z35: =IF(AB35=0,AA35,AB35) -> 16 | AA35: 16 | AB35: =IFERROR(VLOOKUP(Y35,TblAPIWarehouse,2,FALSE),0) -> 0
E36: .2 = every fifth day | Y36: Silver | Z36: =IF(AB36=0,AA36,AB36) -> 201 | AA36: 201 | AB36: =IFERROR(VLOOKUP(Y36,TblAPIWarehouse,2,FALSE),0) -> 0
Y37: Steel | Z37: =IF(AB37=0,AA37,AB37) -> 64 | AA37: 64 | AB37: =IFERROR(VLOOKUP(Y37,TblAPIWarehouse,2,FALSE),0) -> 0
Y38: Titanium | Z38: =IF(AB38=0,AA38,AB38) -> 32 | AA38: 32 | AB38: =IFERROR(VLOOKUP(Y38,TblAPIWarehouse,2,FALSE),0) -> 0
Y39: Trucks | Z39: =IF(AB39=0,AA39,AB39) -> 30 | AA39: 30 | AB39: =IFERROR(VLOOKUP(Y39,TblAPIWarehouse,2,FALSE),0) -> 0
Y40: Weapons | Z40: =IF(AB40=0,AA40,AB40) -> 15 | AA40: 15 | AB40: =IFERROR(VLOOKUP(Y40,TblAPIWarehouse,2,FALSE),0) -> 0

Sheet API INPUTS
A1: factoryID | B1: name | C1: lvl | D1: strike | F1: itemID | G1: itemname | H1: level | I1: amount | K1: specbID | L1: name | M1: lvl | O1: itemID | P1: itemname | Q1: iconURL | S1: questID | T1: title | U1: descr | V1: status | W1: progress | X1: missiongoal | Y1: durHours | Z1: rewarditem | AA1: rewardamount | AB1: penalty | AC1: cooldown | AD1: starttime | AE1: endtime | AF1: intervalDays | AG1: thumb | AI1: itemID | AJ1: itemName | AK1: factoryID | AL1: factoryName | AM1: baseOutputPerHour | AN1: outputPerCycle | AO1: creditsPerCycle | AP1: itemID1 | AQ1: item1QtyPerCycle | AR1: itemID2 | AS1: item2QtyPerCycle | AT1: itemID3 | AU1: item3QtyPerCycle | AW1: mineID | AX1: lat | AY1: lon | AZ1: HQboost | BA1: fullrate | BB1: rawrate | BC1: techfactor | BD1: name | BE1: builddate | BF1: lastmaintenance | BG1: condition | BH1: resourceName | BI1: resourceID | BJ1: lastenemyaction | BK1: def1 | BL1: def2 | BM1: def3 | BN1: attackpenalty | BO1: attackcount | BP1: attacklost | BQ1: quality | BR1: qualityInclTU | BT1: itemID | BU1: itemName | BV1: KIprice | BW1: price | BX1: unixts
A2: 6 | B2: Concrete Factory | C2: 14 | D2: no | F2: 1 | G2: credits | H2: 1 | I2: 90268970344 | K2: 65 | L2: Museum | M2: 2 | O2: 1 | P2: credits | Q2: https://api.resources-game.ch/resimg/res1.png | S2: 9 | T2: Bob The Builder | U2: Build {} mines | V2: 0 | W2: 0 | X2: 470 | Y2: 96 | Z2: 48 | AA2: 10 | AB2: 39968000000 | AC2: 0 | AD2: 0 | AE2: 0 | AF2: 7 | AG2: https://appweb.resources-game.ch/webcontent/img/questimg/schauwieschoenichbau.jpg | AI2: 7 | AJ2: Concrete | AK2: 6 | AL2: Concrete Factory | AM2: 2100 | AN2: 14 | AO2: 20 | AP2: 3 | AQ2: 3 | AR2: 20 | AS2: 2 | AW2: 4 | AX2: 48.243971 | AY2: 16.380043 | AZ2: 1 | BA2: 1122 | BB2: 1122 | BC2: 1 | BD2: Clay Pit | BE2: 1771686087 | BF2: 1772135664 | BG2: 0.971543 | BH2: Clay | BI2: 2 | BJ2: 1771686087 | BK2: 200 | BL2: 5 | BM2: 2 | BN2: 1 | BO2: 0 | BP2: 0 | BQ2: 0.7333 | BR2: 0.7333 | BT2: 2 | BU2: Clay | BV2: 350 | BW2: 354 | BX2: 1772203036
A3: 23 | B3: Fertilizer Factory | C3: 6 | D3: no | F3: 2 | G3: Clay | H3: 30 | I3: 64622 | K3: 97 | L3: Training Camp | M3: 2 | O3: 2 | P3: Clay | Q3: https://api.resources-game.ch/resimg/res2.png | S3: 11 | T3: Need clay! | U3: Sell {}m3 clay | V3: 0 | W3: 0 | X3: 1097300 | Y3: 24 | Z3: 44 | AA3: 40 | AB3: 31085000000 | AC3: 159719 | AD3: 0 | AE3: 0 | AF3: 2 | AG3: https://appweb.resources-game.ch/webcontent/img/questimg/lehmbedarf.jpg | AI3: 22 | AJ3: Fertilizer | AK3: 23 | AL3: Fertilizer Factory | AM3: 1210 | AN3: 11 | AO3: 90 | AP3: 20 | AQ3: 8 | AW3: 4 | AX3: 48.243914 | AY3: 16.380455 | AZ3: 1 | BA3: 966 | BB3: 966 | BC3: 1 | BD3: Clay Pit | BE3: 1771686096 | BF3: 1772135664 | BG3: 0.971543 | BH3: Clay | BI3: 2 | BJ3: 1771686096 | BK3: 200 | BL3: 5 | BM3: 2 | BN3: 1 | BO3: 0 | BP3: 0 | BQ3: 0.6314 | BR3: 0.6314 | BT3: 3 | BU3: Gravel | BV3: 474 | BW3: 478 | BX3: 1772203036
A4: 25 | B4: Brick Factory | C4: 47 | D4: no | F4: 3 | G4: Gravel | H4: 10 | I4: 317038 | K4: 62 | L4: Casino | M4: 3 | O4: 3 | P4: Gravel | Q4: https://api.resources-game.ch/resimg/res3.png | S4: 12 | T4: Collectoritis | U4: Collect {} crates | V4: 0 | W4: 0 | X4: 420 | Y4: 144 | Z4: 46 | AA4: 30 | AB4: 65376000000 | AC4: 0 | AD4: 0 | AE4: 0 | AF4: 6 | AG4: https://appweb.resources-game.ch/webcontent/img/questimg/altersammler.jpg | AI4: 24 | AJ4: Bricks | AK4: 25 | AL4: Brick Factory | AM4: 800 | AN4: 2 | AO4: 10 | AP4: 2 | AQ4: 3 | AW4: 4 | AX4: 48.234626 | AY4: 16.383156 | AZ4: 1 | BA4: 1122 | BB4: 1122 | BC4: 1 | BD4: Clay Pit | BE4: 1771686882 | BF4: 1772135664 | BG4: 0.971543 | BH4: Clay | BI4: 2 | BJ4: 1771686882 | BK4: 200 | BL4: 5 | BM4: 2 | BN4: 1 | BO4: 0 | BP4: 0 | BQ4: 0.7333 | BR4: 0.7333 | BT4: 7 | BU4: Concrete | BV4: 4556 | BW4: 5262 | BX4: 1772203036
A5: 29 | B5: Insecticide Factory | C5: 1 | D5: no | F5: 7 | G5: Concrete | H5: 9 | I5: 216299 | O5: 4 | P5: Clay Pit | S5: 14 | T5: Scan junkie | U5: Scan for deposits {} times | V5: 0 | W5: 0 | X5: 25 | Y5: 48 | Z5: 45 | AA5: 10 | AB5: 2247000000 | AC5: 217908 | AD5: 0 | AE5: 0 | AF5: 3 | AG5: https://appweb.resources-game.ch/webcontent/img/questimg/scanneumgebung.jpg | AI5: 28 | AJ5: Insecticides | AK5: 29 | AL5: Insecticide Factory | AM5: 3500 | AN5: 35 | AO5: 2400 | AP5: 36 | AQ5: 1 | AR5: 20 | AS5: 3 | AW5: 4 | AX5: 48.198863 | AY5: 16.386327 | AZ5: 1 | BA5: 966 | BB5: 966 | BC5: 1 | BD5: Clay Pit | BE5: 1771687402 | BF5: 1772135664 | BG5: 0.971543 | BH5: Clay | BI5: 2 | BJ5: 1771687402 | BK5: 200 | BL5: 5 | BM5: 2 | BN5: 1 | BO5: 0 | BP5: 0 | BQ5: 0.6314 | BR5: 0.6314 | BT5: 8 | BU5: Coal | BV5: 2426 | BW5: 2452 | BX5: 1772203036
A6: 31 | B6: Ironworks | C6: 3 | D6: no | F6: 8 | G6: Coal | H6: 8 | I6: 294499 | O6: 5 | P6: Gravel Pit | S6: 17 | T6: Warehouse boss | U6: Expand your warehouses {} times | V6: 0 | W6: 0 | X6: 104 | Y6: 96 | Z6: 115 | AA6: 13000 | AB6: 415636000000 | AC6: 0 | AD6: 0 | AE6: 0 | AF6: 7 | AG6: https://appweb.resources-game.ch/webcontent/img/questimg/lager.jpg | AI6: 30 | AJ6: Steel | AK6: 31 | AL6: Ironworks | AM6: 450 | AN6: 1 | AO6: 350 | AP6: 13 | AQ6: 7 | AR6: 8 | AS6: 10 | AW6: 4 | AX6: 48.138206 | AY6: 16.445265 | AZ6: 1 | BA6: 996 | BB6: 996 | BC6: 1 | BD6: Clay Pit | BE6: 1771724868 | BF6: 1772135664 | BG6: 0.971543 | BH6: Clay | BI6: 2 | BJ6: 1771724868 | BK6: 200 | BL6: 5 | BM6: 2 | BN6: 1 | BO6: 0 | BP6: 0 | BQ6: 0.651 | BR6: 0.651 | BT6: 10 | BU6: Crude Oil | BV6: 2519 | BW6: 0 | BX6: 1772203036
A7: 33 | B7: Aluminium Factory | C7: 1 | D7: no | F7: 10 | G7: Crude Oil | H7: 3 | I7: 110 | O7: 6 | P7: Concrete Factory | Q7: https://api.resources-game.ch/resimg/res6.png | S7: 22 | T7: Stinginess is awesome! | U7: Perform {} free (="boss in range") maintenances | V7: 0 | W7: 0 | X7: 130 | Y7: 168 | Z7: 43 | AA7: 390 | AB7: 44341000000 | AC7: 0 | AD7: 0 | AE7: 0 | AF7: 7 | AG7: https://appweb.resources-game.ch/webcontent/img/questimg/geizistgeil.jpg | AI7: 32 | AJ7: Aluminium | AK7: 33 | AL7: Aluminium Factory | AM7: 320 | AN7: 4 | AO7: 5000 | AP7: 12 | AQ7: 24 | AW7: 4 | AX7: 48.140479 | AY7: 16.434311 | AZ7: 1 | BA7: 1188 | BB7: 1188 | BC7: 1 | BD7: Clay Pit | BE7: 1771724905 | BF7: 1772135664 | BG7: 0.971543 | BH7: Clay | BI7: 2 | BJ7: 1771724905 | BK7: 200 | BL7: 5 | BM7: 2 | BN7: 1 | BO7: 0 | BP7: 0 | BQ7: 0.7765 | BR7: 0.7765 | BT7: 12 | BU7: Bauxite | BV7: 2045 | BW7: 2086 | BX7: 1772203036
A8: 37 | B8: Copper Refinery | C8: 1 | D8: no | F8: 12 | G8: Bauxite | H8: 6 | I8: 94043 | O8: 7 | P8: Concrete | Q8: https://api.resources-game.ch/resimg/res7.png | S8: 31 | T8: Need more insecticides! | U8: Sell {}m3 insecticides | V8: 0 | W8: 0 | X8: 1441650 | Y8: 72 | Z8: 42 | AA8: 1 | AB8: 95776000000 | AC8: 0 | AD8: 0 | AE8: 0 | AF8: 2 | AG8: https://appweb.resources-game.ch/webcontent/img/questimg/insektizidebedarf.jpg | AI8: 35 | AJ8: Silver | AK8: 34 | AL8: Silver Refinery | AM8: 3000 | AN8: 50 | AO8: 10000 | AP8: 15 | AQ8: 8 | AW8: 4 | AX8: 48.146065 | AY8: 16.430753 | AZ8: 1 | BA8: 1044 | BB8: 1044 | BC8: 1 | BD8: Clay Pit | BE8: 1771724934 | BF8: 1772135664 | BG8: 0.971543 | BH8: Clay | BI8: 2 | BJ8: 1771724934 | BK8: 200 | BL8: 5 | BM8: 2 | BN8: 1 | BO8: 0 | BP8: 0 | BQ8: 0.6824 | BR8: 0.6824 | BT8: 13 | BU8: Iron Ore | BV8: 1267 | BW8: 1499 | BX8: 1772203036
A9: 39 | B9: Oil Refinery | C9: 1 | D9: no | F9: 13 | G9: Iron Ore | H9: 3 | I9: 800 | O9: 8 | P9: Coal | Q9: https://api.resources-game.ch/resimg/res8.png | S9: 32 | T9: Time is Money | U9: Trigger {} instant-productions (use a Giant Diamond to hasten production) | V9: 0 | W9: 0 | X9: 10 | Y9: 144 | Z9: 84 | AA9: 52000 | AB9: 220067000000 | AC9: 0 | AD9: 0 | AE9: 0 | AF9: 4 | AG9: https://appweb.resources-game.ch/webcontent/img/questimg/zeitistgeld.jpg | AI9: 36 | AJ9: Copper | AK9: 37 | AL9: Copper Refinery | AM9: 270 | AN9: 3 | AO9: 2500 | AP9: 26 | AQ9: 9 | AW9: 4 | AX9: 48.146716 | AY9: 16.430304 | AZ9: 1 | BA9: 1476 | BB9: 1476 | BC9: 1 | BD9: Clay Pit | BE9: 1771724937 | BF9: 1772135664 | BG9: 0.971543 | BH9: Clay | BI9: 2 | BJ9: 1771724937 | BK9: 200 | BL9: 5 | BM9: 2 | BN9: 1 | BO9: 0 | BP9: 0 | BQ9: 0.9647 | BR9: 0.9647 | BT9: 14 | BU9: Gold Ore | BV9: 956 | BW9: 0 | BX9: 1772203036
A10: 61 | B10: Glazier's Workshop | C10: 1 | D10: no | F10: 20 | G10: Limestone | H10: 15 | I10: 741425 | O10: 9 | P10: Coal Mine | S10: 33 | T10: Paranoia? | U10: Assign {} units to defend your mines | V10: 0 | W10: 0 | X10: 20000 | Y10: 168 | Z10: 99 | AA10: 130 | AB10: 179657000000 | AC10: 0 | AD10: 0 | AE10: 0 | AF10: 7 | AG10: https://appweb.resources-game.ch/webcontent/img/questimg/paranoid.jpg | AI10: 38 | AJ10: Fossil Fuel | AK10: 39 | AL10: Oil Refinery | AM10: 640 | AN10: 4 | AO10: 150 | AP10: 10 | AQ10: 4 | AW10: 4 | AX10: 48.15238 | AY10: 16.426931 | AZ10: 1 | BA10: 1020 | BB10: 1020 | BC10: 1 | BD10: Clay Pit | BE10: 1771724971 | BF10: 1772135664 | BG10: 0.971543 | BH10: Clay | BI10: 2 | BJ10: 1771724971 | BK10: 200 | BL10: 5 | BM10: 2 | BN10: 1 | BO10: 0 | BP10: 0 | BQ10: 0.6667 | BR10: 0.6667 | BT10: 15 | BU10: Silver Ore | BV10: 1433 | BW10: 0 | BX10: 1772203036
A11: 63 | B11: Plastic Factory | C11: 1 | D11: no | F11: 22 | G11: Fertilizer | H11: 4 | I11: 71149 | O11: 10 | P11: Crude Oil | Q11: https://api.resources-game.ch/resimg/res10.png | S11: 35 | T11: Pimp my mine | U11: Apply {} Tech upgrades to your mines | V11: 0 | W11: 0 | X11: 300 | Y11: 168 | Z11: 44 | AA11: 30 | AB11: 20723000000 | AC11: 0 | AD11: 0 | AE11: 0 | AF11: 7 | AG11: https://appweb.resources-game.ch/webcontent/img/questimg/pimpmyfa.jpg | AI11: 51 | AJ11: Titanium | AK11: 52 | AL11: Titanium Refinery | AM11: 320 | AN11: 4 | AO11: 10000 | AP11: 49 | AQ11: 8 | AW11: 4 | AX11: 48.161225 | AY11: 16.421333 | AZ11: 1 | BA11: 1020 | BB11: 1020 | BC11: 1 | BD11: Clay Pit | BE11: 1771725073 | BF11: 1772135664 | BG11: 0.971543 | BH11: Clay | BI11: 2 | BJ11: 1771725073 | BK11: 200 | BL11: 5 | BM11: 2 | BN11: 1 | BO11: 0 | BP11: 0 | BQ11: 0.6667 | BR11: 0.6667 | BT11: 20 | BU11: Limestone | BV11: 496 | BW11: 515 | BX11: 1772203036
A12: 91 | B12: Lithium Refinery | C12: 1 | D12: no | F12: 24 | G12: Bricks | H12: 10 | I12: 41536 | O12: 11 | P12: Oil Derrick | S12: 37 | T12: Pimp my factory | U12: Upgrade your factories {} times | V12: 0 | W12: 0 | X12: 5 | Y12: 120 | Z12: 1 | AA12: 10400000000 | AB12: 20800000000 | AC12: 0 | AD12: 0 | AE12: 0 | AF12: 5 | AG12: https://appweb.resources-game.ch/webcontent/img/questimg/pimp_my_fabrik.jpg | AI12: 60 | AJ12: Glass | AK12: 61 | AL12: Glazier's Workshop | AM12: 640 | AN12: 8 | AO12: 3000 | AP12: 53 | AQ12: 6 | AR12: 38 | AS12: 8 | AT12: 20 | AU12: 4 | AW12: 4 | AX12: 48.16306 | AY12: 16.419027 | AZ12: 1 | BA12: 1176 | BB12: 1176 | BC12: 1 | BD12: Clay Pit | BE12: 1771725081 | BF12: 1772135664 | BG12: 0.971543 | BH12: Clay | BI12: 2 | BJ12: 1771725081 | BK12: 200 | BL12: 5 | BM12: 2 | BN12: 1 | BO12: 0 | BP12: 0 | BQ12: 0.7686 | BR12: 0.7686 | BT12: 22 | BU12: Fertilizer | BV12: 2169 | BW12: 0 | BX12: 1772203036
A13: 95 | B13: Battery Factory | C13: 1 | D13: no | F13: 26 | G13: Chalcopyrite | H13: 6 | I13: 150705 | O13: 12 | P13: Bauxite | Q13: https://api.resources-game.ch/resimg/res12.png | S13: 38 | T13: Maintenance | U13: Repair {} mines with maintenance kits | V13: 0 | W13: 0 | X13: 40 | Y13: 48 | Z13: 84 | AA13: 1560 | AB13: 33010000000 | AC13: 0 | AD13: 0 | AE13: 0 | AF13: 2 | AG13: https://appweb.resources-game.ch/webcontent/img/questimg/wartung.jpg | AI13: 58 | AJ13: Plastics | AK13: 63 | AL13: Plastic Factory | AM13: 1800 | AN13: 10 | AO13: 400 | AP13: 10 | AQ13: 1 | AW13: 4 | AX13: 48.163251 | AY13: 16.418665 | AZ13: 1 | BA13: 1332 | BB13: 1332 | BC13: 1 | BD13: Clay Pit | BE13: 1771725086 | BF13: 1772135664 | BG13: 0.971543 | BH13: Clay | BI13: 2 | BJ13: 1771725086 | BK13: 200 | BL13: 5 | BM13: 2 | BN13: 1 | BO13: 0 | BP13: 0 | BQ13: 0.8706 | BR13: 0.8706 | BT13: 24 | BU13: Bricks | BV13: 2795 | BW13: 3245 | BX13: 1772203036
F14: 28 | G14: Insecticides | H14: 4 | I14: 72371 | O14: 13 | P14: Iron Ore | Q14: https://api.resources-game.ch/resimg/res13.png | S14: 41 | T14: Consolation money | U14: Suffer an epidemic | V14: 0 | W14: 0 | X14: 1 | Y14: 120 | Z14: 1 | AA14: 5200000000 | AB14: 1041000000 | AC14: 0 | AD14: 0 | AE14: 0 | AF14: 0 | AG14: https://appweb.resources-game.ch/webcontent/img/questimg/trostpflaster.jpg | AI14: 67 | AJ14: Silicon | AK14: 68 | AL14: Silicon Refinery | AM14: 120 | AN14: 2 | AO14: 49500 | AP14: 53 | AQ14: 20 | AR14: 2 | AS14: 1 | AT14: 38 | AU14: 5 | AW14: 4 | AX14: 48.163554 | AY14: 16.418837 | AZ14: 1 | BA14: 1122 | BB14: 1122 | BC14: 1 | BD14: Clay Pit | BE14: 1771725089 | BF14: 1772135664 | BG14: 0.971543 | BH14: Clay | BI14: 2 | BJ14: 1771725089 | BK14: 200 | BL14: 5 | BM14: 2 | BN14: 1 | BO14: 0 | BP14: 0 | BQ14: 0.7333 | BR14: 0.7333 | BT14: 26 | BU14: Chalcopyrite | BV14: 1350 | BW14: 1350 | BX14: 1772203036
F15: 30 | G15: Steel | H15: 2 | I15: 12863 | O15: 14 | P15: Gold Ore | Q15: https://api.resources-game.ch/resimg/res14.png | S15: 42 | T15: Insurance | U15: Suffer a mine accident | V15: 0 | W15: 0 | X15: 1 | Y15: 120 | Z15: 1 | AA15: 7800000000 | AB15: 1561000000 | AC15: 0 | AD15: 0 | AE15: 0 | AF15: 0 | AG15: https://appweb.resources-game.ch/webcontent/img/questimg/insurance.jpg | AI15: 66 | AJ15: Electronics | AK15: 69 | AL15: Electronics Factory | AM15: 480 | AN15: 8 | AO15: 5000 | AP15: 58 | AQ15: 4 | AR15: 36 | AS15: 3 | AT15: 67 | AU15: 1 | AW15: 4 | AX15: 48.163342 | AY15: 16.41915 | AZ15: 1 | BA15: 1008 | BB15: 1008 | BC15: 1 | BD15: Clay Pit | BE15: 1771725093 | BF15: 1772135664 | BG15: 0.971543 | BH15: Clay | BI15: 2 | BJ15: 1771725093 | BK15: 200 | BL15: 5 | BM15: 2 | BN15: 1 | BO15: 0 | BP15: 0 | BQ15: 0.6588 | BR15: 0.6588 | BT15: 28 | BU15: Insecticides | BV15: 4259 | BW15: 4302 | BX15: 1772203036
F16: 32 | G16: Aluminium | H16: 4 | I16: 1687 | O16: 15 | P16: Silver Ore | Q16: https://api.resources-game.ch/resimg/res15.png | S16: 43 | T16: Wanderer | U16: Walk a distance of {}m (Resources must be running to count) | V16: 1 | W16: 2172 | X16: 6335 | Y16: 192 | Z16: 1 | AA16: 2600000000 | AB16: 0 | AC16: 0 | AD16: 1772097546 | AE16: 1772788746 | AF16: 1 | AG16: https://appweb.resources-game.ch/webcontent/img/questimg/wanderer.jpg | AI16: 75 | AJ16: Medical Technology | AK16: 76 | AL16: Medical Technology Inc. | AM16: 400 | AN16: 10 | AO16: 90000 | AP16: 51 | AQ16: 4 | AR16: 58 | AS16: 2 | AT16: 66 | AU16: 2 | AW16: 4 | AX16: 48.163125 | AY16: 16.419453 | AZ16: 1 | BA16: 996 | BB16: 996 | BC16: 1 | BD16: Clay Pit | BE16: 1771725097 | BF16: 1772135664 | BG16: 0.971543 | BH16: Clay | BI16: 2 | BJ16: 1771725097 | BK16: 200 | BL16: 5 | BM16: 2 | BN16: 1 | BO16: 0 | BP16: 0 | BQ16: 0.651 | BR16: 0.651 | BT16: 30 | BU16: Steel | BV16: 43334 | BW16: 49988 | BX16: 1772203036
F17: 36 | G17: Copper | H17: 4 | I17: 9276 | O17: 16 | P17: Bauxite Mine | S17: 44 | T17: Service | U17: Repair {} of someone else's mines | V17: 0 | W17: 0 | X17: 510 | Y17: 72 | Z17: 1 | AA17: 1300000000 | AB17: 1300000000 | AC17: 0 | AD17: 0 | AE17: 0 | AF17: 1 | AG17: https://appweb.resources-game.ch/webcontent/img/questimg/fremdwartung.jpg | AI17: 79 | AJ17: Gold | AK17: 80 | AL17: Gold Refinery | AM17: 240 | AN17: 3 | AO17: 20000 | AP17: 14 | AQ17: 20 | AW17: 4 | AX17: 48.178356 | AY17: 16.408769 | AZ17: 1 | BA17: 1110 | BB17: 1110 | BC17: 1 | BD17: Clay Pit | BE17: 1771725234 | BF17: 1772135664 | BG17: 0.971543 | BH17: Clay | BI17: 2 | BJ17: 1771725234 | BK17: 200 | BL17: 5 | BM17: 2 | BN17: 1 | BO17: 0 | BP17: 0 | BQ17: 0.7255 | BR17: 0.7255 | BT17: 32 | BU17: Aluminium | BV17: 91432 | BW17: 94900 | BX17: 1772203036
F18: 38 | G18: Fossil Fuel | H18: 4 | I18: 962 | O18: 17 | P18: Iron Ore Mine | S18: 50 | T18: Truck dealer | U18: Sell {} trucks | V18: 0 | W18: 0 | X18: 40000 | Y18: 48 | Z18: 1 | AA18: 3640000000 | AB18: 18200000000 | AC18: 0 | AD18: 0 | AE18: 0 | AF18: 3 | AG18: https://appweb.resources-game.ch/webcontent/img/questimg/spediteur.jpg | AI18: 84 | AJ18: Jewellery | AK18: 85 | AL18: Goldsmith | AM18: 100 | AN18: 2 | AO18: 50000 | AP18: 81 | AQ18: 1000 | AR18: 79 | AS18: 1 | AT18: 35 | AU18: 1 | AW18: 4 | AX18: 48.239368 | AY18: 16.381789 | AZ18: 1 | BA18: 1152 | BB18: 1152 | BC18: 1 | BD18: Clay Pit | BE18: 1771726134 | BF18: 1772135664 | BG18: 0.971543 | BH18: Clay | BI18: 2 | BJ18: 1771726134 | BK18: 200 | BL18: 5 | BM18: 2 | BN18: 1 | BO18: 0 | BP18: 0 | BQ18: 0.7529 | BR18: 0.7529 | BT18: 35 | BU18: Silver | BV18: 1645 | BW18: 1661 | BX18: 1772203036
F19: 40 | G19: Roman Coins | H19: 4 | I19: 32384 | O19: 18 | P19: Gold Mine | S19: 55 | T19: ...anyone need drones? | U19: Sell {} scandrones | V19: 0 | W19: 0 | X19: 400 | Y19: 48 | Z19: 1 | AA19: 1040000000 | AB19: 5200000000 | AC19: 0 | AD19: 0 | AE19: 0 | AF19: 3 | AG19: https://appweb.resources-game.ch/webcontent/img/questimg/drohnendroenen2.jpg | AI19: 92 | AJ19: Lithium | AK19: 91 | AL19: Lithium Refinery | AM19: 750 | AN19: 5 | AO19: 5000 | AP19: 90 | AQ19: 115 | AW19: 4 | AX19: 48.237487 | AY19: 16.378735 | AZ19: 1 | BA19: 1086 | BB19: 1086 | BC19: 1 | BD19: Clay Pit | BE19: 1771726816 | BF19: 1772135664 | BG19: 0.971543 | BH19: Clay | BI19: 2 | BJ19: 1771726816 | BK19: 200 | BL19: 5 | BM19: 2 | BN19: 1 | BO19: 0 | BP19: 0 | BQ19: 0.7098 | BR19: 0.7098 | BT19: 36 | BU19: Copper | BV19: 87230 | BW19: 87231 | BX19: 1772203036
F20: 41 | G20: Fossils | H20: 6 | I20: 154965 | O20: 19 | P20: Silver Mine | AI20: 93 | AJ20: Batteries | AK20: 95 | AL20: Battery Factory | AM20: 600 | AN20: 10 | AO20: 75000 | AP20: 92 | AQ20: 20 | AR20: 58 | AS20: 40 | AT20: 32 | AU20: 10 | AW20: 4 | AX20: 48.238542 | AY20: 16.377994 | AZ20: 1 | BA20: 1086 | BB20: 1086 | BC20: 1 | BD20: Clay Pit | BE20: 1771726834 | BF20: 1772135664 | BG20: 0.971543 | BH20: Clay | BI20: 2 | BJ20: 1771726834 | BK20: 200 | BL20: 5 | BM20: 2 | BN20: 1 | BO20: 0 | BP20: 0 | BQ20: 0.7098 | BR20: 0.7098 | BT20: 38 | BU20: Fossil Fuel | BV20: 28209 | BW20: 29550 | BX20: 1772203036
F21: 42 | G21: Giant Diamond | H21: 1 | I21: 5 | O21: 20 | P21: Limestone | Q21: https://api.resources-game.ch/resimg/res20.png | AI21: 87 | AJ21: Weapons | AK21: 101 | AL21: Arms Factory | AM21: 125 | AN21: 25 | AO21: 250000 | AP21: 30 | AQ21: 1 | AR21: 32 | AS21: 1 | AT21: 93 | AU21: 1 | AW21: 4 | AX21: 48.238741 | AY21: 16.377676 | AZ21: 1 | BA21: 1098 | BB21: 1098 | BC21: 1 | BD21: Clay Pit | BE21: 1771726837 | BF21: 1772135664 | BG21: 0.971543 | BH21: Clay | BI21: 2 | BJ21: 1771726837 | BK21: 200 | BL21: 5 | BM21: 2 | BN21: 1 | BO21: 0 | BP21: 0 | BQ21: 0.7176 | BR21: 0.7176 | BT21: 40 | BU21: Roman Coins | BV21: 56771 | BW21: 65651 | BX21: 1772203036
F22: 44 | G22: Tech Upgrade 1 | H22: 1 | I22: 65 | O22: 21 | P22: Limestone Quarry | AI22: 117 | AJ22: Scan Drones | AK22: 118 | AL22: Drone Shipyard | AM22: 1 | AN22: 1 | AO22: 25000000 | AP22: 66 | AQ22: 25 | AR22: 51 | AS22: 50 | AT22: 93 | AU22: 250 | AW22: 4 | AX22: 48.238961 | AY22: 16.377405 | AZ22: 1 | BA22: 1098 | BB22: 1098 | BC22: 1 | BD22: Clay Pit | BE22: 1771726840 | BF22: 1772135664 | BG22: 0.971543 | BH22: Clay | BI22: 2 | BJ22: 1771726840 | BK22: 200 | BL22: 5 | BM22: 2 | BN22: 1 | BO22: 0 | BP22: 0 | BQ22: 0.7176 | BR22: 0.7176 | BT22: 41 | BU22: Fossils | BV22: 11066 | BW22: 13954 | BX22: 1772203036
F23: 45 | G23: Tech Upgrade 2 | H23: 1 | I23: 10 | O23: 22 | P23: Fertilizer | Q23: https://api.resources-game.ch/resimg/res22.png | AI23: 124 | AJ23: Trucks | AK23: 125 | AL23: Truck plant | AM23: 100 | AN23: 50 | AO23: 2500000 | AP23: 30 | AQ23: 100 | AR23: 93 | AS23: 25 | AT23: 35 | AU23: 50 | AW23: 4 | AX23: 48.239184 | AY23: 16.377115 | AZ23: 1 | BA23: 1122 | BB23: 1122 | BC23: 1 | BD23: Clay Pit | BE23: 1771726844 | BF23: 1772135664 | BG23: 0.971543 | BH23: Clay | BI23: 2 | BJ23: 1771726844 | BK23: 200 | BL23: 5 | BM23: 2 | BN23: 1 | BO23: 0 | BP23: 0 | BQ23: 0.7333 | BR23: 0.7333 | BT23: 42 | BU23: Giant Diamond | BV23: 957950133 | BW23: 0 | BX23: 1772203036
F24: 49 | G24: Ilmenite | H24: 4 | I24: 43902 | O24: 23 | P24: Fertilizer Factory | Q24: https://api.resources-game.ch/resimg/res23.png | AW24: 4 | AX24: 48.239348 | AY24: 16.376758 | AZ24: 1 | BA24: 1272 | BB24: 1272 | BC24: 1 | BD24: Clay Pit | BE24: 1771726847 | BF24: 1772135664 | BG24: 0.971543 | BH24: Clay | BI24: 2 | BJ24: 1771726847 | BK24: 200 | BL24: 5 | BM24: 2 | BN24: 1 | BO24: 0 | BP24: 0 | BQ24: 0.8314 | BR24: 0.8314 | BT24: 43 | BU24: Maintenance Kit | BV24: 56876282 | BW24: 63428000 | BX24: 1772203036
F25: 53 | G25: Quartz Sand | H25: 8 | I25: 279676 | O25: 24 | P25: Bricks | Q25: https://api.resources-game.ch/resimg/res24.png | AW25: 4 | AX25: 48.23961 | AY25: 16.376551 | AZ25: 1 | BA25: 1230 | BB25: 1230 | BC25: 1 | BD25: Clay Pit | BE25: 1771726850 | BF25: 1772135664 | BG25: 0.971543 | BH25: Clay | BI25: 2 | BJ25: 1771726850 | BK25: 200 | BL25: 5 | BM25: 2 | BN25: 1 | BO25: 0 | BP25: 0 | BQ25: 0.8039 | BR25: 0.8039 | BT25: 44 | BU25: Tech Upgrade 1 | BV25: 79761236 | BW25: 81500000 | BX25: 1772203036
F26: 55 | G26: Copper Coins | H26: 4 | I26: 55954 | O26: 25 | P26: Brick Factory | Q26: https://api.resources-game.ch/resimg/res25.png | AW26: 4 | AX26: 48.239876 | AY26: 16.376589 | AZ26: 1 | BA26: 1332 | BB26: 1332 | BC26: 1 | BD26: Clay Pit | BE26: 1771726854 | BF26: 1772135664 | BG26: 0.971543 | BH26: Clay | BI26: 2 | BJ26: 1771726854 | BK26: 200 | BL26: 5 | BM26: 2 | BN26: 1 | BO26: 0 | BP26: 0 | BQ26: 0.8706 | BR26: 0.8706 | BT26: 45 | BU26: Tech Upgrade 2 | BV26: 224349572 | BW26: 262165702 | BX26: 1772203036
F27: 57 | G27: Old Tires | H27: 4 | I27: 54650 | O27: 26 | P27: Chalcopyrite | Q27: https://api.resources-game.ch/resimg/res26.png | AW27: 4 | AX27: 48.239867 | AY27: 16.37617 | AZ27: 1 | BA27: 1476 | BB27: 1476 | BC27: 1 | BD27: Clay Pit | BE27: 1771726857 | BF27: 1772135664 | BG27: 0.971543 | BH27: Clay | BI27: 2 | BJ27: 1771726857 | BK27: 200 | BL27: 5 | BM27: 2 | BN27: 1 | BO27: 0 | BP27: 0 | BQ27: 0.9647 | BR27: 0.9647 | BT27: 46 | BU27: Tech Upgrade 3 | BV27: 251990064 | BW27: 281171204 | BX27: 1772203036
F28: 58 | G28: Plastics | H28: 4 | I28: 51576 | O28: 27 | P28: Copper Mine | AW28: 4 | AX28: 48.240123 | AY28: 16.375953 | AZ28: 1 | BA28: 1530 | BB28: 1530 | BC28: 1 | BD28: Clay Pit | BE28: 1771726861 | BF28: 1772135664 | BG28: 0.971543 | BH28: Clay | BI28: 2 | BJ28: 1771726861 | BK28: 200 | BL28: 5 | BM28: 2 | BN28: 1 | BO28: 0 | BP28: 0 | BQ28: 1 | BR28: 1 | BT28: 48 | BU28: Tech Upgrade 4 | BV28: 104048340 | BW28: 0 | BX28: 1772203036
F29: 60 | G29: Glass | H29: 4 | I29: 31559 | O29: 28 | P29: Insecticides | Q29: https://api.resources-game.ch/resimg/res28.png | AW29: 4 | AX29: 48.240374 | AY29: 16.37608 | AZ29: 1 | BA29: 1464 | BB29: 1464 | BC29: 1 | BD29: Clay Pit | BE29: 1771726864 | BF29: 1772135664 | BG29: 0.971543 | BH29: Clay | BI29: 2 | BJ29: 1771726864 | BK29: 200 | BL29: 5 | BM29: 2 | BN29: 1 | BO29: 0 | BP29: 0 | BQ29: 0.9569 | BR29: 0.9569 | BT29: 49 | BU29: Ilmenite | BV29: 309 | BW29: 312 | BX29: 1772203036
F30: 81 | G30: Rough Diamonds | H30: 2 | I30: 4266 | O30: 29 | P30: Insecticide Factory | Q30: https://api.resources-game.ch/resimg/res29.png | AW30: 4 | AX30: 48.240379 | AY30: 16.375647 | AZ30: 1 | BA30: 1386 | BB30: 1386 | BC30: 1 | BD30: Clay Pit | BE30: 1771726868 | BF30: 1772135664 | BG30: 0.971543 | BH30: Clay | BI30: 2 | BJ30: 1771726868 | BK30: 200 | BL30: 5 | BM30: 2 | BN30: 1 | BO30: 0 | BP30: 0 | BQ30: 0.9059 | BR30: 0.9059 | BT30: 51 | BU30: Titanium | BV30: 35998 | BW30: 36155 | BX30: 1772203036
F31: 90 | G31: Lithium Ore | H31: 4 | I31: 756 | O31: 30 | P31: Steel | Q31: https://api.resources-game.ch/resimg/res30.png | AW31: 4 | AX31: 48.240651 | AY31: 16.375767 | AZ31: 1 | BA31: 1074 | BB31: 1074 | BC31: 1 | BD31: Clay Pit | BE31: 1771726871 | BF31: 1772135664 | BG31: 0.971543 | BH31: Clay | BI31: 2 | BJ31: 1771726871 | BK31: 200 | BL31: 5 | BM31: 2 | BN31: 1 | BO31: 0 | BP31: 0 | BQ31: 0.702 | BR31: 0.702 | BT31: 53 | BU31: Quartz Sand | BV31: 357 | BW31: 0 | BX31: 1772203036
F32: 92 | G32: Lithium | H32: 4 | I32: 166 | O32: 31 | P32: Ironworks | Q32: https://api.resources-game.ch/resimg/res31.png | AW32: 4 | AX32: 48.244113 | AY32: 16.379694 | AZ32: 1 | BA32: 1176 | BB32: 1176 | BC32: 1 | BD32: Clay Pit | BE32: 1771758658 | BF32: 1772135664 | BG32: 0.971543 | BH32: Clay | BI32: 2 | BJ32: 1771758658 | BK32: 200 | BL32: 5 | BM32: 2 | BN32: 1 | BO32: 0 | BP32: 0 | BQ32: 0.7686 | BR32: 0.7686 | BT32: 55 | BU32: Copper Coins | BV32: 20060 | BW32: 23355 | BX32: 1772203036
F33: 93 | G33: Batteries | H33: 4 | I33: 3110 | O33: 32 | P33: Aluminium | Q33: https://api.resources-game.ch/resimg/res32.png | AW33: 4 | AX33: 48.244246 | AY33: 16.380074 | AZ33: 1 | BA33: 1122 | BB33: 1122 | BC33: 1 | BD33: Clay Pit | BE33: 1771758662 | BF33: 1772135664 | BG33: 0.971543 | BH33: Clay | BI33: 2 | BJ33: 1771758662 | BK33: 200 | BL33: 5 | BM33: 2 | BN33: 1 | BO33: 0 | BP33: 0 | BQ33: 0.7333 | BR33: 0.7333 | BT33: 57 | BU33: Old Tires | BV33: 19973 | BW33: 21561 | BX33: 1772203036
F34: 96 | G34: Watch Dogs | H34: 1 | I34: 1135 | O34: 33 | P34: Aluminium Factory | Q34: https://api.resources-game.ch/resimg/res33.png | AW34: 4 | AX34: 48.244186 | AY34: 16.380517 | AZ34: 1 | BA34: 1020 | BB34: 1020 | BC34: 1 | BD34: Clay Pit | BE34: 1771758667 | BF34: 1772135664 | BG34: 0.971543 | BH34: Clay | BI34: 2 | BJ34: 1771758667 | BK34: 200 | BL34: 5 | BM34: 2 | BN34: 1 | BO34: 0 | BP34: 0 | BQ34: 0.6667 | BR34: 0.6667 | BT34: 58 | BU34: Plastics | BV34: 4268 | BW34: 4785 | BX34: 1772203036
F35: 160 | G35: Guest Workers | H35: 1 | I35: 0 | O35: 34 | P35: Silver Refinery | Q35: https://api.resources-game.ch/resimg/res34.png | AW35: 4 | AX35: 48.244444 | AY35: 16.38034 | AZ35: 1 | BA35: 1044 | BB35: 1044 | BC35: 1 | BD35: Clay Pit | BE35: 1771758672 | BF35: 1772135664 | BG35: 0.971543 | BH35: Clay | BI35: 2 | BJ35: 1771758672 | BK35: 200 | BL35: 5 | BM35: 2 | BN35: 1 | BO35: 0 | BP35: 0 | BQ35: 0.6824 | BR35: 0.6824 | BT35: 60 | BU35: Glass | BV35: 43144 | BW35: 49183 | BX35: 1772203036
O36: 35 | P36: Silver | Q36: https://api.resources-game.ch/resimg/res35.png | AW36: 4 | AX36: 48.235403 | AY36: 16.382939 | AZ36: 1 | BA36: 1032 | BB36: 1032 | BC36: 1 | BD36: Clay Pit | BE36: 1771759049 | BF36: 1772135664 | BG36: 0.971543 | BH36: Clay | BI36: 2 | BJ36: 1771759049 | BK36: 200 | BL36: 5 | BM36: 2 | BN36: 1 | BO36: 0 | BP36: 0 | BQ36: 0.6745 | BR36: 0.6745 | BT36: 66 | BU36: Electronics | BV36: 63711 | BW36: 65150 | BX36: 1772203036
O37: 36 | P37: Copper | Q37: https://api.resources-game.ch/resimg/res36.png | AW37: 4 | AX37: 48.228458 | AY37: 16.389524 | AZ37: 1 | BA37: 1218 | BB37: 1218 | BC37: 1 | BD37: Clay Pit | BE37: 1771759170 | BF37: 1772135664 | BG37: 0.971543 | BH37: Clay | BI37: 2 | BJ37: 1771759170 | BK37: 200 | BL37: 5 | BM37: 2 | BN37: 1 | BO37: 0 | BP37: 0 | BQ37: 0.7961 | BR37: 0.7961 | BT37: 67 | BU37: Silicon | BV37: 117430 | BW37: 117431 | BX37: 1772203036
O38: 37 | P38: Copper Refinery | Q38: https://api.resources-game.ch/resimg/res37.png | AW38: 4 | AX38: 48.228181 | AY38: 16.389549 | AZ38: 1 | BA38: 1152 | BB38: 1152 | BC38: 1 | BD38: Clay Pit | BE38: 1771759173 | BF38: 1772135664 | BG38: 0.971543 | BH38: Clay | BI38: 2 | BJ38: 1771759173 | BK38: 200 | BL38: 5 | BM38: 2 | BN38: 1 | BO38: 0 | BP38: 0 | BQ38: 0.7529 | BR38: 0.7529 | BT38: 70 | BU38: Scrap Metal | BV38: 24372 | BW38: 30197 | BX38: 1772203036
O39: 38 | P39: Fossil Fuel | Q39: https://api.resources-game.ch/resimg/res38.png | AW39: 4 | AX39: 48.22741 | AY39: 16.389713 | AZ39: 1 | BA39: 1044 | BB39: 1044 | BC39: 1 | BD39: Clay Pit | BE39: 1771759179 | BF39: 1772135664 | BG39: 0.971543 | BH39: Clay | BI39: 2 | BJ39: 1771759179 | BK39: 200 | BL39: 5 | BM39: 2 | BN39: 1 | BO39: 0 | BP39: 0 | BQ39: 0.6824 | BR39: 0.6824 | BT39: 74 | BU39: Used Oil | BV39: 10356 | BW39: 12723 | BX39: 1772203036
O40: 39 | P40: Oil Refinery | Q40: https://api.resources-game.ch/resimg/res39.png | AW40: 4 | AX40: 48.196772 | AY40: 16.385904 | AZ40: 1 | BA40: 1284 | BB40: 1284 | BC40: 1 | BD40: Clay Pit | BE40: 1771759602 | BF40: 1772135664 | BG40: 0.971543 | BH40: Clay | BI40: 2 | BJ40: 1771759602 | BK40: 200 | BL40: 5 | BM40: 2 | BN40: 1 | BO40: 0 | BP40: 0 | BQ40: 0.8392 | BR40: 0.8392 | BT40: 75 | BU40: Medical Technology | BV40: 171496 | BW40: 0 | BX40: 1772203036
O41: 40 | P41: Roman Coins | Q41: https://api.resources-game.ch/resimg/res40.png | AW41: 4 | AX41: 48.196755 | AY41: 16.38548 | AZ41: 1 | BA41: 1284 | BB41: 1284 | BC41: 1 | BD41: Clay Pit | BE41: 1771759605 | BF41: 1772135664 | BG41: 0.971543 | BH41: Clay | BI41: 2 | BJ41: 1771759605 | BK41: 200 | BL41: 5 | BM41: 2 | BN41: 1 | BO41: 0 | BP41: 0 | BQ41: 0.8392 | BR41: 0.8392 | BT41: 77 | BU41: Plastic Scrap | BV41: 9569 | BW41: 10968 | BX41: 1772203036
O42: 41 | P42: Fossils | Q42: https://api.resources-game.ch/resimg/res41.png | AW42: 4 | AX42: 48.19294 | AY42: 16.388851 | AZ42: 1 | BA42: 1362 | BB42: 1362 | BC42: 1 | BD42: Clay Pit | BE42: 1771759692 | BF42: 1772135664 | BG42: 0.971543 | BH42: Clay | BI42: 2 | BJ42: 1771759692 | BK42: 200 | BL42: 5 | BM42: 2 | BN42: 1 | BO42: 0 | BP42: 0 | BQ42: 0.8902 | BR42: 0.8902 | BT42: 78 | BU42: Electronic Scrap | BV42: 159787 | BW42: 191392 | BX42: 1772203036
O43: 42 | P43: Giant Diamond | Q43: https://api.resources-game.ch/resimg/res42.png | AW43: 4 | AX43: 48.187636 | AY43: 16.390424 | AZ43: 1 | BA43: 1284 | BB43: 1284 | BC43: 1 | BD43: Clay Pit | BE43: 1771759751 | BF43: 1772135664 | BG43: 0.971543 | BH43: Clay | BI43: 2 | BJ43: 1771759751 | BK43: 200 | BL43: 5 | BM43: 2 | BN43: 1 | BO43: 0 | BP43: 0 | BQ43: 0.8392 | BR43: 0.8392 | BT43: 79 | BU43: Gold | BV43: 61076 | BW43: 61076 | BX43: 1772203036
O44: 43 | P44: Maintenance Kit | Q44: https://api.resources-game.ch/resimg/res43.png | AW44: 4 | AX44: 48.187295 | AY44: 16.389721 | AZ44: 1 | BA44: 1206 | BB44: 1206 | BC44: 1 | BD44: Clay Pit | BE44: 1771759755 | BF44: 1772135664 | BG44: 0.971543 | BH44: Clay | BI44: 2 | BJ44: 1771759755 | BK44: 200 | BL44: 5 | BM44: 2 | BN44: 1 | BO44: 0 | BP44: 0 | BQ44: 0.7882 | BR44: 0.7882 | BT44: 81 | BU44: Rough Diamonds | BV44: 3014 | BW44: 3391 | BX44: 1772203036
O45: 44 | P45: Tech Upgrade 1 | Q45: https://api.resources-game.ch/resimg/res44.png | AW45: 4 | AX45: 48.185618 | AY45: 16.39731 | AZ45: 1 | BA45: 1386 | BB45: 1386 | BC45: 1 | BD45: Clay Pit | BE45: 1771762197 | BF45: 1772135664 | BG45: 0.971543 | BH45: Clay | BI45: 2 | BJ45: 1771762197 | BK45: 200 | BL45: 5 | BM45: 2 | BN45: 1 | BO45: 0 | BP45: 0 | BQ45: 0.9059 | BR45: 0.9059 | BT45: 84 | BU45: Jewellery | BV45: 2092699 | BW45: 2092699 | BX45: 1772203036
O46: 45 | P46: Tech Upgrade 2 | Q46: https://api.resources-game.ch/resimg/res45.png | AW46: 4 | AX46: 48.188 | AY46: 16.409108 | AZ46: 1 | BA46: 978 | BB46: 978 | BC46: 1 | BD46: Clay Pit | BE46: 1771762302 | BF46: 1772135664 | BG46: 0.971543 | BH46: Clay | BI46: 2 | BJ46: 1771762302 | BK46: 200 | BL46: 5 | BM46: 2 | BN46: 1 | BO46: 0 | BP46: 0 | BQ46: 0.6392 | BR46: 0.6392 | BT46: 87 | BU46: Weapons | BV46: 277789 | BW46: 280566 | BX46: 1772203036
O47: 46 | P47: Tech Upgrade 3 | Q47: https://api.resources-game.ch/resimg/res46.png | AW47: 4 | AX47: 48.189864 | AY47: 16.411908 | AZ47: 1 | BA47: 1284 | BB47: 1284 | BC47: 1 | BD47: Clay Pit | BE47: 1771762314 | BF47: 1772135664 | BG47: 0.971543 | BH47: Clay | BI47: 2 | BJ47: 1771762314 | BK47: 200 | BL47: 5 | BM47: 2 | BN47: 1 | BO47: 0 | BP47: 0 | BQ47: 0.8392 | BR47: 0.8392 | BT47: 90 | BU47: Lithium Ore | BV47: 460 | BW47: 501 | BX47: 1772203036
... O49: 49 | P49: Ilmenite | Q49: https://api.resources-game.ch/resimg/res49.png | AW49: 4 | AX49: 48.213403 | AY49: 16.445713 | AZ49: 1 | BA49: 1176 | BB49: 1176 | BC49: 1 | BD49: Clay Pit | BE49: 1771762487 | BF49: 1772135664 | BG49: 0.971543 | BH49: Clay | BI49: 2 | BJ49: 1771762487 | BK49: 200 | BL49: 5 | BM49: 2 | BN49: 1 | BO49: 0 | BP49: 0 | BQ49: 0.7686 | BR49: 0.7686 | BT49: 93 | BU49: Batteries | BV49: 205031 | BW49: 207151 | BX49: 1772203036
O50: 50 | P50: Ilmenite Mine | AW50: 4 | AX50: 48.21744 | AY50: 16.447018 | AZ50: 1 | BA50: 1296 | BB50: 1296 | BC50: 1 | BD50: Clay Pit | BE50: 1771762509 | BF50: 1772135664 | BG50: 0.971543 | BH50: Clay | BI50: 2 | BJ50: 1771762509 | BK50: 200 | BL50: 5 | BM50: 2 | BN50: 1 | BO50: 0 | BP50: 0 | BQ50: 0.8471 | BR50: 0.8471 | BT50: 96 | BU50: Watch Dogs | BV50: 901960 | BW50: 1074300 | BX50: 1772203036
O51: 51 | P51: Titanium | Q51: https://api.resources-game.ch/resimg/res51.png | AW51: 4 | AX51: 48.232132 | AY51: 16.45402 | AZ51: 1 | BA51: 1098 | BB51: 1098 | BC51: 1 | BD51: Clay Pit | BE51: 1771762594 | BF51: 1772135664 | BG51: 0.971543 | BH51: Clay | BI51: 2 | BJ51: 1771762594 | BK51: 200 | BL51: 5 | BM51: 2 | BN51: 1 | BO51: 0 | BP51: 0 | BQ51: 0.7176 | BR51: 0.7176 | BT51: 98 | BU51: Security Staff | BV51: 9015284 | BW51: 10828000 | BX51: 1772203036
O52: 52 | P52: Titanium Refinery | Q52: https://api.resources-game.ch/resimg/res52.png | AW52: 4 | AX52: 48.232419 | AY52: 16.454271 | AZ52: 1 | BA52: 1176 | BB52: 1176 | BC52: 1 | BD52: Clay Pit | BE52: 1771762603 | BF52: 1772135664 | BG52: 0.971543 | BH52: Clay | BI52: 2 | BJ52: 1771762603 | BK52: 200 | BL52: 5 | BM52: 2 | BN52: 1 | BO52: 0 | BP52: 0 | BQ52: 0.7686 | BR52: 0.7686 | BT52: 99 | BU52: Elite Force | BV52: 27606409 | BW52: 34372901 | BX52: 1772203036
O53: 53 | P53: Quartz Sand | Q53: https://api.resources-game.ch/resimg/res53.png | AW53: 4 | AX53: 48.237132 | AY53: 16.458268 | AZ53: 1 | BA53: 1230 | BB53: 1230 | BC53: 1 | BD53: Clay Pit | BE53: 1771762618 | BF53: 1772135664 | BG53: 0.971543 | BH53: Clay | BI53: 2 | BJ53: 1771762618 | BK53: 200 | BL53: 5 | BM53: 2 | BN53: 1 | BO53: 0 | BP53: 0 | BQ53: 0.8039 | BR53: 0.8039 | BT53: 102 | BU53: Attack Dogs | BV53: 988590 | BW53: 1363500 | BX53: 1772203036
O54: 54 | P54: Sand Mine | AW54: 4 | AX54: 48.237781 | AY54: 16.458417 | AZ54: 1 | BA54: 1320 | BB54: 1320 | BC54: 1 | BD54: Clay Pit | BE54: 1771762624 | BF54: 1772135664 | BG54: 0.971543 | BH54: Clay | BI54: 2 | BJ54: 1771762624 | BK54: 200 | BL54: 5 | BM54: 2 | BN54: 1 | BO54: 0 | BP54: 0 | BQ54: 0.8627 | BR54: 0.8627 | BT54: 103 | BU54: Gangster | BV54: 10854366 | BW54: 12400000 | BX54: 1772203036
O55: 55 | P55: Copper Coins | Q55: https://api.resources-game.ch/resimg/res55.png | AW55: 4 | AX55: 48.264821 | AY55: 16.476384 | AZ55: 1 | BA55: 1062 | BB55: 1062 | BC55: 1 | BD55: Clay Pit | BE55: 1771762779 | BF55: 1772135664 | BG55: 0.971543 | BH55: Clay | BI55: 2 | BJ55: 1771762779 | BK55: 200 | BL55: 5 | BM55: 2 | BN55: 1 | BO55: 0 | BP55: 0 | BQ55: 0.6941 | BR55: 0.6941 | BT55: 104 | BU55: Private Army | BV55: 37803242 | BW55: 48424148 | BX55: 1772203036
O56: 57 | P56: Old Tires | Q56: https://api.resources-game.ch/resimg/res57.png | AW56: 4 | AX56: 48.26536 | AY56: 16.476615 | AZ56: 1 | BA56: 1020 | BB56: 1020 | BC56: 1 | BD56: Clay Pit | BE56: 1771762783 | BF56: 1772135664 | BG56: 0.971543 | BH56: Clay | BI56: 2 | BJ56: 1771762783 | BK56: 200 | BL56: 5 | BM56: 2 | BN56: 1 | BO56: 0 | BP56: 0 | BQ56: 0.6667 | BR56: 0.6667 | BT56: 115 | BU56: Waste Glass | BV56: 32002 | BW56: 39188 | BX56: 1772203036
O57: 58 | P57: Plastics | Q57: https://api.resources-game.ch/resimg/res58.png | AW57: 4 | AX57: 48.26719 | AY57: 16.498518 | AZ57: 1 | BA57: 1176 | BB57: 1176 | BC57: 1 | BD57: Clay Pit | BE57: 1771762859 | BF57: 1772135664 | BG57: 0.971543 | BH57: Clay | BI57: 2 | BJ57: 1771762859 | BK57: 200 | BL57: 5 | BM57: 2 | BN57: 1 | BO57: 0 | BP57: 0 | BQ57: 0.7686 | BR57: 0.7686 | BT57: 117 | BU57: Scan Drones | BV57: 95975976 | BW57: 0 | BX57: 1772203036
O58: 59 | P58: Recycling Plant | Q58: https://api.resources-game.ch/resimg/res59.png | AW58: 4 | AX58: 48.297842 | AY58: 16.509616 | AZ58: 1 | BA58: 1044 | BB58: 1044 | BC58: 1 | BD58: Clay Pit | BE58: 1771763002 | BF58: 1772135664 | BG58: 0.971543 | BH58: Clay | BI58: 2 | BJ58: 1771763002 | BK58: 200 | BL58: 5 | BM58: 2 | BN58: 1 | BO58: 0 | BP58: 0 | BQ58: 0.6824 | BR58: 0.6824 | BT58: 120 | BU58: Drone Wreckage | BV58: 9738851 | BW58: 11539372 | BX58: 1772203036
O59: 60 | P59: Glass | Q59: https://api.resources-game.ch/resimg/res60.png | AW59: 4 | AX59: 48.298972 | AY59: 16.509309 | AZ59: 1 | BA59: 1008 | BB59: 1008 | BC59: 1 | BD59: Clay Pit | BE59: 1771763006 | BF59: 1772135664 | BG59: 0.971543 | BH59: Clay | BI59: 2 | BJ59: 1771763006 | BK59: 200 | BL59: 5 | BM59: 2 | BN59: 1 | BO59: 0 | BP59: 0 | BQ59: 0.6588 | BR59: 0.6588 | BT59: 124 | BU59: Trucks | BV59: 293067 | BW59: 293375 | BX59: 1772203036
O60: 61 | P60: Glazier's Workshop | Q60: https://api.resources-game.ch/resimg/res61.png | AW60: 4 | AX60: 48.352176 | AY60: 16.483148 | AZ60: 1 | BA60: 1464 | BB60: 1464 | BC60: 1 | BD60: Clay Pit | BE60: 1771763270 | BF60: 1772135664 | BG60: 0.971543 | BH60: Clay | BI60: 2 | BJ60: 1771763270 | BK60: 200 | BL60: 5 | BM60: 2 | BN60: 1 | BO60: 0 | BP60: 0 | BQ60: 0.9569 | BR60: 0.9569 | BT60: 158 | BU60: Night Shift | BV60: 5936962629 | BW60: 7373000000 | BX60: 1772203036
O61: 62 | P61: Casino | Q61: https://api.resources-game.ch/resimg/res62.png | AW61: 4 | AX61: 48.397014 | AY61: 16.514596 | AZ61: 1 | BA61: 1464 | BB61: 1464 | BC61: 1 | BD61: Clay Pit | BE61: 1771763486 | BF61: 1772135664 | BG61: 0.971543 | BH61: Clay | BI61: 2 | BJ61: 1771763486 | BK61: 200 | BL61: 5 | BM61: 2 | BN61: 1 | BO61: 0 | BP61: 0 | BQ61: 0.9569 | BR61: 0.9569 | BT61: 159 | BU61: Overtime | BV61: 8391908029 | BW61: 10302083759 | BX61: 1772203036
O62: 63 | P62: Plastic Factory | Q62: https://api.resources-game.ch/resimg/res63.png | AW62: 4 | AX62: 48.427789 | AY62: 16.548463 | AZ62: 1 | BA62: 1032 | BB62: 1032 | BC62: 1 | BD62: Clay Pit | BE62: 1771763647 | BF62: 1772135664 | BG62: 0.971543 | BH62: Clay | BI62: 2 | BJ62: 1771763647 | BK62: 200 | BL62: 5 | BM62: 2 | BN62: 1 | BO62: 0 | BP62: 0 | BQ62: 0.6745 | BR62: 0.6745 | BT62: 160 | BU62: Guest Workers | BV62: 27599847754 | BW62: 31025300000 | BX62: 1772203036
O63: 65 | P63: Museum | Q63: https://api.resources-game.ch/resimg/res65.png | AW63: 4 | AX63: 48.446444 | AY63: 16.555065 | AZ63: 1 | BA63: 1206 | BB63: 1206 | BC63: 1 | BD63: Clay Pit | BE63: 1771763727 | BF63: 1772135664 | BG63: 0.971543 | BH63: Clay | BI63: 2 | BJ63: 1771763727 | BK63: 200 | BL63: 5 | BM63: 2 | BN63: 1 | BO63: 0 | BP63: 0 | BQ63: 0.7882 | BR63: 0.7882 | BT63: 161 | BU63: Wage Subsidy | BV63: 76762929932 | BW63: 90690000000 | BX63: 1772203036
O64: 66 | P64: Electronics | Q64: https://api.resources-game.ch/resimg/res66.png | AW64: 4 | AX64: 48.447364 | AY64: 16.554801 | AZ64: 1 | BA64: 1254 | BB64: 1254 | BC64: 1 | BD64: Clay Pit | BE64: 1771763733 | BF64: 1772135664 | BG64: 0.971543 | BH64: Clay | BI64: 2 | BJ64: 1771763733 | BK64: 200 | BL64: 5 | BM64: 2 | BN64: 1 | BO64: 0 | BP64: 0 | BQ64: 0.8196 | BR64: 0.8196
O65: 67 | P65: Silicon | Q65: https://api.resources-game.ch/resimg/res67.png | AW65: 4 | AX65: 48.471857 | AY65: 16.559531 | AZ65: 1 | BA65: 1044 | BB65: 1044 | BC65: 1 | BD65: Clay Pit | BE65: 1771763831 | BF65: 1772135664 | BG65: 0.971543 | BH65: Clay | BI65: 2 | BJ65: 1771763831 | BK65: 200 | BL65: 5 | BM65: 2 | BN65: 1 | BO65: 0 | BP65: 0 | BQ65: 0.6824 | BR65: 0.6824
O66: 68 | P66: Silicon Refinery | Q66: https://api.resources-game.ch/resimg/res68.png | AW66: 4 | AX66: 48.67011 | AY66: 16.67661 | AZ66: 1 | BA66: 1074 | BB66: 1074 | BC66: 1 | BD66: Clay Pit | BE66: 1771764805 | BF66: 1772135664 | BG66: 0.971543 | BH66: Clay | BI66: 2 | BJ66: 1771764805 | BK66: 200 | BL66: 5 | BM66: 2 | BN66: 1 | BO66: 0 | BP66: 0 | BQ66: 0.702 | BR66: 0.702
O67: 69 | P67: Electronics Factory | Q67: https://api.resources-game.ch/resimg/res69.png | AW67: 4 | AX67: 48.674772 | AY67: 16.671315 | AZ67: 1 | BA67: 1152 | BB67: 1152 | BC67: 1 | BD67: Clay Pit | BE67: 1771764828 | BF67: 1772135664 | BG67: 0.971543 | BH67: Clay | BI67: 2 | BJ67: 1771764828 | BK67: 200 | BL67: 5 | BM67: 2 | BN67: 1 | BO67: 0 | BP67: 0 | BQ67: 0.7529 | BR67: 0.7529
O68: 70 | P68: Scrap Metal | Q68: https://api.resources-game.ch/resimg/res70.png | AW68: 4 | AX68: 48.675615 | AY68: 16.670077 | AZ68: 1 | BA68: 966 | BB68: 966 | BC68: 1 | BD68: Clay Pit | BE68: 1771764833 | BF68: 1772135664 | BG68: 0.971543 | BH68: Clay | BI68: 2 | BJ68: 1771764833 | BK68: 200 | BL68: 5 | BM68: 2 | BN68: 1 | BO68: 0 | BP68: 0 | BQ68: 0.6314 | BR68: 0.6314
O69: 71 | P69: Hospital | Q69: https://api.resources-game.ch/resimg/res71.png | AW69: 4 | AX69: 48.680547 | AY69: 16.660828 | AZ69: 1 | BA69: 1296 | BB69: 1296 | BC69: 1 | BD69: Clay Pit | BE69: 1771764867 | BF69: 1772135664 | BG69: 0.971543 | BH69: Clay | BI69: 2 | BJ69: 1771764867 | BK69: 200 | BL69: 5 | BM69: 2 | BN69: 1 | BO69: 0 | BP69: 0 | BQ69: 0.8471 | BR69: 0.8471
O70: 72 | P70: Law Firm | Q70: https://api.resources-game.ch/resimg/res72.png | AW70: 4 | AX70: 48.696647 | AY70: 16.654447 | AZ70: 1 | BA70: 1152 | BB70: 1152 | BC70: 1 | BD70: Clay Pit | BE70: 1771764937 | BF70: 1772135664 | BG70: 0.971543 | BH70: Clay | BI70: 2 | BJ70: 1771764937 | BK70: 200 | BL70: 5 | BM70: 2 | BN70: 1 | BO70: 0 | BP70: 0 | BQ70: 0.7529 | BR70: 0.7529
O71: 74 | P71: Used Oil | Q71: https://api.resources-game.ch/resimg/res74.png | AW71: 4 | AX71: 48.697505 | AY71: 16.653727 | AZ71: 1 | BA71: 1176 | BB71: 1176 | BC71: 1 | BD71: Clay Pit | BE71: 1771764940 | BF71: 1772135664 | BG71: 0.971543 | BH71: Clay | BI71: 2 | BJ71: 1771764940 | BK71: 200 | BL71: 5 | BM71: 2 | BN71: 1 | BO71: 0 | BP71: 0 | BQ71: 0.7686 | BR71: 0.7686
O72: 75 | P72: Medical Technology | Q72: https://api.resources-game.ch/resimg/res75.png | AW72: 4 | AX72: 49.565693 | AY72: 15.28968 | AZ72: 1 | BA72: 1110 | BB72: 1110 | BC72: 1 | BD72: Clay Pit | BE72: 1771771802 | BF72: 1772135664 | BG72: 0.971543 | BH72: Clay | BI72: 2 | BJ72: 1771771802 | BK72: 200 | BL72: 5 | BM72: 2 | BN72: 1 | BO72: 0 | BP72: 0 | BQ72: 0.7255 | BR72: 0.7255
O73: 76 | P73: Medical Technology Inc. | Q73: https://api.resources-game.ch/resimg/res76.png | AW73: 4 | AX73: 49.56554 | AY73: 15.290033 | AZ73: 1 | BA73: 1008 | BB73: 1008 | BC73: 1 | BD73: Clay Pit | BE73: 1771771828 | BF73: 1772135664 | BG73: 0.971543 | BH73: Clay | BI73: 2 | BJ73: 1771771828 | BK73: 200 | BL73: 5 | BM73: 2 | BN73: 1 | BO73: 0 | BP73: 0 | BQ73: 0.6588 | BR73: 0.6588
O74: 77 | P74: Plastic Scrap | Q74: https://api.resources-game.ch/resimg/res77.png | AW74: 4 | AX74: 49.565425 | AY74: 15.289657 | AZ74: 1 | BA74: 1086 | BB74: 1086 | BC74: 1 | BD74: Clay Pit | BE74: 1771771834 | BF74: 1772135664 | BG74: 0.971543 | BH74: Clay | BI74: 2 | BJ74: 1771771834 | BK74: 200 | BL74: 5 | BM74: 2 | BN74: 1 | BO74: 0 | BP74: 0 | BQ74: 0.7098 | BR74: 0.7098
O75: 78 | P75: Electronic Scrap | Q75: https://api.resources-game.ch/resimg/res78.png | AW75: 4 | AX75: 49.565566 | AY75: 15.289306 | AZ75: 1 | BA75: 1032 | BB75: 1032 | BC75: 1 | BD75: Clay Pit | BE75: 1771771841 | BF75: 1772135664 | BG75: 0.971543 | BH75: Clay | BI75: 2 | BJ75: 1771771841 | BK75: 200 | BL75: 5 | BM75: 2 | BN75: 1 | BO75: 0 | BP75: 0 | BQ75: 0.6745 | BR75: 0.6745
... O78: 81 | P78: Rough Diamonds | Q78: https://api.resources-game.ch/resimg/res81.png | AW78: 4 | AX78: 50.082611 | AY78: 14.415282 | AZ78: 1 | BA78: 1044 | BB78: 1044 | BC78: 1 | BD78: Clay Pit | BE78: 1771891737 | BF78: 1772135664 | BG78: 0.971543 | BH78: Clay | BI78: 2 | BJ78: 1771891737 | BK78: 200 | BL78: 5 | BM78: 2 | BN78: 1 | BO78: 0 | BP78: 0 | BQ78: 0.6824 | BR78: 0.6824
O79: 82 | P79: Diamond Mine | AW79: 4 | AX79: 50.080299 | AY79: 14.4163 | AZ79: 1 | BA79: 1140 | BB79: 1140 | BC79: 1 | BD79: Clay Pit | BE79: 1771891990 | BF79: 1772135664 | BG79: 0.971543 | BH79: Clay | BI79: 2 | BJ79: 1771891990 | BK79: 200 | BL79: 5 | BM79: 2 | BN79: 1 | BO79: 0 | BP79: 0 | BQ79: 0.7451 | BR79: 0.7451
O80: 84 | P80: Jewellery | Q80: https://api.resources-game.ch/resimg/res84.png | AW80: 4 | AX80: 50.079717 | AY80: 14.416041 | AZ80: 1 | BA80: 1188 | BB80: 1188 | BC80: 1 | BD80: Clay Pit | BE80: 1771892064 | BF80: 1772135664 | BG80: 0.971543 | BH80: Clay | BI80: 2 | BJ80: 1771892064 | BK80: 200 | BL80: 5 | BM80: 2 | BN80: 1 | BO80: 0 | BP80: 0 | BQ80: 0.7765 | BR80: 0.7765
O81: 85 | P81: Goldsmith | Q81: https://api.resources-game.ch/resimg/res85.png | AW81: 4 | AX81: 50.07924 | AY81: 14.416043 | AZ81: 1 | BA81: 1152 | BB81: 1152 | BC81: 1 | BD81: Clay Pit | BE81: 1771892108 | BF81: 1772135664 | BG81: 0.971543 | BH81: Clay | BI81: 2 | BJ81: 1771892108 | BK81: 200 | BL81: 5 | BM81: 2 | BN81: 1 | BO81: 0 | BP81: 0 | BQ81: 0.7529 | BR81: 0.7529
O82: 86 | P82: Mafia HQ | Q82: https://api.resources-game.ch/resimg/res86.png | AW82: 4 | AX82: 50.078916 | AY82: 14.416476 | AZ82: 1 | BA82: 1272 | BB82: 1272 | BC82: 1 | BD82: Clay Pit | BE82: 1771892143 | BF82: 1772135664 | BG82: 0.971543 | BH82: Clay | BI82: 2 | BJ82: 1771892143 | BK82: 200 | BL82: 5 | BM82: 2 | BN82: 1 | BO82: 0 | BP82: 0 | BQ82: 0.8314 | BR82: 0.8314
O83: 87 | P83: Weapons | Q83: https://api.resources-game.ch/resimg/res87.png | AW83: 4 | AX83: 50.078451 | AY83: 14.416916 | AZ83: 1 | BA83: 1272 | BB83: 1272 | BC83: 1 | BD83: Clay Pit | BE83: 1771892177 | BF83: 1772135664 | BG83: 0.971543 | BH83: Clay | BI83: 2 | BJ83: 1771892177 | BK83: 200 | BL83: 5 | BM83: 2 | BN83: 1 | BO83: 0 | BP83: 0 | BQ83: 0.8314 | BR83: 0.8314
O84: 89 | P84: Lithium Ore Mine | AW84: 4 | AX84: 50.078335 | AY84: 14.417309 | AZ84: 1 | BA84: 1044 | BB84: 1044 | BC84: 1 | BD84: Clay Pit | BE84: 1771892184 | BF84: 1772135664 | BG84: 0.971543 | BH84: Clay | BI84: 2 | BJ84: 1771892184 | BK84: 200 | BL84: 5 | BM84: 2 | BN84: 1 | BO84: 0 | BP84: 0 | BQ84: 0.6824 | BR84: 0.6824
O85: 90 | P85: Lithium Ore | Q85: https://api.resources-game.ch/resimg/res90.png | AW85: 4 | AX85: 50.078238 | AY85: 14.417763 | AZ85: 1 | BA85: 1206 | BB85: 1206 | BC85: 1 | BD85: Clay Pit | BE85: 1771892193 | BF85: 1772135664 | BG85: 0.971543 | BH85: Clay | BI85: 2 | BJ85: 1771892193 | BK85: 200 | BL85: 5 | BM85: 2 | BN85: 1 | BO85: 0 | BP85: 0 | BQ85: 0.7882 | BR85: 0.7882
O86: 91 | P86: Lithium Refinery | Q86: https://api.resources-game.ch/resimg/res91.png | AW86: 4 | AX86: 50.077968 | AY86: 14.417815 | AZ86: 1 | BA86: 1308 | BB86: 1308 | BC86: 1 | BD86: Clay Pit | BE86: 1771892222 | BF86: 1772135664 | BG86: 0.971543 | BH86: Clay | BI86: 2 | BJ86: 1771892222 | BK86: 200 | BL86: 5 | BM86: 2 | BN86: 1 | BO86: 0 | BP86: 0 | BQ86: 0.8549 | BR86: 0.8549
O87: 92 | P87: Lithium | Q87: https://api.resources-game.ch/resimg/res92.png | AW87: 4 | AX87: 50.077724 | AY87: 14.418032 | AZ87: 1 | BA87: 1464 | BB87: 1464 | BC87: 1 | BD87: Clay Pit | BE87: 1771892252 | BF87: 1772135664 | BG87: 0.971543 | BH87: Clay | BI87: 2 | BJ87: 1771892252 | BK87: 200 | BL87: 5 | BM87: 2 | BN87: 1 | BO87: 0 | BP87: 0 | BQ87: 0.9569 | BR87: 0.9569
O88: 93 | P88: Batteries | Q88: https://api.resources-game.ch/resimg/res93.png | AW88: 4 | AX88: 50.077947 | AY88: 14.418281 | AZ88: 1 | BA88: 1416 | BB88: 1416 | BC88: 1 | BD88: Clay Pit | BE88: 1771892257 | BF88: 1772135664 | BG88: 0.971543 | BH88: Clay | BI88: 2 | BJ88: 1771892257 | BK88: 200 | BL88: 5 | BM88: 2 | BN88: 1 | BO88: 0 | BP88: 0 | BQ88: 0.9255 | BR88: 0.9255
O89: 95 | P89: Battery Factory | Q89: https://api.resources-game.ch/resimg/res95.png | AW89: 4 | AX89: 50.077458 | AY89: 14.418117 | AZ89: 1 | BA89: 1332 | BB89: 1332 | BC89: 1 | BD89: Clay Pit | BE89: 1771892277 | BF89: 1772135664 | BG89: 0.971543 | BH89: Clay | BI89: 2 | BJ89: 1771892277 | BK89: 200 | BL89: 5 | BM89: 2 | BN89: 1 | BO89: 0 | BP89: 0 | BQ89: 0.8706 | BR89: 0.8706
O90: 96 | P90: Watch Dogs | Q90: https://api.resources-game.ch/resimg/res96.png | AW90: 4 | AX90: 50.078461 | AY90: 14.418058 | AZ90: 1 | BA90: 1176 | BB90: 1176 | BC90: 1 | BD90: Clay Pit | BE90: 1771892463 | BF90: 1772135664 | BG90: 0.971543 | BH90: Clay | BI90: 2 | BJ90: 1771892463 | BK90: 200 | BL90: 5 | BM90: 2 | BN90: 1 | BO90: 0 | BP90: 0 | BQ90: 0.7686 | BR90: 0.7686
O91: 97 | P91: Training Camp | Q91: https://api.resources-game.ch/resimg/res97.png | AW91: 4 | AX91: 50.066684 | AY91: 14.429955 | AZ91: 1 | BA91: 1152 | BB91: 1152 | BC91: 1 | BD91: Clay Pit | BE91: 1771892927 | BF91: 1772135664 | BG91: 0.971543 | BH91: Clay | BI91: 2 | BJ91: 1771892927 | BK91: 200 | BL91: 5 | BM91: 2 | BN91: 1 | BO91: 0 | BP91: 0 | BQ91: 0.7529 | BR91: 0.7529
O92: 98 | P92: Security Staff | Q92: https://api.resources-game.ch/resimg/res98.png | AW92: 4 | AX92: 50.066252 | AY92: 14.430388 | AZ92: 1 | BA92: 1254 | BB92: 1254 | BC92: 1 | BD92: Clay Pit | BE92: 1771892933 | BF92: 1772135664 | BG92: 0.971543 | BH92: Clay | BI92: 2 | BJ92: 1771892933 | BK92: 200 | BL92: 5 | BM92: 2 | BN92: 1 | BO92: 0 | BP92: 0 | BQ92: 0.8196 | BR92: 0.8196
O93: 99 | P93: Elite Force | Q93: https://api.resources-game.ch/resimg/res99.png | AW93: 4 | AX93: 50.065847 | AY93: 14.430108 | AZ93: 1 | BA93: 1176 | BB93: 1176 | BC93: 1 | BD93: Clay Pit | BE93: 1771892938 | BF93: 1772135664 | BG93: 0.971543 | BH93: Clay | BI93: 2 | BJ93: 1771892938 | BK93: 200 | BL93: 5 | BM93: 2 | BN93: 1 | BO93: 0 | BP93: 0 | BQ93: 0.7686 | BR93: 0.7686
O94: 101 | P94: Arms Factory | Q94: https://api.resources-game.ch/resimg/res101.png | AW94: 4 | AX94: 50.065357 | AY94: 14.430437 | AZ94: 1 | BA94: 1218 | BB94: 1218 | BC94: 1 | BD94: Clay Pit | BE94: 1771892942 | BF94: 1772135664 | BG94: 0.971543 | BH94: Clay | BI94: 2 | BJ94: 1771892942 | BK94: 200 | BL94: 5 | BM94: 2 | BN94: 1 | BO94: 0 | BP94: 0 | BQ94: 0.7961 | BR94: 0.7961
O95: 102 | P95: Attack Dogs | Q95: https://api.resources-game.ch/resimg/res102.png | AW95: 4 | AX95: 50.065121 | AY95: 14.430198 | AZ95: 1 | BA95: 1074 | BB95: 1074 | BC95: 1 | BD95: Clay Pit | BE95: 1771892946 | BF95: 1772135664 | BG95: 0.971543 | BH95: Clay | BI95: 2 | BJ95: 1771892946 | BK95: 200 | BL95: 5 | BM95: 2 | BN95: 1 | BO95: 0 | BP95: 0 | BQ95: 0.702 | BR95: 0.702
O96: 103 | P96: Gangster | Q96: https://api.resources-game.ch/resimg/res103.png | AW96: 4 | AX96: 50.047772 | AY96: 14.453513 | AZ96: 1 | BA96: 1206 | BB96: 1206 | BC96: 1 | BD96: Clay Pit | BE96: 1771893801 | BF96: 1772135664 | BG96: 0.971543 | BH96: Clay | BI96: 2 | BJ96: 1771893801 | BK96: 200 | BL96: 5 | BM96: 2 | BN96: 1 | BO96: 0 | BP96: 0 | BQ96: 0.7882 | BR96: 0.7882
... O114: 161 | P114: Wage Subsidy | Q114: https://api.resources-game.ch/resimg/res161.png | AW114: 4 | AX114: 50.08252 | AY114: 14.43335 | AZ114: 1 | BA114: 1374 | BB114: 1374 | BC114: 1 | BD114: Clay Pit | BE114: 1772019693 | BF114: 1772135664 | BG114: 0.971543 | BH114: Clay | BI114: 2 | BJ114: 1772019693 | BK114: 200 | BL114: 5 | BM114: 2 | BN114: 1 | BO114: 0 | BP114: 0 | BQ114: 0.898 | BR114: 0.898
AW115: 4 | AX115: 50.084168 | AY115: 14.4338 | AZ115: 1 | BA115: 1530 | BB115: 1530 | BC115: 1 | BD115: Clay Pit | BE115: 1772019811 | BF115: 1772135664 | BG115: 0.971543 | BH115: Clay | BI115: 2 | BJ115: 1772019811 | BK115: 200 | BL115: 5 | BM115: 2 | BN115: 1 | BO115: 0 | BP115: 0 | BQ115: 1 | BR115: 1
AW116: 4 | AX116: 50.028159 | AY116: 15.205324 | AZ116: 1 | BA116: 1176 | BB116: 1176 | BC116: 1 | BD116: Clay Pit | BE116: 1772023234 | BF116: 1772135664 | BG116: 0.971543 | BH116: Clay | BI116: 2 | BJ116: 1772023234 | BK116: 200 | BL116: 5 | BM116: 2 | BN116: 1 | BO116: 0 | BP116: 0 | BQ116: 0.7686 | BR116: 0.7686
AW117: 4 | AX117: 50.027638 | AY117: 15.205318 | AZ117: 1 | BA117: 1188 | BB117: 1188 | BC117: 1 | BD117: Clay Pit | BE117: 1772023245 | BF117: 1772135664 | BG117: 0.971543 | BH117: Clay | BI117: 2 | BJ117: 1772023245 | BK117: 200 | BL117: 5 | BM117: 2 | BN117: 1 | BO117: 0 | BP117: 0 | BQ117: 0.7765 | BR117: 0.7765
AW118: 4 | AX118: 50.010013 | AY118: 15.269925 | AZ118: 1 | BA118: 1386 | BB118: 1386 | BC118: 1 | BD118: Clay Pit | BE118: 1772023468 | BF118: 1772135664 | BG118: 0.971543 | BH118: Clay | BI118: 2 | BJ118: 1772023468 | BK118: 200 | BL118: 5 | BM118: 2 | BN118: 1 | BO118: 0 | BP118: 0 | BQ118: 0.9059 | BR118: 0.9059
AW119: 4 | AX119: 50.010428 | AY119: 15.28549 | AZ119: 1 | BA119: 1320 | BB119: 1320 | BC119: 1 | BD119: Clay Pit | BE119: 1772023500 | BF119: 1772135664 | BG119: 0.971543 | BH119: Clay | BI119: 2 | BJ119: 1772023500 | BK119: 200 | BL119: 5 | BM119: 2 | BN119: 1 | BO119: 0 | BP119: 0 | BQ119: 0.8627 | BR119: 0.8627
AW120: 4 | AX120: 50.011315 | AY120: 15.303448 | AZ120: 1 | BA120: 1188 | BB120: 1188 | BC120: 1 | BD120: Clay Pit | BE120: 1772023533 | BF120: 1772135664 | BG120: 0.971543 | BH120: Clay | BI120: 2 | BJ120: 1772023533 | BK120: 200 | BL120: 5 | BM120: 2 | BN120: 1 | BO120: 0 | BP120: 0 | BQ120: 0.7765 | BR120: 0.7765
...

Sheet STATIC DATA
B1: Resource | C1: Level | D1: Map distribution (%) | E1: m3/h (Q100%) | F1: €/h (Q100%) | G1: Base cost | K1: Number of hours | L1: Condition | M1: Production
B2: Limestone | C2: 2 | D2: 96 | E2: 510 | F2: 253470 | G2: 1000000 | K2: 1 | L2: 1 | M2: =1530*L2 -> 1530
B3: Clay | C3: 1 | D3: 95 | E3: 1530 | F3: 540090 | G3: 2500000 | K3: =K2+1 -> 2 | L3: =L2-(0.04/24)*L2 -> 0.99833333 | M3: =1530*L3 -> 1527.45
B4: Gravel | C4: 1 | D4: 95 | E4: 542 | F4: 256908 | G4: 5000000 | K4: =K3+1 -> 3 | L4: =L3-(0.04/24)*L3 -> 0.99666944 | M4: =1530*L4 -> 1524.9042
B5: Coal | C5: 4 | D5: 52 | E5: 510 | F5: 1250520 | G5: 50000000 | K5: =K4+1 -> 4 | L5: =L4-(0.04/24)*L4 -> 0.99500833 | M5: =1530*L5 -> 1522.3627
B6: Iron ore | C6: 4 | D6: 48 | E6: 382.5 | F6: 556956 | G6: 10000000 | K6: =K5+1 -> 5 | L6: =L5-(0.04/24)*L5 -> 0.99334998 | M6: =1530*L6 -> 1519.8255
B7: Bauxite | C7: 11 | D7: 43 | E7: 306 | F7: 673506 | G7: 100000000 | K7: =K6+1 -> 6 | L7: =L6-(0.04/24)*L6 -> 0.9916944 | M7: =1530*L7 -> 1517.2924
B8: Ilmenite | C8: 20 | D8: 42 | E8: 280.5 | F8: 86520 | G8: 200000000 | K8: =K7+1 -> 7 | L8: =L7-(0.04/24)*L7 -> 0.99004157 | M8: =1530*L8 -> 1514.7636
B9: Chalcopyrite | C9: 9 | D9: 39 | E9: 408 | F9: 552432 | G9: 400000000 | K9: =K8+1 -> 8 | L9: =L8-(0.04/24)*L8 -> 0.9883915 | M9: =1530*L9 -> 1512.239
B10: Quartz sand | C10: 7 | D10: 35 | E10: 765 | F10: 276165 | G10: 600000000 | K10: =K9+1 -> 9 | L10: =L9-(0.04/24)*L9 -> 0.98674419 | M10: =1530*L10 -> 1509.7186
B11: Lithium ore | C11: 15 | D11: 30 | E11: 2040 | F11: 1026120 | G11: 800000000 | K11: =K10+1 -> 10 | L11: =L10-(0.04/24)*L10 -> 0.98509961 | M11: =1530*L11 -> 1507.2024
B12: Crude oil | C12: 5 | D12: 22 | E12: 306 | F12: 773874 | G12: 1000000000 | K12: =K11+1 -> 11 | L12: =L11-(0.04/24)*L11 -> 0.98345778 | M12: =1530*L12 -> 1504.6904
B13: Silver ore | C13: 33 | D13: 17 | E13: 637.5 | F13: 914732 | G13: 1250000000 | K13: =K12+1 -> 12 | L13: =L12-(0.04/24)*L12 -> 0.98181868 | M13: =1530*L13 -> 1502.1826
B14: Gold ore | C14: 38 | D14: 5 | E14: 2040 | F14: 1970640 | G14: 1500000000 | K14: =K13+1 -> 13 | L14: =L13-(0.04/24)*L13 -> 0.98018232 | M14: =1530*L14 -> 1499.6789
B15: Rough diamonds | C15: 48 | D15: 3 | E15: 1275 | F15: 4300575 | G15: 2000000000 | K15: =K14+1 -> 14 | L15: =L14-(0.04/24)*L14 -> 0.97854868 | M15: =1530*L15 -> 1497.1795
K16: =K15+1 -> 15 | L16: =L15-(0.04/24)*L15 -> 0.97691777 | M16: =1530*L16 -> 1494.6842
K17: =K16+1 -> 16 | L17: =L16-(0.04/24)*L16 -> 0.97528957 | M17: =1530*L17 -> 1492.193
B18: ROI = (zisk-náklady)/náklady*100 | K18: =K17+1 -> 17 | L18: =L17-(0.04/24)*L17 -> 0.97366409 | M18: =1530*L18 -> 1489.7061
K19: =K18+1 -> 18 | L19: =L18-(0.04/24)*L18 -> 0.97204131 | M19: =1530*L19 -> 1487.2232
B20: Formula for Mine Cost: [Base Cost] * (1 + [Total number of mines]/50) | K20: =K19+1 -> 19 | L20: =L19-(0.04/24)*L19 -> 0.97042125 | M20: =1530*L20 -> 1484.7445
K21: =K20+1 -> 20 | L21: =L20-(0.04/24)*L20 -> 0.96880388 | M21: =1530*L21 -> 1482.2699
B22: Graf ROI 20 dní pro všechny resources | K22: =K21+1 -> 21 | L22: =L21-(0.04/24)*L21 -> 0.9671892 | M22: =1530*L22 -> 1479.7995
K23: =K22+1 -> 22 | L23: =L22-(0.04/24)*L22 -> 0.96557722 | M23: =1530*L23 -> 1477.3331
B24: Každý den condition ztratí 4%. Pod 20% se důl zhroutí. | K24: =K23+1 -> 23 | L24: =L23-(0.04/24)*L23 -> 0.96396793 | M24: =1530*L24 -> 1474.8709
K25: =K24+1 -> 24 | L25: =L24-(0.04/24)*L24 -> 0.96236131 | M25: =1530*L25 -> 1472.4128
B26: Experts can be hired to repair a mine individually, or a team of experts can be hired to repair every mine for 3x the normal price per mine.
K27: Excel: =EXP(-0.04/24*A2)
B28: Diferenciální rovnice
K29: Produkce: =1530*EXP(-0.04/24*A2)
B32: Ceny warehouse updatů
B33: Mise?
B34: Skóre - jak se počítá?

Sheet README
B2: Proudly serving the Resources Game community since 2015
B3: Boy what a time it has been. I've been basically inactive since early 2017. I lost my mines sometime mid 2018. Rest in peace.
B4: As of September 2019, I'm still happy to provide support for this spreadsheet. Feel free to reach out with comments or concerns.
B5: Likewise with the accompanying game guide. It's so cool to see the game community still active and I wish I hadn't lost my mines.
B6: You guys are a great community and I'm so happy to have been able to provide this resource (pun intended).
B8: For all current and future versions of this sheet, unless otherwise noted, you can update by making a new copy of the sheet,
C9: then copying your entire UserBuildings tab from your old sheet and replacing the data on the new sheet.
B11: 25 Nov: It is important for those of you who will be using the API to read the API instructions to avoid excessive use of your api data.
C12: Added API support for entire User Buildings tab.
C13: DO NOT copy and paste your User Buildings tab from a previous version, this update invovles heavy User Buildings tab updates.
C14: For now, API settings (On/Off switch and API Key input) are on the API Raw page. However, I will move it to the UserBuildings page if enough people express support for that idea.
B16: Below you will find helpful instructions, urls, and credits.
B18: This sheet is 100% free for personal use.
B19: I kindly ask that you do not redistribute this sheet, but feel free to direct people to this one.
B20: If you have suggestions for improvement, I welcome your feedback.
B22: Acknowledgements:
C23: Individual value, Profit Ratio column, Actual Profit column, Adj Value columns, and "All" lines on the Supply chain tab were created by Ghukek.
C24: Factory ROI, Mine ROI, Mine Accident, TU5.05 Cost, Headquarters, and Recycling/Units tabs created by Ghukek.
C25: All other portions of this sheet were copied from a sheet created by Koen Rijnsent, IGN cq27.
C26: This sheet is related to the Android game "Resources Game," and I claim no ownership of or afiliation with the game.
C27: Special mention to user "Apoc" for contributions to the "Profit over time" table in the Factory ROI page
C28: Special mention to user "Plan-B" for helping setup the sheet to auto-update the Markets tab.
C29: Special mention to user "Fraggle Rock1" for reverse-engineering the tech center scan accuracy formula.
C30: Special mention to user "Redeye Inc" for designing the "HQ Progress Tracker" and "Recycling Calculator" tables along with the recycling table in the static tab.
C31: Special mention to users "Redeye Inc" and "mkb1" for their joint contributions to the TU5.05 calculator table in columns J-N of the TU sheet.
C32: Special mention to user "Ar0nius" for writing the "how often should I repair my mines" table in the Mine ROI tab.
C33: Thanks to user Defenestration for minor bug report.
C34: Thanks to user [HU3] LSV CORP. for PT-BR translation.
... C39: Update 2.5.2 brought to you by Silverskin GmbH, feel free to drop him a donation for his efforts
B41: To make a copy of this sheet.
C42: If on desktop (ideal) go to "file," "make a copy."
C43: If on mobile, click the three verticle dots in the google sheets app. "Share & Export," "Make a Copy."
B45: Auto Updating Markets:
B46: To make sure your sheet auto-updates more often than once an hour, follow these instructions. (Thanks to user Plan-B)
C47: Once sheets is open go to tools / script editor.
C48: In the new page that opens, go to Resources / Current project triggers
C49: Add new trigger with settings: Get data, Time-Driven, Minutes Timer, Every 15 minutes. [Or whatever time you chose.]
C50: Click save and accept access prompt.
C51: Then go to file / save and save the whole script.
C52: These instructions apply to the desktop browser version.
B54: Number Formatting:
B55: If you use the x.xxx.xxx,xx format (that is the European number format) rather than the American format.
C56: You can just use the x,xxx,xxx.xx if you want, but the following is instructions to change to your preferred format.
C57: First, go to "file" "spreadsheet settings" and change the "locale" to whatever country you're from.
C58: All numbers and formulas will automatically convert. Except for the base market pull formula.
C59: This is because the script that runs that is separate from the spreadsheet, and will continue pushing the American formula.
C60: Go to "tools" "script editor." | J60: (---------V---------)
C61: Line 4 will read = var cellFunction1 = '=IMPORTXML("http://www.resources-game.ch/exchange/kurseliste.xml?' + queryString + '","//RESOURCES_RATES/ITEM")';
C62: Change the comma between [queryString + "] and ["//RES] to a semicolon. (change , to ;) (Make sure it's ; not :) The (---------V---------) is pointing directly to it for your convenience.
C63: Save and run the script.
B65: API Instructions:
C66: The sheet automatically updates hourly I believe, I'm currently testing. To prevent unnecessary API Credit waste,
D67: make sure to keep User Buildings tab C2 at 0 when not at use.
C68: To minimise credit usage, copy the yellow cells and right click on the corresponding blue cells and select "Paste Special" -> "Paste Values Only".
C69: This will allow you to retain data after you turn off the API data.
C70: If you want to remove a specific feature from the API Raw page in order to preserve credits:
D71: Go the the API Raw sheet, which is hidden by default.
D72: Find the name of the table you wish to remove.
D73: Edit the cell two blocks below the bold title by removing the equals (=) sign from the page.
D74: To restore, just put the equals (=) sign back.
B76: Translations:
C77: All Readme translation tabs are hidden by default. View them by "View" -> "Hidden Sheets" on desktop and by bringing up the four horizontal bar menu in the bottom left corner on mobile.
C78: PT-BR: Readme Translation and Translation table: Credit: [HU3] LSV CORP.
B80: Haulage Firm ROI:
C81: For the ROI on haulage firm, I estimate approximately your daily profit as your bm turnaround. This means that 1% of your daily profit is your savings per haulage level.
C82: This will be higher if you use the market a lot and lower if you make a point to be self sufficient.
C83: Use your discretion to read the estimation and draw your own conclusions.
B85: If you are experiencing problems with the sheet, submit a support ticket by going to share settings.
B86: Add legowiebe@gmail.com with comment permissions.
B87: In the notes section, explain your issue.
B89: My Current Project:
C90: I'm designing and 3D printing miniature warships and planes for wargaming.
C91: Website: | D91: https://www.ghukek.com/
C92: Instagram: | D92: =HYPERLINK("https://www.instagram.com/ghukekminiatures/") -> https://www.instagram.com/ghukekminiatures/
C93: Facebook: | D93: =HYPERLINK("https://www.facebook.com/GhukekMiniatures/") -> https://www.facebook.com/GhukekMiniatures/
C94: Shapeways: | D94: =HYPERLINK("https://www.cgtrader.com/ghukek") -> https://www.cgtrader.com/ghukek
C95: CGTrader: | D95: =HYPERLINK("https://www.shapeways.com/shops/ghukek-s-miniatures") -> https://www.shapeways.com/shops/ghukek-s-miniatures
B97: Current boxes in the game
B98: =HYPERLINK("http://appweb.resources-game.ch/stats/getBoxesStat_hp.php","http://appweb.resources-game.ch/stats/getBoxesStat_hp.php") -> http://appweb.resources-game.ch/stats/getBoxesStat_hp.php
B100: Top 20 miners
B101: =HYPERLINK("http://appweb.resources-game.ch/stats/masterminer_hp.php","http://appweb.resources-game.ch/stats/masterminer_hp.php") -> http://appweb.resources-game.ch/stats/masterminer_hp.php
B103: In-game data
B104: =HYPERLINK("http://ssl.resources-game.ch/","http://ssl.resources-game.ch/") -> http://ssl.resources-game.ch/
B106: Game guide
B107: =HYPERLINK("http://tinyurl.com/npa82ky","http://tinyurl.com/npa82ky") -> http://tinyurl.com/npa82ky
B109: Loan record spreadsheet
B110: =HYPERLINK("http://tinyurl.com/usabanking","http://tinyurl.com/usabanking") -> http://tinyurl.com/usabanking
B112: Player Fraggle Rock1's original spreadsheet for scan accuracy.
B113: =HYPERLINK("https://docs.google.com/spreadsheets/d/1Lsno9_Jpwv4JTD14339H-yFaoUV7Kaev_FImGg6XpCM/edit?ts=566f2a7a#gid=0","https://docs.google.com/spreadsheets/d/1Lsno9_Jpwv4JTD14339H-yFaoUV7Kaev_FImGg6XpCM/edit?ts=566f2a7a#gid=0") -> https://docs.google.com/spreadsheets/d/1Lsno9_Jpwv4JTD14339H-yFaoUV7Kaev_FImGg6XpCM/edit?ts=566f2a7a#gid=0
B115: Sheet descriptions.
C116: Supply Chain: | D116: This cumulates all of your production into neat totals.
D117: It also shows your production shortages.
D118: Adj value is based on how much of that resource you will need to feed into factories
C119: User Buildings: | D119: This is where you input your data.
D120: The blue cells are user input.
D121: The orange cells are auto-filled if you use the API functionality. The sheet will default to them if in use, otherwise it will use the manual entry data. See the API Instructions above for details.
D122: "Using?" Column in factories is a "Yes" or "No" answer. It allows you to see your profit totals if you chose not to run certain factories.
D123: Maintenance cost section. In the second row, chose which type you use.
C124: Factory ROI | D124: This is where factory upgrade prices are calculated.
D125: Days to ROI is how many days until the increase in production will pay off the cost of the upgrade.
...

Sheet Mine ROI
G1: User Input Column
B2: Assuming constant 100% condition. Not factoring in maintenance costs. #=Days until mine pays itself off. | J2: Scan Cost: | K2: =ROUND((10000*2.4^UserBuildings!S5)*(1+UserBuildings!D20/1000),-3) -> 136127000
G3: ROI @ XX% | H3: Hrly Prod @ XX% | J3: Scan costs assume avg of 4 scans.
B4: Mine type | C4: Hrly Production @ 100% | D4: ROI @ 50% | E4: ROI @ 75 | F4: ROI @ 100% | G4: 20 | H4: =$G$4 -> 20
B5: Clay pit | C5: =I5*'Supply Chain'!E33 -> 535500 | D5: =($J5*(1+$K5/50)+$K$2*4)/($C5*0.5)/24 -> 88.460629 | E5: =($J5*(1+$K5/50)+$K$2*4)/($C5*0.75)/24 -> 58.973752 | F5: =($J5*(1+$K5/50)+$K$2*4)/$C5/24 -> 44.230314 | G5: =(J5*(1+K5/50)+$K$2*4)/(C5*($G$4/100))/24 -> 221.15157 | H5: =C5*($G$4/100) -> 107100 | I5: =VLOOKUP(B5,Static!$R$4:$W$17,4,FALSE) -> 1530 | J5: =VLOOKUP(B5,Static!$R$4:$W$17,6,FALSE) -> 1000000 | K5: =UserBuildings!$D$20 -> 1147
B6: Limestone quarry | C6: =I6*'Supply Chain'!E34 -> 261120 | D6: =($J6*(1+$K6/50)+$K$2*4)/($C6*0.5)/24 -> 192.87365 | E6: =($J6*(1+$K6/50)+$K$2*4)/($C6*0.75)/24 -> 128.58243 | F6: =($J6*(1+$K6/50)+$K$2*4)/$C6/24 -> 96.436823 | G6: =(J6*(1+K6/50)+$K$2*4)/(C6*($G$4/100))/24 -> 482.18412 | H6: =C6*($G$4/100) -> 52224 | I6: =VLOOKUP(B6,Static!$R$4:$W$17,4,FALSE) -> 510 | J6: =VLOOKUP(B6,Static!$R$4:$W$17,6,FALSE) -> 2500000 | K6: =UserBuildings!$D$20 -> 1147
B7: Gravel pit | C7: =I7*'Supply Chain'!E35 -> 260160 | D7: =($J7*(1+$K7/50)+$K$2*4)/($C7*0.5)/24 -> 212.75625 | E7: =($J7*(1+$K7/50)+$K$2*4)/($C7*0.75)/24 -> 141.8375 | F7: =($J7*(1+$K7/50)+$K$2*4)/$C7/24 -> 106.37813 | G7: =(J7*(1+K7/50)+$K$2*4)/(C7*($G$4/100))/24 -> 531.89063 | H7: =C7*($G$4/100) -> 52032 | I7: =VLOOKUP(B7,Static!$R$4:$W$17,4,FALSE) -> 542 | J7: =VLOOKUP(B7,Static!$R$4:$W$17,6,FALSE) -> 5000000 | K7: =UserBuildings!$D$20 -> 1147
B8: Coal mine | C8: =I8*'Supply Chain'!E36 -> 1232160 | D8: =($J8*(1+$K8/50)+$K$2*4)/($C8*0.5)/24 -> 117.78151 | E8: =($J8*(1+$K8/50)+$K$2*4)/($C8*0.75)/24 -> 78.521007 | F8: =($J8*(1+$K8/50)+$K$2*4)/$C8/24 -> 58.890756 | G8: =(J8*(1+K8/50)+$K$2*4)/(C8*($G$4/100))/24 -> 294.45378 | H8: =C8*($G$4/100) -> 246432 | I8: =VLOOKUP(B8,Static!$R$4:$W$17,4,FALSE) -> 510 | J8: =VLOOKUP(B8,Static!$R$4:$W$17,6,FALSE) -> 50000000 | K8: =UserBuildings!$D$20 -> 1147
B9: Iron ore mine | C9: =I9*'Supply Chain'!E37 -> 526320 | D9: =($J9*(1+$K9/50)+$K$2*4)/($C9*0.5)/24 -> 124.11777 | E9: =($J9*(1+$K9/50)+$K$2*4)/($C9*0.75)/24 -> 82.745182 | F9: =($J9*(1+$K9/50)+$K$2*4)/$C9/24 -> 62.058887 | G9: =(J9*(1+K9/50)+$K$2*4)/(C9*($G$4/100))/24 -> 310.29443 | H9: =C9*($G$4/100) -> 105264 | I9: =VLOOKUP(B9,Static!$R$4:$W$17,4,FALSE) -> 382.5 | J9: =VLOOKUP(B9,Static!$R$4:$W$17,6,FALSE) -> 10000000 | K9: =UserBuildings!$D$20 -> 1147
B10: Derrick | C10: =I10*'Supply Chain'!E38 -> 788868 | D10: =($J10*(1+$K10/50)+$K$2*4)/($C10*0.5)/24 -> 310.41399 | E10: =($J10*(1+$K10/50)+$K$2*4)/($C10*0.75)/24 -> 206.94266 | F10: =($J10*(1+$K10/50)+$K$2*4)/$C10/24 -> 155.207 | G10: =(J10*(1+K10/50)+$K$2*4)/(C10*($G$4/100))/24 -> 776.03499 | H10: =C10*($G$4/100) -> 157773.6 | I10: =VLOOKUP(B10,Static!$R$4:$W$17,4,FALSE) -> 306 | J10: =VLOOKUP(B10,Static!$R$4:$W$17,6,FALSE) -> 100000000 | K10: =UserBuildings!$D$20 -> 1147
B11: Sand mine | C11: =I11*'Supply Chain'!E39 -> 273105 | D11: =($J11*(1+$K11/50)+$K$2*4)/($C11*0.5)/24 -> 1627.1239 | E11: =($J11*(1+$K11/50)+$K$2*4)/($C11*0.75)/24 -> 1084.7493 | F11: =($J11*(1+$K11/50)+$K$2*4)/$C11/24 -> 813.56194 | G11: =(J11*(1+K11/50)+$K$2*4)/(C11*($G$4/100))/24 -> 4067.8097 | H11: =C11*($G$4/100) -> 54621 | I11: =VLOOKUP(B11,Static!$R$4:$W$17,4,FALSE) -> 765 | J11: =VLOOKUP(B11,Static!$R$4:$W$17,6,FALSE) -> 200000000 | K11: =UserBuildings!$D$20 -> 1147
B12: Copper mine | C12: =I12*'Supply Chain'!E40 -> 553656 | D12: =($J12*(1+$K12/50)+$K$2*4)/($C12*0.5)/24 -> 1523.2846 | E12: =($J12*(1+$K12/50)+$K$2*4)/($C12*0.75)/24 -> 1015.5231 | F12: =($J12*(1+$K12/50)+$K$2*4)/$C12/24 -> 761.64231 | G12: =(J12*(1+K12/50)+$K$2*4)/(C12*($G$4/100))/24 -> 3808.2115 | H12: =C12*($G$4/100) -> 110731.2 | I12: =VLOOKUP(B12,Static!$R$4:$W$17,4,FALSE) -> 408 | J12: =VLOOKUP(B12,Static!$R$4:$W$17,6,FALSE) -> 400000000 | K12: =UserBuildings!$D$20 -> 1147
B13: Bauxite mine | C13: =I13*'Supply Chain'!E41 -> 627300 | D13: =($J13*(1+$K13/50)+$K$2*4)/($C13*0.5)/24 -> 1980.5128 | E13: =($J13*(1+$K13/50)+$K$2*4)/($C13*0.75)/24 -> 1320.3419 | F13: =($J13*(1+$K13/50)+$K$2*4)/$C13/24 -> 990.25639 | G13: =(J13*(1+K13/50)+$K$2*4)/(C13*($G$4/100))/24 -> 4951.2819 | H13: =C13*($G$4/100) -> 125460 | I13: =VLOOKUP(B13,Static!$R$4:$W$17,4,FALSE) -> 306 | J13: =VLOOKUP(B13,Static!$R$4:$W$17,6,FALSE) -> 600000000 | K13: =UserBuildings!$D$20 -> 1147
B14: Lithium ore mine | C14: =I14*'Supply Chain'!E42 -> 993480 | D14: =($J14*(1+$K14/50)+$K$2*4)/($C14*0.5)/24 -> 1652.1477 | E14: =($J14*(1+$K14/50)+$K$2*4)/($C14*0.75)/24 -> 1101.4318 | F14: =($J14*(1+$K14/50)+$K$2*4)/$C14/24 -> 826.07383 | G14: =(J14*(1+K14/50)+$K$2*4)/(C14*($G$4/100))/24 -> 4130.3692 | H14: =C14*($G$4/100) -> 198696 | I14: =VLOOKUP(B14,Static!$R$4:$W$17,4,FALSE) -> 2040 | J14: =VLOOKUP(B14,Static!$R$4:$W$17,6,FALSE) -> 800000000 | K14: =UserBuildings!$D$20 -> 1147
B15: Ilmenite mine | C15: =I15*'Supply Chain'!E43 -> 84150 | D15: =($J15*(1+$K15/50)+$K$2*4)/($C15*0.5)/24 -> 24246.888 | E15: =($J15*(1+$K15/50)+$K$2*4)/($C15*0.75)/24 -> 16164.592 | F15: =($J15*(1+$K15/50)+$K$2*4)/$C15/24 -> 12123.444 | G15: =(J15*(1+K15/50)+$K$2*4)/(C15*($G$4/100))/24 -> 60617.221 | H15: =C15*($G$4/100) -> 16830 | I15: =VLOOKUP(B15,Static!$R$4:$W$17,4,FALSE) -> 280.5 | J15: =VLOOKUP(B15,Static!$R$4:$W$17,6,FALSE) -> 1000000000 | K15: =UserBuildings!$D$20 -> 1147
B16: Silver mine | C16: =I16*'Supply Chain'!E44 -> 963262.5 | D16: =($J16*(1+$K16/50)+$K$2*4)/($C16*0.5)/24 -> 2635.9644 | E16: =($J16*(1+$K16/50)+$K$2*4)/($C16*0.75)/24 -> 1757.3096 | F16: =($J16*(1+$K16/50)+$K$2*4)/$C16/24 -> 1317.9822 | G16: =(J16*(1+K16/50)+$K$2*4)/(C16*($G$4/100))/24 -> 6589.911 | H16: =C16*($G$4/100) -> 192652.5 | I16: =VLOOKUP(B16,Static!$R$4:$W$17,4,FALSE) -> 637.5 | J16: =VLOOKUP(B16,Static!$R$4:$W$17,6,FALSE) -> 1250000000 | K16: =UserBuildings!$D$20 -> 1147
... B18: Diamond mine | C18: =I18*'Supply Chain'!E46 -> 4364325 | D18: =($J18*(1+$K18/50)+$K$2*4)/($C18*0.5)/24 -> 924.62767 | E18: =($J18*(1+$K18/50)+$K$2*4)/($C18*0.75)/24 -> 616.41845 | F18: =($J18*(1+$K18/50)+$K$2*4)/$C18/24 -> 462.31384 | G18: =(J18*(1+K18/50)+$K$2*4)/(C18*($G$4/100))/24 -> 2311.5692 | H18: =C18*($G$4/100) -> 872865 | I18: =VLOOKUP(B18,Static!$R$4:$W$17,4,FALSE) -> 1275 | J18: =VLOOKUP(B18,Static!$R$4:$W$17,6,FALSE) -> 2000000000 | K18: =UserBuildings!$D$20 -> 1147
B20: Assuming lowest cost 0-TU4 combo. Not including original mine cost
B21: Mine type | C21: Hrly Prod @ 505% | D21: Base 50 | E21: Base 75 | F21: Base 100 | G21: =$G$4 -> 20 | H21: =$G$4 -> 20
B22: Clay pit | C22: =I5*5.05*'Supply Chain'!$E33 -> 2704275 | D22: ='TU5.05'!$G$3/(C22*0.5)/24 -> 451.59005 | E22: ='TU5.05'!$G$3/(C22*0.75)/24 -> 301.06003 | F22: ='TU5.05'!$G$3/C22/24 -> 225.79502 | G22: ='TU5.05'!$G$3/(C22*($G$4/100))/24 -> 1128.9751 | H22: =(I5*($G$4/100))*5.05*'Supply Chain'!$E33 -> 540855
B23: Limestone quarry | C23: =I6*5.05*'Supply Chain'!$E34 -> 1318656 | D23: ='TU5.05'!$G$3/(C23*0.5)/24 -> 926.1124 | E23: ='TU5.05'!$G$3/(C23*0.75)/24 -> 617.40827 | F23: ='TU5.05'!$G$3/C23/24 -> 463.0562 | G23: ='TU5.05'!$G$3/(C23*($G$4/100))/24 -> 2315.281 | H23: =(I6*($G$4/100))*5.05*'Supply Chain'!$E34 -> 263731.2
B24: Gravel pit | C24: =I7*5.05*'Supply Chain'!$E35 -> 1313808 | D24: ='TU5.05'!$G$3/(C24*0.5)/24 -> 929.52979 | E24: ='TU5.05'!$G$3/(C24*0.75)/24 -> 619.68653 | F24: ='TU5.05'!$G$3/C24/24 -> 464.76489 | G24: ='TU5.05'!$G$3/(C24*($G$4/100))/24 -> 2323.8245 | H24: =(I7*($G$4/100))*5.05*'Supply Chain'!$E35 -> 262761.6
B25: Coal mine | C25: =I8*5.05*'Supply Chain'!$E36 -> 6222408 | D25: ='TU5.05'!$G$3/(C25*0.5)/24 -> 196.26223 | E25: ='TU5.05'!$G$3/(C25*0.75)/24 -> 130.84149 | F25: ='TU5.05'!$G$3/C25/24 -> 98.131115 | G25: ='TU5.05'!$G$3/(C25*($G$4/100))/24 -> 490.65558 | H25: =(I8*($G$4/100))*5.05*'Supply Chain'!$E36 -> 1244481.6
B26: Iron ore mine | C26: =I9*5.05*'Supply Chain'!$E37 -> 2657916 | D26: ='TU5.05'!$G$3/(C26*0.5)/24 -> 459.46662 | E26: ='TU5.05'!$G$3/(C26*0.75)/24 -> 306.31108 | F26: ='TU5.05'!$G$3/C26/24 -> 229.73331 | G26: ='TU5.05'!$G$3/(C26*($G$4/100))/24 -> 1148.6665 | H26: =(I9*($G$4/100))*5.05*'Supply Chain'!$E37 -> 531583.2
B27: Derrick | C27: =I10*5.05*'Supply Chain'!$E38 -> 3983783.4 | D27: ='TU5.05'!$G$3/(C27*0.5)/24 -> 306.54871 | E27: ='TU5.05'!$G$3/(C27*0.75)/24 -> 204.36581 | F27: ='TU5.05'!$G$3/C27/24 -> 153.27436 | G27: ='TU5.05'!$G$3/(C27*($G$4/100))/24 -> 766.37178 | H27: =(I10*($G$4/100))*5.05*'Supply Chain'!$E38 -> 796756.68
B28: Sand mine | C28: =I11*5.05*'Supply Chain'!$E39 -> 1379180.2 | D28: ='TU5.05'!$G$3/(C28*0.5)/24 -> 885.47068 | E28: ='TU5.05'!$G$3/(C28*0.75)/24 -> 590.31379 | F28: ='TU5.05'!$G$3/C28/24 -> 442.73534 | G28: ='TU5.05'!$G$3/(C28*($G$4/100))/24 -> 2213.6767 | H28: =(I11*($G$4/100))*5.05*'Supply Chain'!$E39 -> 275836.05
B29: Copper mine | C29: =I12*5.05*'Supply Chain'!$E40 -> 2795962.8 | D29: ='TU5.05'!$G$3/(C29*0.5)/24 -> 436.78109 | E29: ='TU5.05'!$G$3/(C29*0.75)/24 -> 291.18739 | F29: ='TU5.05'!$G$3/C29/24 -> 218.39054 | G29: ='TU5.05'!$G$3/(C29*($G$4/100))/24 -> 1091.9527 | H29: =(I12*($G$4/100))*5.05*'Supply Chain'!$E40 -> 559192.56
B30: Bauxite mine | C30: =I13*5.05*'Supply Chain'!$E41 -> 3167865 | D30: ='TU5.05'!$G$3/(C30*0.5)/24 -> 385.5037 | E30: ='TU5.05'!$G$3/(C30*0.75)/24 -> 257.00247 | F30: ='TU5.05'!$G$3/C30/24 -> 192.75185 | G30: ='TU5.05'!$G$3/(C30*($G$4/100))/24 -> 963.75924 | H30: =(I13*($G$4/100))*5.05*'Supply Chain'!$E41 -> 633573
B31: Lithium ore mine | C31: =I14*5.05*'Supply Chain'!$E42 -> 5017074 | D31: ='TU5.05'!$G$3/(C31*0.5)/24 -> 243.41353 | E31: ='TU5.05'!$G$3/(C31*0.75)/24 -> 162.27568 | F31: ='TU5.05'!$G$3/C31/24 -> 121.70676 | G31: ='TU5.05'!$G$3/(C31*($G$4/100))/24 -> 608.53381 | H31: =(I14*($G$4/100))*5.05*'Supply Chain'!$E42 -> 1003414.8
B32: Ilmenite mine | C32: =I15*5.05*'Supply Chain'!$E43 -> 424957.5 | D32: ='TU5.05'!$G$3/(C32*0.5)/24 -> 2873.7548 | E32: ='TU5.05'!$G$3/(C32*0.75)/24 -> 1915.8366 | F32: ='TU5.05'!$G$3/C32/24 -> 1436.8774 | G32: ='TU5.05'!$G$3/(C32*($G$4/100))/24 -> 7184.3871 | H32: =(I15*($G$4/100))*5.05*'Supply Chain'!$E43 -> 84991.5
B33: Silver mine | C33: =I16*5.05*'Supply Chain'!$E44 -> 4864475.6 | D33: ='TU5.05'!$G$3/(C33*0.5)/24 -> 251.0494 | E33: ='TU5.05'!$G$3/(C33*0.75)/24 -> 167.36626 | F33: ='TU5.05'!$G$3/C33/24 -> 125.5247 | G33: ='TU5.05'!$G$3/(C33*($G$4/100))/24 -> 627.62349 | H33: =(I16*($G$4/100))*5.05*'Supply Chain'!$E44 -> 972895.12
... B35: Diamond mine | C35: =I18*5.05*'Supply Chain'!$E46 -> 22039841 | D35: ='TU5.05'!$G$3/(C35*0.5)/24 -> 55.409822 | E35: ='TU5.05'!$G$3/(C35*0.75)/24 -> 36.939881 | F35: ='TU5.05'!$G$3/C35/24 -> 27.704911 | G35: ='TU5.05'!$G$3/(C35*($G$4/100))/24 -> 138.52455 | H35: =(I18*($G$4/100))*5.05*'Supply Chain'!$E46 -> 4407968.2
B37: Total including mine cost.
B38: Mine type | D38: Base 50 | E38: Base 75 | F38: Base 100 | G38: =$G$4 -> 20
B39: Clay pit | D39: =('TU5.05'!$G$3+(J5*(1+(K5/50))+$K$2*4))/(C22*0.5)/24 -> 469.107 | E39: =('TU5.05'!$G$3+(J5*(1+(K5/50)))+$K$2*4)/(C22*0.75)/24 -> 312.738 | F39: =('TU5.05'!$G$3+(J5*(1+(K5/50)))+$K$2*4)/C22/24 -> 234.5535 | G39: =('TU5.05'!$G$3+(J5*(1+(K5/50)))+$K$2*4)/(C22*($G$4/100))/24 -> 1172.7675
B40: Limestone quarry | D40: =('TU5.05'!$G$3+(J6*(1+(K6/50))+$K$2*4))/(C23*0.5)/24 -> 964.3052 | E40: =('TU5.05'!$G$3+(J6*(1+(K6/50)))+$K$2*4)/(C23*0.75)/24 -> 642.87013 | F40: =('TU5.05'!$G$3+(J6*(1+(K6/50)))+$K$2*4)/C23/24 -> 482.1526 | G40: =('TU5.05'!$G$3+(J6*(1+(K6/50)))+$K$2*4)/(C23*($G$4/100))/24 -> 2410.763
B41: Gravel pit | D41: =('TU5.05'!$G$3+(J7*(1+(K7/50))+$K$2*4))/(C24*0.5)/24 -> 971.65974 | E41: =('TU5.05'!$G$3+(J7*(1+(K7/50)))+$K$2*4)/(C24*0.75)/24 -> 647.77316 | F41: =('TU5.05'!$G$3+(J7*(1+(K7/50)))+$K$2*4)/C24/24 -> 485.82987 | G41: =('TU5.05'!$G$3+(J7*(1+(K7/50)))+$K$2*4)/(C24*($G$4/100))/24 -> 2429.1493
B42: Coal mine | D42: =('TU5.05'!$G$3+(J8*(1+(K8/50))+$K$2*4))/(C25*0.5)/24 -> 219.5853 | E42: =('TU5.05'!$G$3+(J8*(1+(K8/50)))+$K$2*4)/(C25*0.75)/24 -> 146.3902 | F42: =('TU5.05'!$G$3+(J8*(1+(K8/50)))+$K$2*4)/C25/24 -> 109.79265 | G42: =('TU5.05'!$G$3+(J8*(1+(K8/50)))+$K$2*4)/(C25*($G$4/100))/24 -> 548.96325
B43: Iron ore mine | D43: =('TU5.05'!$G$3+(J9*(1+(K9/50))+$K$2*4))/(C26*0.5)/24 -> 484.04439 | E43: =('TU5.05'!$G$3+(J9*(1+(K9/50)))+$K$2*4)/(C26*0.75)/24 -> 322.69626 | F43: =('TU5.05'!$G$3+(J9*(1+(K9/50)))+$K$2*4)/C26/24 -> 242.0222 | G43: =('TU5.05'!$G$3+(J9*(1+(K9/50)))+$K$2*4)/(C26*($G$4/100))/24 -> 1210.111
B44: Derrick | D44: =('TU5.05'!$G$3+(J10*(1+(K10/50))+$K$2*4))/(C27*0.5)/24 -> 368.01683 | E44: =('TU5.05'!$G$3+(J10*(1+(K10/50)))+$K$2*4)/(C27*0.75)/24 -> 245.34455 | F44: =('TU5.05'!$G$3+(J10*(1+(K10/50)))+$K$2*4)/C27/24 -> 184.00841 | G44: =('TU5.05'!$G$3+(J10*(1+(K10/50)))+$K$2*4)/(C27*($G$4/100))/24 -> 920.04207
B45: Sand mine | D45: =('TU5.05'!$G$3+(J11*(1+(K11/50))+$K$2*4))/(C28*0.5)/24 -> 1207.6734 | E45: =('TU5.05'!$G$3+(J11*(1+(K11/50)))+$K$2*4)/(C28*0.75)/24 -> 805.11562 | F45: =('TU5.05'!$G$3+(J11*(1+(K11/50)))+$K$2*4)/C28/24 -> 603.83671 | G45: =('TU5.05'!$G$3+(J11*(1+(K11/50)))+$K$2*4)/(C28*($G$4/100))/24 -> 3019.1836
B46: Copper mine | D46: =('TU5.05'!$G$3+(J12*(1+(K12/50))+$K$2*4))/(C29*0.5)/24 -> 738.4216 | E46: =('TU5.05'!$G$3+(J12*(1+(K12/50)))+$K$2*4)/(C29*0.75)/24 -> 492.28107 | F46: =('TU5.05'!$G$3+(J12*(1+(K12/50)))+$K$2*4)/C29/24 -> 369.2108 | G46: =('TU5.05'!$G$3+(J12*(1+(K12/50)))+$K$2*4)/(C29*($G$4/100))/24 -> 1846.054
B47: Bauxite mine | D47: =('TU5.05'!$G$3+(J13*(1+(K13/50))+$K$2*4))/(C30*0.5)/24 -> 777.68445 | E47: =('TU5.05'!$G$3+(J13*(1+(K13/50)))+$K$2*4)/(C30*0.75)/24 -> 518.4563 | F47: =('TU5.05'!$G$3+(J13*(1+(K13/50)))+$K$2*4)/C30/24 -> 388.84222 | G47: =('TU5.05'!$G$3+(J13*(1+(K13/50)))+$K$2*4)/(C30*($G$4/100))/24 -> 1944.2111
B48: Lithium ore mine | D48: =('TU5.05'!$G$3+(J14*(1+(K14/50))+$K$2*4))/(C31*0.5)/24 -> 570.57148 | E48: =('TU5.05'!$G$3+(J14*(1+(K14/50)))+$K$2*4)/(C31*0.75)/24 -> 380.38099 | F48: =('TU5.05'!$G$3+(J14*(1+(K14/50)))+$K$2*4)/C31/24 -> 285.28574 | G48: =('TU5.05'!$G$3+(J14*(1+(K14/50)))+$K$2*4)/(C31*($G$4/100))/24 -> 1426.4287
B49: Ilmenite mine | D49: =('TU5.05'!$G$3+(J15*(1+(K15/50))+$K$2*4))/(C32*0.5)/24 -> 7675.1189 | E49: =('TU5.05'!$G$3+(J15*(1+(K15/50)))+$K$2*4)/(C32*0.75)/24 -> 5116.7459 | F49: =('TU5.05'!$G$3+(J15*(1+(K15/50)))+$K$2*4)/C32/24 -> 3837.5594 | G49: =('TU5.05'!$G$3+(J15*(1+(K15/50)))+$K$2*4)/(C32*($G$4/100))/24 -> 19187.797
B50: Silver mine | D50: =('TU5.05'!$G$3+(J16*(1+(K16/50))+$K$2*4))/(C33*0.5)/24 -> 773.02255 | E50: =('TU5.05'!$G$3+(J16*(1+(K16/50)))+$K$2*4)/(C33*0.75)/24 -> 515.34836 | F50: =('TU5.05'!$G$3+(J16*(1+(K16/50)))+$K$2*4)/C33/24 -> 386.51127 | G50: =('TU5.05'!$G$3+(J16*(1+(K16/50)))+$K$2*4)/(C33*($G$4/100))/24 -> 1932.5564
... B52: Diamond mine | D52: =('TU5.05'!$G$3+(J18*(1+(K18/50))+$K$2*4))/(C35*0.5)/24 -> 238.50441 | E52: =('TU5.05'!$G$3+(J18*(1+(K18/50)))+$K$2*4)/(C35*0.75)/24 -> 159.00294 | F52: =('TU5.05'!$G$3+(J18*(1+(K18/50)))+$K$2*4)/C35/24 -> 119.25221 | G52: =('TU5.05'!$G$3+(J18*(1+(K18/50)))+$K$2*4)/(C35*($G$4/100))/24 -> 596.26103
B54: Total With HQ
B55: Mine type | C55: Hrly Prod w/ HQ | D55: Base 50 | E55: Base 75 | F55: Base 100 | G55: =$G$4 -> 20 | H55: =$G$4 -> 20
B56: Clay pit | C56: =C22*(UserBuildings!$W$5*0.9+1) -> 24608902 | D56: =('TU5.05'!$G$3+(J5*(1+(K5/50))+$K$2*4))/(C56*0.5)/24 -> 51.55022 | E56: =('TU5.05'!$G$3+(J5*(1+(K5/50)))+$K$2*4)/(C56*0.75)/24 -> 34.366813 | F56: =('TU5.05'!$G$3+(J5*(1+(K5/50)))+$K$2*4)/C56/24 -> 25.77511 | G56: =('TU5.05'!$G$3+(J5*(1+(K5/50)))+$K$2*4)/(C56*0.75)/24 -> 34.366813 | H56: =C56*($G$4/100) -> 4921780.5
B57: Limestone quarry | C57: =C23*(UserBuildings!$W$5*0.9+1) -> 11999770 | D57: =('TU5.05'!$G$3+(J6*(1+(K6/50))+$K$2*4))/(C57*0.5)/24 -> 105.9676 | E57: =('TU5.05'!$G$3+(J6*(1+(K6/50)))+$K$2*4)/(C57*0.75)/24 -> 70.64507 | F57: =('TU5.05'!$G$3+(J6*(1+(K6/50)))+$K$2*4)/C57/24 -> 52.983802 | G57: =('TU5.05'!$G$3+(J6*(1+(K6/50)))+$K$2*4)/(($I6*($G$4/100))*5.05* (UserBuildings!$W$5*0.9+1) *'Supply Chain'!$E34)/24 -> 264.91901 | H57: =C57*($G$4/100) -> 2399953.9
B58: Gravel pit | C58: =C24*(UserBuildings!$W$5*0.9+1) -> 11955653 | D58: =('TU5.05'!$G$3+(J7*(1+(K7/50))+$K$2*4))/(C58*0.5)/24 -> 106.7758 | E58: =('TU5.05'!$G$3+(J7*(1+(K7/50)))+$K$2*4)/(C58*0.75)/24 -> 71.183864 | F58: =('TU5.05'!$G$3+(J7*(1+(K7/50)))+$K$2*4)/C58/24 -> 53.387898 | G58: =('TU5.05'!$G$3+(J7*(1+(K7/50)))+$K$2*4)/(($I7*($G$4/100))*5.05* (UserBuildings!$W$5*0.9+1) *'Supply Chain'!$E35)/24 -> 266.93949 | H58: =C58*($G$4/100) -> 2391130.6
B59: Coal mine | C59: =C25*(UserBuildings!$W$5*0.9+1) -> 56623913 | D59: =('TU5.05'!$G$3+(J8*(1+(K8/50))+$K$2*4))/(C59*0.5)/24 -> 24.130253 | E59: =('TU5.05'!$G$3+(J8*(1+(K8/50)))+$K$2*4)/(C59*0.75)/24 -> 16.086835 | F59: =('TU5.05'!$G$3+(J8*(1+(K8/50)))+$K$2*4)/C59/24 -> 12.065126 | G59: =('TU5.05'!$G$3+(J8*(1+(K8/50)))+$K$2*4)/(($I8*($G$4/100))*5.05* (UserBuildings!$W$5*0.9+1) *'Supply Chain'!$E36)/24 -> 60.325632 | H59: =C59*($G$4/100) -> 11324783
B60: Iron ore mine | C60: =C26*(UserBuildings!$W$5*0.9+1) -> 24187036 | D60: =('TU5.05'!$G$3+(J9*(1+(K9/50))+$K$2*4))/(C60*0.5)/24 -> 53.191692 | E60: =('TU5.05'!$G$3+(J9*(1+(K9/50)))+$K$2*4)/(C60*0.75)/24 -> 35.461128 | F60: =('TU5.05'!$G$3+(J9*(1+(K9/50)))+$K$2*4)/C60/24 -> 26.595846 | G60: =('TU5.05'!$G$3+(J9*(1+(K9/50)))+$K$2*4)/(($I9*($G$4/100))*5.05* (UserBuildings!$W$5*0.9+1) *'Supply Chain'!$E37)/24 -> 132.97923 | H60: =C60*($G$4/100) -> 4837407.1
B61: Derrick | C61: =C27*(UserBuildings!$W$5*0.9+1) -> 36252429 | D61: =('TU5.05'!$G$3+(J10*(1+(K10/50))+$K$2*4))/(C61*0.5)/24 -> 40.44141 | E61: =('TU5.05'!$G$3+(J10*(1+(K10/50)))+$K$2*4)/(C61*0.75)/24 -> 26.96094 | F61: =('TU5.05'!$G$3+(J10*(1+(K10/50)))+$K$2*4)/C61/24 -> 20.220705 | G61: =('TU5.05'!$G$3+(J10*(1+(K10/50)))+$K$2*4)/(($I10*($G$4/100))*5.05* (UserBuildings!$W$5*0.9+1) *'Supply Chain'!$E38)/24 -> 101.10352 | H61: =C61*($G$4/100) -> 7250485.8
B62: Sand mine | C62: =C28*(UserBuildings!$W$5*0.9+1) -> 12550540 | D62: =('TU5.05'!$G$3+(J11*(1+(K11/50))+$K$2*4))/(C62*0.5)/24 -> 132.71137 | E62: =('TU5.05'!$G$3+(J11*(1+(K11/50)))+$K$2*4)/(C62*0.75)/24 -> 88.474244 | F62: =('TU5.05'!$G$3+(J11*(1+(K11/50)))+$K$2*4)/C62/24 -> 66.355683 | G62: =('TU5.05'!$G$3+(J11*(1+(K11/50)))+$K$2*4)/(($I11*($G$4/100))*5.05* (UserBuildings!$W$5*0.9+1) *'Supply Chain'!$E39)/24 -> 331.77841 | H62: =C62*($G$4/100) -> 2510108.1
B63: Copper mine | C63: =C29*(UserBuildings!$W$5*0.9+1) -> 25443261 | D63: =('TU5.05'!$G$3+(J12*(1+(K12/50))+$K$2*4))/(C63*0.5)/24 -> 81.145231 | E63: =('TU5.05'!$G$3+(J12*(1+(K12/50)))+$K$2*4)/(C63*0.75)/24 -> 54.096821 | F63: =('TU5.05'!$G$3+(J12*(1+(K12/50)))+$K$2*4)/C63/24 -> 40.572616 | G63: =('TU5.05'!$G$3+(J12*(1+(K12/50)))+$K$2*4)/(($I12*($G$4/100))*5.05* (UserBuildings!$W$5*0.9+1) *'Supply Chain'!$E40)/24 -> 202.86308 | H63: =C63*($G$4/100) -> 5088652.3
B64: Bauxite mine | C64: =C30*(UserBuildings!$W$5*0.9+1) -> 28827572 | D64: =('TU5.05'!$G$3+(J13*(1+(K13/50))+$K$2*4))/(C64*0.5)/24 -> 85.459829 | E64: =('TU5.05'!$G$3+(J13*(1+(K13/50)))+$K$2*4)/(C64*0.75)/24 -> 56.973219 | F64: =('TU5.05'!$G$3+(J13*(1+(K13/50)))+$K$2*4)/C64/24 -> 42.729915 | G64: =('TU5.05'!$G$3+(J13*(1+(K13/50)))+$K$2*4)/(($I13*($G$4/100))*5.05* (UserBuildings!$W$5*0.9+1) *'Supply Chain'!$E41)/24 -> 213.64957 | H64: =C64*($G$4/100) -> 5765514.3
B65: Lithium ore mine | C65: =C31*(UserBuildings!$W$5*0.9+1) -> 45655373 | D65: =('TU5.05'!$G$3+(J14*(1+(K14/50))+$K$2*4))/(C65*0.5)/24 -> 62.700163 | E65: =('TU5.05'!$G$3+(J14*(1+(K14/50)))+$K$2*4)/(C65*0.75)/24 -> 41.800108 | F65: =('TU5.05'!$G$3+(J14*(1+(K14/50)))+$K$2*4)/C65/24 -> 31.350081 | G65: =('TU5.05'!$G$3+(J14*(1+(K14/50)))+$K$2*4)/(($I14*($G$4/100))*5.05* (UserBuildings!$W$5*0.9+1) *'Supply Chain'!$E42)/24 -> 156.75041 | H65: =C65*($G$4/100) -> 9131074.7
B66: Ilmenite mine | C66: =C32*(UserBuildings!$W$5*0.9+1) -> 3867113.2 | D66: =('TU5.05'!$G$3+(J15*(1+(K15/50))+$K$2*4))/(C66*0.5)/24 -> 843.41966 | E66: =('TU5.05'!$G$3+(J15*(1+(K15/50)))+$K$2*4)/(C66*0.75)/24 -> 562.27977 | F66: =('TU5.05'!$G$3+(J15*(1+(K15/50)))+$K$2*4)/C66/24 -> 421.70983 | G66: =('TU5.05'!$G$3+(J15*(1+(K15/50)))+$K$2*4)/(($I15*($G$4/100))*5.05* (UserBuildings!$W$5*0.9+1) *'Supply Chain'!$E43)/24 -> 2108.5491 | H66: =C66*($G$4/100) -> 773422.65
B67: Silver mine | C67: =C33*(UserBuildings!$W$5*0.9+1) -> 44266728 | D67: =('TU5.05'!$G$3+(J16*(1+(K16/50))+$K$2*4))/(C67*0.5)/24 -> 84.947533 | E67: =('TU5.05'!$G$3+(J16*(1+(K16/50)))+$K$2*4)/(C67*0.75)/24 -> 56.631688 | F67: =('TU5.05'!$G$3+(J16*(1+(K16/50)))+$K$2*4)/C67/24 -> 42.473766 | G67: =('TU5.05'!$G$3+(J16*(1+(K16/50)))+$K$2*4)/(($I16*($G$4/100))*5.05* (UserBuildings!$W$5*0.9+1) *'Supply Chain'!$E44)/24 -> 212.36883 | H67: =C67*($G$4/100) -> 8853345.6
B68: Gold mine | C68: =C34*(UserBuildings!$W$5*0.9+1) -> 89248286 | D68: =('TU5.05'!$G$3+(J17*(1+(K17/50))+$K$2*4))/(C68*0.5)/24 -> 47.721917 | E68: =('TU5.05'!$G$3+(J17*(1+(K17/50)))+$K$2*4)/(C68*0.75)/24 -> 31.814611 | F68: =('TU5.05'!$G$3+(J17*(1+(K17/50)))+$K$2*4)/C68/24 -> 23.860959 | G68: =('TU5.05'!$G$3+(J17*(1+(K17/50)))+$K$2*4)/(($I17*($G$4/100))*5.05* (UserBuildings!$W$5*0.9+1) *'Supply Chain'!$E45)/24 -> 119.30479 | H68: =C68*($G$4/100) -> 17849657
B69: Diamond mine | C69: =C35*(UserBuildings!$W$5*0.9+1) -> 2.0056256e+08 | D69: =('TU5.05'!$G$3+(J18*(1+(K18/50))+$K$2*4))/(C69*0.5)/24 -> 26.209276 | E69: =('TU5.05'!$G$3+(J18*(1+(K18/50)))+$K$2*4)/(C69*0.75)/24 -> 17.472851 | F69: =('TU5.05'!$G$3+(J18*(1+(K18/50)))+$K$2*4)/C69/24 -> 13.104638 | G69: =('TU5.05'!$G$3+(J18*(1+(K18/50)))+$K$2*4)/(($I18*($G$4/100))*5.05* (UserBuildings!$W$5*0.9+1) *'Supply Chain'!$E46)/24 -> 65.52319 | H69: =C69*($G$4/100) -> 40112511
B71: To help plan mines under HQ. Note that a 70% lithium is better than a 30% diamond.
C72: 10 | D72: 20 | E72: 30 | F72: 40 | G72: 50 | H72: 60 | I72: 70 | J72: 80 | K72: 90 | L72: 100
B73: Clay pit | C73: =(C$72/100)*$L73 -> 2460890.2 | D73: =(D$72/100)*$L73 -> 4921780.5 | E73: =(E$72/100)*$L73 -> 7382670.8 | F73: =(F$72/100)*$L73 -> 9843561 | G73: =(G$72/100)*$L73 -> 12304451 | H73: =(H$72/100)*$L73 -> 14765342 | I73: =(I$72/100)*$L73 -> 17226232 | J73: =(J$72/100)*$L73 -> 19687122 | K73: =(K$72/100)*$L73 -> 22148012 | L73: =C56 -> 24608902
B74: Limestone quarry | C74: =(C$72/100)*$L74 -> 1199977 | D74: =(D$72/100)*$L74 -> 2399953.9 | E74: =(E$72/100)*$L74 -> 3599930.9 | F74: =(F$72/100)*$L74 -> 4799907.8 | G74: =(G$72/100)*$L74 -> 5999884.8 | H74: =(H$72/100)*$L74 -> 7199861.8 | I74: =(I$72/100)*$L74 -> 8399838.7 | J74: =(J$72/100)*$L74 -> 9599815.7 | K74: =(K$72/100)*$L74 -> 10799793 | L74: =C57 -> 11999770
B75: Gravel pit | C75: =(C$72/100)*$L75 -> 1195565.3 | D75: =(D$72/100)*$L75 -> 2391130.6 | E75: =(E$72/100)*$L75 -> 3586695.8 | F75: =(F$72/100)*$L75 -> 4782261.1 | G75: =(G$72/100)*$L75 -> 5977826.4 | H75: =(H$72/100)*$L75 -> 7173391.7 | I75: =(I$72/100)*$L75 -> 8368957 | J75: =(J$72/100)*$L75 -> 9564522.2 | K75: =(K$72/100)*$L75 -> 10760088 | L75: =C58 -> 11955653
B76: Coal mine | C76: =(C$72/100)*$L76 -> 5662391.3 | D76: =(D$72/100)*$L76 -> 11324783 | E76: =(E$72/100)*$L76 -> 16987174 | F76: =(F$72/100)*$L76 -> 22649565 | G76: =(G$72/100)*$L76 -> 28311956 | H76: =(H$72/100)*$L76 -> 33974348 | I76: =(I$72/100)*$L76 -> 39636739 | J76: =(J$72/100)*$L76 -> 45299130 | K76: =(K$72/100)*$L76 -> 50961522 | L76: =C59 -> 56623913
B77: Iron ore mine | C77: =(C$72/100)*$L77 -> 2418703.6 | D77: =(D$72/100)*$L77 -> 4837407.1 | E77: =(E$72/100)*$L77 -> 7256110.7 | F77: =(F$72/100)*$L77 -> 9674814.2 | G77: =(G$72/100)*$L77 -> 12093518 | H77: =(H$72/100)*$L77 -> 14512221 | I77: =(I$72/100)*$L77 -> 16930925 | J77: =(J$72/100)*$L77 -> 19349628 | K77: =(K$72/100)*$L77 -> 21768332 | L77: =C60 -> 24187036
B78: Derrick | C78: =(C$72/100)*$L78 -> 3625242.9 | D78: =(D$72/100)*$L78 -> 7250485.8 | E78: =(E$72/100)*$L78 -> 10875729 | F78: =(F$72/100)*$L78 -> 14500972 | G78: =(G$72/100)*$L78 -> 18126214 | H78: =(H$72/100)*$L78 -> 21751457 | I78: =(I$72/100)*$L78 -> 25376700 | J78: =(J$72/100)*$L78 -> 29001943 | K78: =(K$72/100)*$L78 -> 32627186 | L78: =C61 -> 36252429
B79: Sand mine | C79: =(C$72/100)*$L79 -> 1255054 | D79: =(D$72/100)*$L79 -> 2510108.1 | E79: =(E$72/100)*$L79 -> 3765162.1 | F79: =(F$72/100)*$L79 -> 5020216.1 | G79: =(G$72/100)*$L79 -> 6275270.1 | H79: =(H$72/100)*$L79 -> 7530324.2 | I79: =(I$72/100)*$L79 -> 8785378.2 | J79: =(J$72/100)*$L79 -> 10040432 | K79: =(K$72/100)*$L79 -> 11295486 | L79: =C62 -> 12550540
B80: Copper mine | C80: =(C$72/100)*$L80 -> 2544326.1 | D80: =(D$72/100)*$L80 -> 5088652.3 | E80: =(E$72/100)*$L80 -> 7632978.4 | F80: =(F$72/100)*$L80 -> 10177305 | G80: =(G$72/100)*$L80 -> 12721631 | H80: =(H$72/100)*$L80 -> 15265957 | I80: =(I$72/100)*$L80 -> 17810283 | J80: =(J$72/100)*$L80 -> 20354609 | K80: =(K$72/100)*$L80 -> 22898935 | L80: =C63 -> 25443261
B81: Bauxite mine | C81: =(C$72/100)*$L81 -> 2882757.2 | D81: =(D$72/100)*$L81 -> 5765514.3 | E81: =(E$72/100)*$L81 -> 8648271.4 | F81: =(F$72/100)*$L81 -> 11531029 | G81: =(G$72/100)*$L81 -> 14413786 | H81: =(H$72/100)*$L81 -> 17296543 | I81: =(I$72/100)*$L81 -> 20179300 | J81: =(J$72/100)*$L81 -> 23062057 | K81: =(K$72/100)*$L81 -> 25944814 | L81: =C64 -> 28827572
B82: Lithium ore mine | C82: =(C$72/100)*$L82 -> 4565537.3 | D82: =(D$72/100)*$L82 -> 9131074.7 | E82: =(E$72/100)*$L82 -> 13696612 | F82: =(F$72/100)*$L82 -> 18262149 | G82: =(G$72/100)*$L82 -> 22827687 | H82: =(H$72/100)*$L82 -> 27393224 | I82: =(I$72/100)*$L82 -> 31958761 | J82: =(J$72/100)*$L82 -> 36524299 | K82: =(K$72/100)*$L82 -> 41089836 | L82: =C65 -> 45655373
B83: Ilmenite mine | C83: =(C$72/100)*$L83 -> 386711.32 | D83: =(D$72/100)*$L83 -> 773422.65 | E83: =(E$72/100)*$L83 -> 1160134 | F83: =(F$72/100)*$L83 -> 1546845.3 | G83: =(G$72/100)*$L83 -> 1933556.6 | H83: =(H$72/100)*$L83 -> 2320267.9 | I83: =(I$72/100)*$L83 -> 2706979.3 | J83: =(J$72/100)*$L83 -> 3093690.6 | K83: =(K$72/100)*$L83 -> 3480401.9 | L83: =C66 -> 3867113.2
B84: Silver mine | C84: =(C$72/100)*$L84 -> 4426672.8 | D84: =(D$72/100)*$L84 -> 8853345.6 | E84: =(E$72/100)*$L84 -> 13280018 | F84: =(F$72/100)*$L84 -> 17706691 | G84: =(G$72/100)*$L84 -> 22133364 | H84: =(H$72/100)*$L84 -> 26560037 | I84: =(I$72/100)*$L84 -> 30986710 | J84: =(J$72/100)*$L84 -> 35413383 | K84: =(K$72/100)*$L84 -> 39840055 | L84: =C67 -> 44266728
... B86: Diamond mine | C86: =(C$72/100)*$L86 -> 20056256 | D86: =(D$72/100)*$L86 -> 40112511 | E86: =(E$72/100)*$L86 -> 60168767 | F86: =(F$72/100)*$L86 -> 80225022 | G86: =(G$72/100)*$L86 -> 1.0028128e+08 | H86: =(H$72/100)*$L86 -> 1.2033753e+08 | I86: =(I$72/100)*$L86 -> 1.4039379e+08 | J86: =(J$72/100)*$L86 -> 1.6045004e+08 | K86: =(K$72/100)*$L86 -> 1.805063e+08 | L86: =C69 -> 2.0056256e+08
B91: How Often Should I Repair My Mines?
B92: Repair on Day | D92: Extrapolated | E92: with MKs
B93: Days | C93: Mine Production ($Bil/hr) | D93: Cost to Repair All | E93: Cost to Repair | F93: Cumulative Lost Production Opportunity Cost | I93: Minimize this Total Loss ($Bil/day) | K93: Mine Condition
B94: ½ | C94: =('Supply Chain'!D48)/1000000000 -> 20.50479 | D94: =D95*(1+(0.5-1)/30) -> 9.8333333 | E94: =IF(UserBuildings!C25="Yes",UserBuildings!C24,0)/1000000000 -> 0 | F94: =12*(C94-C95)/2 -> 4.9211496 | I94: =IF(UserBuildings!C25="Yes",(F94+E94)/0.5,(F94+D94)/0.5) -> 29.508966 | K94: 0.98
B95: 1 | C95: =C94*(1-(0.04*B95)) -> 19.684598 | D95: 10 | E95: =IF(UserBuildings!C25="Yes",UserBuildings!C24,0)/1000000000 -> 0 | F95: =12*(C$94-C95)*B95 -> 9.8422992 | I95: =IF(UserBuildings!C25="Yes",(F95+E95)/B95,(F95+D95)/B95) -> 19.842299 | K95: 0.96
B96: 2 | C96: =C94*(1-(0.04*B96)) -> 18.864407 | D96: =D95*(1+(B96-1)/30) -> 10.333333 | E96: =IF(UserBuildings!C25="Yes",UserBuildings!C24,0)/1000000000 -> 0 | F96: =12*(C$94-C96)*B96 -> 39.369197 | I96: =IF(UserBuildings!C26="Yes",(F96+E96)/B96,(F96+D96)/B96) -> 24.851265 | K96: 0.92
B97: 3 | C97: =C94*(1-(0.04*B97)) -> 18.044215 | D97: =D95*(1+(B97-1)/30) -> 10.666667 | E97: =IF(UserBuildings!C25="Yes",UserBuildings!C24,0)/1000000000 -> 0 | F97: =12*(C$94-C97)*B97 -> 88.580693 | I97: =IF(UserBuildings!C27="Yes",(F97+E97)/B97,(F97+D97)/B97) -> 33.082453 | K97: 0.88
B98: 4 | C98: =C94*(1-(0.04*B98)) -> 17.224024 | D98: =D95*(1+(B98-1)/30) -> 11 | E98: =IF(UserBuildings!C25="Yes",UserBuildings!C24,0)/1000000000 -> 0 | F98: =12*(C$94-C98)*B98 -> 157.47679 | I98: =IF(UserBuildings!C28="Yes",(F98+E98)/B98,(F98+D98)/B98) -> 42.119197 | K98: 0.84
B99: 5 | C99: =C94*(1-(0.04*B99)) -> 16.403832 | D99: =D95*(1+(B99-1)/30) -> 11.333333 | E99: =IF(UserBuildings!C25="Yes",UserBuildings!C24,0)/1000000000 -> 0 | F99: =12*(C$94-C99)*B99 -> 246.05748 | I99: =IF(UserBuildings!C29="Yes",(F99+E99)/B99,(F99+D99)/B99) -> 51.478163 | K99: 0.8
B100: 6 | C100: =C94*(1-(0.04*B100)) -> 15.58364 | D100: =D95*(1+(B100-1)/30) -> 11.666667 | E100: =IF(UserBuildings!C25="Yes",UserBuildings!C24,0)/1000000000 -> 0 | F100: =12*(C$94-C100)*B100 -> 354.32277 | I100: =IF(UserBuildings!C30="Yes",(F100+E100)/B100,(F100+D100)/B100) -> 60.99824 | K100: 0.76
B101: 7 | C101: =C94*(1-(0.04*B101)) -> 14.763449 | D101: =D95*(1+(B101-1)/30) -> 12 | E101: =IF(UserBuildings!C25="Yes",UserBuildings!C24,0)/1000000000 -> 0 | F101: =12*(C$94-C101)*B101 -> 482.27266 | I101: =IF(UserBuildings!C31="Yes",(F101+E101)/B101,(F101+D101)/B101) -> 70.61038 | K101: 0.72
B102: 8 | C102: =C94*(1-(0.04*B102)) -> 13.943257 | D102: =D95*(1+(B102-1)/30) -> 12.333333 | E102: =IF(UserBuildings!C25="Yes",UserBuildings!C24,0)/1000000000 -> 0 | F102: =12*(C$94-C102)*B102 -> 629.90715 | I102: =IF(UserBuildings!C32="Yes",(F102+E102)/B102,(F102+D102)/B102) -> 80.28006 | K102: 0.68
B103: 9 | C103: =C94*(1-(0.04*B103)) -> 13.123066 | D103: =D95*(1+(B103-1)/30) -> 12.666667 | E103: =IF(UserBuildings!C25="Yes",UserBuildings!C24,0)/1000000000 -> 0 | F103: =12*(C$94-C103)*B103 -> 797.22623 | I103: =IF(UserBuildings!C33="Yes",(F103+E103)/B103,(F103+D103)/B103) -> 89.9881 | K103: 0.64
B104: 10 | C104: =C94*(1-(0.04*B104)) -> 12.302874 | D104: =D95*(1+(B104-1)/30) -> 13 | E104: =IF(UserBuildings!C25="Yes",UserBuildings!C24,0)/1000000000 -> 0 | F104: =12*(C$94-C104)*B104 -> 984.22992 | I104: =IF(UserBuildings!C34="Yes",(F104+E104)/B104,(F104+D104)/B104) -> 99.722992 | K104: 0.6
B105: 11 | C105: =C94*(1-(0.04*B105)) -> 11.482682 | D105: =D95*(1+(B105-1)/30) -> 13.333333 | E105: =IF(UserBuildings!C25="Yes",UserBuildings!C24,0)/1000000000 -> 0 | F105: =12*(C$94-C105)*B105 -> 1190.9182 | I105: =IF(UserBuildings!C35="Yes",(F105+E105)/B105,(F105+D105)/B105) -> 109.47741 | K105: 0.56
B106: 12 | C106: =C94*(1-(0.04*B106)) -> 10.662491 | D106: =D95*(1+(B106-1)/30) -> 13.666667 | E106: =IF(UserBuildings!C25="Yes",UserBuildings!C24,0)/1000000000 -> 0 | F106: =12*(C$94-C106)*B106 -> 1417.2911 | I106: =IF(UserBuildings!C36="Yes",(F106+E106)/B106,(F106+D106)/B106) -> 119.24648 | K106: 0.52
B107: 13 | C107: =C94*(1-(0.04*B107)) -> 9.8422992 | D107: =D95*(1+(B107-1)/30) -> 14 | E107: =IF(UserBuildings!C25="Yes",UserBuildings!C24,0)/1000000000 -> 0 | F107: =12*(C$94-C107)*B107 -> 1663.3486 | I107: =IF(UserBuildings!C37="Yes",(F107+E107)/B107,(F107+D107)/B107) -> 129.02681 | K107: 0.48
B108: 14 | C108: =C94*(1-(0.04*B108)) -> 9.0221076 | D108: =D95*(1+(B108-1)/30) -> 14.333333 | E108: =IF(UserBuildings!C25="Yes",UserBuildings!C24,0)/1000000000 -> 0 | F108: =12*(C$94-C108)*B108 -> 1929.0906 | I108: =IF(UserBuildings!C38="Yes",(F108+E108)/B108,(F108+D108)/B108) -> 138.816 | K108: 0.44
B109: 15 | C109: =C94*(1-(0.04*B109)) -> 8.201916 | D109: =D95*(1+(B109-1)/30) -> 14.666667 | E109: =IF(UserBuildings!C25="Yes",UserBuildings!C24,0)/1000000000 -> 0 | F109: =12*(C$94-C109)*B109 -> 2214.5173 | I109: =IF(UserBuildings!C39="Yes",(F109+E109)/B109,(F109+D109)/B109) -> 148.61227 | K109: 0.4
B110: 16 | C110: =C94*(1-(0.04*B110)) -> 7.3817244 | D110: =D95*(1+(B110-1)/30) -> 15 | E110: =IF(UserBuildings!C25="Yes",UserBuildings!C24,0)/1000000000 -> 0 | F110: =12*(C$94-C110)*B110 -> 2519.6286 | I110: =IF(UserBuildings!C40="Yes",(F110+E110)/B110,(F110+D110)/B110) -> 158.41429 | K110: 0.36
B111: 17 | C111: =C94*(1-(0.04*B111)) -> 6.5615328 | D111: =D95*(1+(B111-1)/30) -> 15.333333 | E111: =IF(UserBuildings!C25="Yes",UserBuildings!C24,0)/1000000000 -> 0 | F111: =12*(C$94-C111)*B111 -> 2844.4245 | I111: =IF(UserBuildings!C41="Yes",(F111+E111)/B111,(F111+D111)/B111) -> 168.22105 | K111: 0.32
B112: 18 | C112: =C94*(1-(0.04*B112)) -> 5.7413412 | D112: =D95*(1+(B112-1)/30) -> 15.666667 | E112: =IF(UserBuildings!C25="Yes",UserBuildings!C24,0)/1000000000 -> 0 | F112: =12*(C$94-C112)*B112 -> 3188.9049 | I112: =IF(UserBuildings!C42="Yes",(F112+E112)/B112,(F112+D112)/B112) -> 178.03176 | K112: 0.28
...

Sheet README-PT-BR
B2: TRADUÇÕES DE ITENS NA LINHA 201 EM DIANTE
B3: Para todas as versões atuais e futuras desta folha, a menos que indicado de outra forma, você pode atualizar fazendo uma nova cópia da folha,
B4: Em seguida, copiar toda a guia UserBuildings de sua folha antiga e substituir os dados na nova planilha.
B6: 25 Nov # 2: Correção de bugs menores onde minas e fábricas não aparecem.
B8: 25 Nov: É importante para aqueles de vocês que usarão a API para ler as instruções da API para evitar o uso excessivo de seus dados api.
C9: Suporte API adicionado para a guia Completa de Edifícios de Usuário.
C10: NÃO copie e cole o separador User Buildings de uma versão anterior, esta actualização invovles pesadas actualizações guia tabelas edifícios.
B11: Por enquanto, as configurações de API (chave liga / desliga e entrada de chave de API) estão na página API Raw. No entanto, vou movê-lo para a página UserBuildings se suficientes pessoas expressam suporte para essa idéia.
B13: 24 Nov: Feliz Dia de Ação de Graças! Correção menor na guia Mine ROI onde o ROI condicional (padrão em 35 foi fritzed para cima).
B15: Pequena modificação na guia Mine ROI para contabilizar os custos de digitalização. Isso pressupõe uma média de 4 varreduras por mina para explicar a colocação precisa.
B17: Novo: grandes melhorias para finalmente se preocupar em incorporar a nova API. Estou indo as cegas, e não podemos ver nenhum resultado, mas estou tentando.
B19: 12 Set: ENORME BUG FIX. Altere a célula E48 na guia Cadeia de Fornecimento para ler "= D48 * 24" em vez de "= C48 * 24" Folha está subestimando grosseiramente seus lucros
B20: Contando o valor dos recursos colocados em fábricas duas vezes. Crédito a Arn0io pela ajuda.
B21: Altere também adicionar "+ C77" ao final de D48.
B23: UPDATED: Adicionado custos de transporte para a cadeia de abastecimento. O ROI da fábrica, Reciclagem / Unidades, Edifícios Especiais e QG não contabilizam os custos de transporte.
B24: Adicionado caminhão fábrica, fábrica roi, caminhão lucros, adicionado caminhões para cadeia de abastecimento.
B26: CONTACTE-ME PARA RELATAR BUGS, informações de contato está abaixo.
B27: Também sinta-se livre para sugerir recursos, especialmente os relacionados com a nova atualização que eu possa ter perdido.
B28: 29 de julho: Correção de bugs. Você pode copiar a célula diretamente individual
... B119: Caixas atuais no jogo
B120: =HYPERLINK("http://appweb.resources-game.ch/stats/getBoxesStat_hp.php","http://appweb.resources-game.ch/stats/getBoxesStat_hp.php") -> http://appweb.resources-game.ch/stats/getBoxesStat_hp.php
B122: Top 20 mineiros
B123: =HYPERLINK("http://appweb.resources-game.ch/stats/masterminer_hp.php","http://appweb.resources-game.ch/stats/masterminer_hp.php") -> http://appweb.resources-game.ch/stats/masterminer_hp.php
B125: Dados no jogo
B126: =HYPERLINK("http://ssl.resources-game.ch/","http://ssl.resources-game.ch/") -> http://ssl.resources-game.ch/
B128: Guia de jogo
B129: =HYPERLINK("http://tinyurl.com/npa82ky","http://tinyurl.com/npa82ky") -> http://tinyurl.com/npa82ky
B131: Folha de cálculo do registro de empréstimo
B132: =HYPERLINK("http://tinyurl.com/usabanking","http://tinyurl.com/usabanking") -> http://tinyurl.com/usabanking
B134: Player Fraggle Folha de cálculo original do Rock1 para precisão de digitalização.
B135: =HYPERLINK("https://docs.google.com/spreadsheets/d/1Lsno9_Jpwv4JTD14339H-yFaoUV7Kaev_FimGg6XpCM/edit?ts=566f2a7a#gid=0","https://docs.google.com/spreadsheets/d/1Lsno9_Jpwv4JTD14339H-yFaoUV7Kaev_FimGg6XpCM/edit?ts=566f2a7a#gid=0") -> https://docs.google.com/spreadsheets/d/1Lsno9_Jpwv4JTD14339H-yFaoUV7Kaev_FimGg6XpCM/edit?ts=566f2a7a#gid=0
B137: Descrições da folha.
B138: (Supply Chain) Cadeia de Fornecimento: Isso acumula toda a sua produção em totais ordenados.
B139: Ele também mostra sua escassez de produção.
B140: O valor de ajuste é baseado em quanto desse recurso você precisará alimentar em fábricas
B142: (User Buildings) Edifícios do Usuário: Aqui é onde você insere seus dados.
B143: As células azuis são entrada do usuário.
B144: - Usando? Coluna em fábricas é um "Sim" ou "Não" resposta. Ele permite que você veja seus lucros totais se você optar por não executar certas fábricas.
B145: Seção de custos de manutenção. Na segunda linha, escolha o tipo que você usa.
B147: Factory ROI: Aqui é onde os preços de atualização de fábrica são calculados.
B148: Dias para ROI é quantos dias até o aumento da produção vai pagar o custo da atualização.
B149: Multiplicador é quantas vezes você tem que atualizar a fábrica para aumentar os lucros por hora em 100 milhões.
B150: Média é um composto de ROI e Multiplicador. Em última análise, o consenso geral é que o ROI é o mais importante.
... B200: TRADUÇÕES:
B202: Clay | D202: -> | E202: Argila | G202: =Calc!C4 -> Bricks | I202: -> | J202: Tijolos
B203: Limestone | D203: -> | E203: Calcário | G203: =Calc!C5 -> Concrete | I203: -> | J203: Concreto
B204: Gravel | D204: -> | E204: Cascalho | G204: =Calc!C6 -> Fertilizer | I204: -> | J204: Fertilizante
B205: Coal | D205: -> | E205: Carvão | G205: =Calc!C7 -> Steel | I205: -> | J205: Aço
B206: Iron Ore | D206: -> | E206: Minério de ferro | G206: =Calc!C8 -> Fossil fuel | I206: -> | J206: Combustível fóssil
B207: Crude Oil | D207: -> | E207: Óleo cru | G207: =Calc!C9 -> Glass | I207: -> | J207: Vidro
B208: Quartz Sand | D208: -> | E208: Areia de Quartzo | G208: =Calc!C10 -> Copper | I208: -> | J208: Cobre
B209: Chalcopyrite | D209: -> | E209: Calcopirita | G209: =Calc!C11 -> Insecticides | I209: -> | J209: Inseticidas
B210: Bauxite | D210: -> | E210: Bauxita | G210: =Calc!C12 -> Aluminium | I210: -> | J210: Alumínio
B211: Lithium Ore | D211: -> | E211: Minério de lítio | G211: =Calc!C13 -> Plastics | I211: -> | J211: Plásticos
B212: Ilmenite | D212: -> | E212: Ilmenite | G212: =Calc!C14 -> Lithium | I212: -> | J212: Lítio
B213: Silver Ore | D213: -> | E213: Minério de prata | G213: =Calc!C15 -> Batteries | I213: -> | J213: Baterias
... B215: Rough Diamonds | D215: -> | E215: Diamantes bruto | G215: =Calc!C17 -> Silicon | I215: -> | J215: Silício
G216: =Calc!C18 -> Electronics | I216: -> | J216: Eletrônicos
G217: =Calc!C19 -> Titanium | I217: -> | J217: Titânio
G218: =Calc!C20 -> Medical technology | I218: -> | J218: Tecnologia médica
G219: =Calc!C21 -> Silver | I219: -> | J219: Prata
G220: =Calc!C22 -> Gold | I220: -> | J220: Ouro
G221: =Calc!C23 -> Jewellery | I221: -> | J221: Jóias
G222: =Calc!C24 -> Scan drones | I222: -> | J222: Scan drones
G223: Trucks | I223: -> | J223: caminhões

Sheet TU5.05
J1: Mines to Tech | K1: 10
B2: Tech upgrade 1 | C2: Tech upgrade 2 | D2: Tech upgrade 3 | E2: Tech upgrade 4 | F2: Result | G2: Cost | H2: TU4 Relative Cost | J2: Upgrades in stock
B3: =IF(VLOOKUP(B2,TblMarket,3,FALSE)=0,VLOOKUP(B2,TblMarket,2,FALSE), VLOOKUP(B2,TblMarket,3,FALSE)) -> 88588508 | C3: =IF(VLOOKUP(C2,TblMarket,3,FALSE)=0,VLOOKUP(C2,TblMarket,2,FALSE), VLOOKUP(C2,TblMarket,3,FALSE)) -> 263741086 | D3: =IF(VLOOKUP(D2,TblMarket,3,FALSE)=0,VLOOKUP(D2,TblMarket,2,FALSE), VLOOKUP(D2,TblMarket,3,FALSE)) -> 270969163 | E3: =MAX(H29:H298) -> 545117527 | G3: =MIN(G6:G27) -> 14654684056 | J3: 39 | K3: 1 | L3: 664 | M3: 27
J4: Techupgrade 1 | K4: Techupgrade 2 | L4: Techupgrade 3 | M4: Techupgrade 4 | N4: OK
B6: 111 | C6: 26 | D6: 0 | E6: 0 | F6: 5.0498323 | G6: =(B6*$B$3)+(C6*$C$3)+(D6*$D$3) -> 16690592624 | J6: =$K$1*B6 -> 1110 | K6: =$K$1*C6 -> 260 | L6: =$K$1*D6 -> 0 | M6: =$K$1*E6 -> 0 | N6: =ROUNDDOWN(MIN($J$3/(B6+0.001),$K$3/(C6+0.001),$L$3/(D6+0.001)),0) -> 0
B7: 114 | C7: 23 | D7: 1 | E7: 0 | F7: 5.049842 | G7: =(B7*$B$3)+(C7*$C$3)+(D7*$D$3) -> 16436104053 | J7: =$K$1*B7 -> 1140 | K7: =$K$1*C7 -> 230 | L7: =$K$1*D7 -> 10 | M7: =$K$1*E7 -> 0 | N7: =ROUNDDOWN(MIN($J$3/(B7+0.001),$K$3/(C7+0.001),$L$3/(D7+0.001)),0) -> 0
B8: 117 | C8: 20 | D8: 2 | E8: 0 | F8: 5.0498516 | G8: =(B8*$B$3)+(C8*$C$3)+(D8*$D$3) -> 16181615482 | J8: =$K$1*B8 -> 1170 | K8: =$K$1*C8 -> 200 | L8: =$K$1*D8 -> 20 | M8: =$K$1*E8 -> 0 | N8: =ROUNDDOWN(MIN($J$3/(B8+0.001),$K$3/(C8+0.001),$L$3/(D8+0.001)),0) -> 0
B9: 120 | C9: 17 | D9: 3 | E9: 0 | F9: 5.0498613 | G9: =(B9*$B$3)+(C9*$C$3)+(D9*$D$3) -> 15927126911 | J9: =$K$1*B9 -> 1200 | K9: =$K$1*C9 -> 170 | L9: =$K$1*D9 -> 30 | M9: =$K$1*E9 -> 0 | N9: =ROUNDDOWN(MIN($J$3/(B9+0.001),$K$3/(C9+0.001),$L$3/(D9+0.001)),0) -> 0
B10: 123 | C10: 14 | D10: 4 | E10: 0 | F10: 5.0498709 | G10: =(B10*$B$3)+(C10*$C$3)+(D10*$D$3) -> 15672638340 | J10: =$K$1*B10 -> 1230 | K10: =$K$1*C10 -> 140 | L10: =$K$1*D10 -> 40 | M10: =$K$1*E10 -> 0 | N10: =ROUNDDOWN(MIN($J$3/(B10+0.001),$K$3/(C10+0.001),$L$3/(D10+0.001)),0) -> 0
B11: 126 | C11: 11 | D11: 5 | E11: 0 | F11: 5.0498806 | G11: =(B11*$B$3)+(C11*$C$3)+(D11*$D$3) -> 15418149769 | J11: =$K$1*B11 -> 1260 | K11: =$K$1*C11 -> 110 | L11: =$K$1*D11 -> 50 | M11: =$K$1*E11 -> 0 | N11: =ROUNDDOWN(MIN($J$3/(B11+0.001),$K$3/(C11+0.001),$L$3/(D11+0.001)),0) -> 0
B12: 129 | C12: 8 | D12: 6 | E12: 0 | F12: 5.0498903 | G12: =(B12*$B$3)+(C12*$C$3)+(D12*$D$3) -> 15163661198 | J12: =$K$1*B12 -> 1290 | K12: =$K$1*C12 -> 80 | L12: =$K$1*D12 -> 60 | M12: =$K$1*E12 -> 0 | N12: =ROUNDDOWN(MIN($J$3/(B12+0.001),$K$3/(C12+0.001),$L$3/(D12+0.001)),0) -> 0
B13: 132 | C13: 5 | D13: 7 | E13: 0 | F13: 5.0498999 | G13: =(B13*$B$3)+(C13*$C$3)+(D13*$D$3) -> 14909172627 | J13: =$K$1*B13 -> 1320 | K13: =$K$1*C13 -> 50 | L13: =$K$1*D13 -> 70 | M13: =$K$1*E13 -> 0 | N13: =ROUNDDOWN(MIN($J$3/(B13+0.001),$K$3/(C13+0.001),$L$3/(D13+0.001)),0) -> 0
B14: 135 | C14: 2 | D14: 8 | E14: 0 | F14: 5.0499096 | G14: =(B14*$B$3)+(C14*$C$3)+(D14*$D$3) -> 14654684056 | J14: =$K$1*B14 -> 1350 | K14: =$K$1*C14 -> 20 | L14: =$K$1*D14 -> 80 | M14: =$K$1*E14 -> 0 | N14: =ROUNDDOWN(MIN($J$3/(B14+0.001),$K$3/(C14+0.001),$L$3/(D14+0.001)),0) -> 0
B15: 1 | C15: 35 | D15: 31 | E15: 0 | F15: 5.0498834 | G15: =(B15*$B$3)+(C15*$C$3)+(D15*$D$3) -> 17719570571 | J15: =$K$1*B15 -> 10 | K15: =$K$1*C15 -> 350 | L15: =$K$1*D15 -> 310 | M15: =$K$1*E15 -> 0 | N15: =ROUNDDOWN(MIN($J$3/(B15+0.001),$K$3/(C15+0.001),$L$3/(D15+0.001)),0) -> 0
B16: 4 | C16: 32 | D16: 32 | E16: 0 | F16: 5.0498931 | G16: =(B16*$B$3)+(C16*$C$3)+(D16*$D$3) -> 17465082000 | J16: =$K$1*B16 -> 40 | K16: =$K$1*C16 -> 320 | L16: =$K$1*D16 -> 320 | M16: =$K$1*E16 -> 0 | N16: =ROUNDDOWN(MIN($J$3/(B16+0.001),$K$3/(C16+0.001),$L$3/(D16+0.001)),0) -> 0
B17: 7 | C17: 29 | D17: 33 | E17: 0 | F17: 5.0499027 | G17: =(B17*$B$3)+(C17*$C$3)+(D17*$D$3) -> 17210593429 | J17: =$K$1*B17 -> 70 | K17: =$K$1*C17 -> 290 | L17: =$K$1*D17 -> 330 | M17: =$K$1*E17 -> 0 | N17: =ROUNDDOWN(MIN($J$3/(B17+0.001),$K$3/(C17+0.001),$L$3/(D17+0.001)),0) -> 0
... B27: 35 | C27: 0 | D27: 43 | E27: 0 | F27: 5.0495043 | G27: =(B27*$B$3)+(C27*$C$3)+(D27*$D$3) -> 14752271789 | J27: =$K$1*B27 -> 350 | K27: =$K$1*C27 -> 0 | L27: =$K$1*D27 -> 430 | M27: =$K$1*E27 -> 0 | N27: =ROUNDDOWN(MIN($J$3/(B27+0.001),$K$3/(C27+0.001),$L$3/(D27+0.001)),0) -> 1
B29: 126 | C29: 16 | D29: 0 | E29: 1 | F29: 5.0499275 | G29: =(B29*$B$3)+(C29*$C$3)+(D29*$D$3) -> 15382009384 | H29: =($G$3-G29)/E29 -> -727325328 | J29: =$K$1*B29 -> 1260 | K29: =$K$1*C29 -> 160 | L29: =$K$1*D29 -> 0 | M29: =$K$1*E29 -> 10 | N29: =ROUNDDOWN(MIN($J$3/(B29+0.001),$K$3/(C29+0.001),$L$3/(D29+0.001),$M$3/(E29+0.001)),0) -> 0
B30: 129 | C30: 13 | D30: 1 | E30: 1 | F30: 5.0499372 | G30: =(B30*$B$3)+(C30*$C$3)+(D30*$D$3) -> 15127520813 | H30: =($G$3-G30)/E30 -> -472836757 | J30: =$K$1*B30 -> 1290 | K30: =$K$1*C30 -> 130 | L30: =$K$1*D30 -> 10 | M30: =$K$1*E30 -> 10 | N30: =ROUNDDOWN(MIN($J$3/(B30+0.001),$K$3/(C30+0.001),$L$3/(D30+0.001),$M$3/(E30+0.001)),0) -> 0
B31: 132 | C31: 10 | D31: 2 | E31: 1 | F31: 5.0499468 | G31: =(B31*$B$3)+(C31*$C$3)+(D31*$D$3) -> 14873032242 | H31: =($G$3-G31)/E31 -> -218348186 | J31: =$K$1*B31 -> 1320 | K31: =$K$1*C31 -> 100 | L31: =$K$1*D31 -> 20 | M31: =$K$1*E31 -> 10 | N31: =ROUNDDOWN(MIN($J$3/(B31+0.001),$K$3/(C31+0.001),$L$3/(D31+0.001),$M$3/(E31+0.001)),0) -> 0
B32: 135 | C32: 7 | D32: 3 | E32: 1 | F32: 5.0499565 | G32: =(B32*$B$3)+(C32*$C$3)+(D32*$D$3) -> 14618543671 | H32: =($G$3-G32)/E32 -> 36140385 | J32: =$K$1*B32 -> 1350 | K32: =$K$1*C32 -> 70 | L32: =$K$1*D32 -> 30 | M32: =$K$1*E32 -> 10 | N32: =ROUNDDOWN(MIN($J$3/(B32+0.001),$K$3/(C32+0.001),$L$3/(D32+0.001),$M$3/(E32+0.001)),0) -> 0
B33: 138 | C33: 4 | D33: 4 | E33: 1 | F33: 5.0499661 | G33: =(B33*$B$3)+(C33*$C$3)+(D33*$D$3) -> 14364055100 | H33: =($G$3-G33)/E33 -> 290628956 | J33: =$K$1*B33 -> 1380 | K33: =$K$1*C33 -> 40 | L33: =$K$1*D33 -> 40 | M33: =$K$1*E33 -> 10 | N33: =ROUNDDOWN(MIN($J$3/(B33+0.001),$K$3/(C33+0.001),$L$3/(D33+0.001),$M$3/(E33+0.001)),0) -> 0
B34: 141 | C34: 1 | D34: 5 | E34: 1 | F34: 5.0499758 | G34: =(B34*$B$3)+(C34*$C$3)+(D34*$D$3) -> 14109566529 | H34: =($G$3-G34)/E34 -> 545117527 | J34: =$K$1*B34 -> 1410 | K34: =$K$1*C34 -> 10 | L34: =$K$1*D34 -> 50 | M34: =$K$1*E34 -> 10 | N34: =ROUNDDOWN(MIN($J$3/(B34+0.001),$K$3/(C34+0.001),$L$3/(D34+0.001),$M$3/(E34+0.001)),0) -> 0
B35: 1 | C35: 40 | D35: 26 | E35: 1 | F35: 5.0499303 | G35: =(B35*$B$3)+(C35*$C$3)+(D35*$D$3) -> 17683430186 | H35: =($G$3-G35)/E35 -> -3028746130 | J35: =$K$1*B35 -> 10 | K35: =$K$1*C35 -> 400 | L35: =$K$1*D35 -> 260 | M35: =$K$1*E35 -> 10 | N35: =ROUNDDOWN(MIN($J$3/(B35+0.001),$K$3/(C35+0.001),$L$3/(D35+0.001),$M$3/(E35+0.001)),0) -> 0
B36: 4 | C36: 37 | D36: 27 | E36: 1 | F36: 5.04994 | G36: =(B36*$B$3)+(C36*$C$3)+(D36*$D$3) -> 17428941615 | H36: =($G$3-G36)/E36 -> -2774257559 | J36: =$K$1*B36 -> 40 | K36: =$K$1*C36 -> 370 | L36: =$K$1*D36 -> 270 | M36: =$K$1*E36 -> 10 | N36: =ROUNDDOWN(MIN($J$3/(B36+0.001),$K$3/(C36+0.001),$L$3/(D36+0.001),$M$3/(E36+0.001)),0) -> 0
B37: 7 | C37: 34 | D37: 28 | E37: 1 | F37: 5.0499496 | G37: =(B37*$B$3)+(C37*$C$3)+(D37*$D$3) -> 17174453044 | H37: =($G$3-G37)/E37 -> -2519768988 | J37: =$K$1*B37 -> 70 | K37: =$K$1*C37 -> 340 | L37: =$K$1*D37 -> 280 | M37: =$K$1*E37 -> 10 | N37: =ROUNDDOWN(MIN($J$3/(B37+0.001),$K$3/(C37+0.001),$L$3/(D37+0.001),$M$3/(E37+0.001)),0) -> 0
B38: 10 | C38: 31 | D38: 29 | E38: 1 | F38: 5.0499593 | G38: =(B38*$B$3)+(C38*$C$3)+(D38*$D$3) -> 16919964473 | H38: =($G$3-G38)/E38 -> -2265280417 | J38: =$K$1*B38 -> 100 | K38: =$K$1*C38 -> 310 | L38: =$K$1*D38 -> 290 | M38: =$K$1*E38 -> 10 | N38: =ROUNDDOWN(MIN($J$3/(B38+0.001),$K$3/(C38+0.001),$L$3/(D38+0.001),$M$3/(E38+0.001)),0) -> 0
B39: 13 | C39: 28 | D39: 30 | E39: 1 | F39: 5.049969 | G39: =(B39*$B$3)+(C39*$C$3)+(D39*$D$3) -> 16665475902 | H39: =($G$3-G39)/E39 -> -2010791846 | J39: =$K$1*B39 -> 130 | K39: =$K$1*C39 -> 280 | L39: =$K$1*D39 -> 300 | M39: =$K$1*E39 -> 10 | N39: =ROUNDDOWN(MIN($J$3/(B39+0.001),$K$3/(C39+0.001),$L$3/(D39+0.001),$M$3/(E39+0.001)),0) -> 0
B40: 16 | C40: 25 | D40: 31 | E40: 1 | F40: 5.0499786 | G40: =(B40*$B$3)+(C40*$C$3)+(D40*$D$3) -> 16410987331 | H40: =($G$3-G40)/E40 -> -1756303275 | J40: =$K$1*B40 -> 160 | K40: =$K$1*C40 -> 250 | L40: =$K$1*D40 -> 310 | M40: =$K$1*E40 -> 10 | N40: =ROUNDDOWN(MIN($J$3/(B40+0.001),$K$3/(C40+0.001),$L$3/(D40+0.001),$M$3/(E40+0.001)),0) -> 0
... B298: 45 | C298: 1 | D298: 1 | E298: 23 | F298: 5.0495549 | G298: =(B298*$B$3)+(C298*$C$3)+(D298*$D$3) -> 4521193109 | H298: =($G$3-G298)/E298 -> 4.4058656e+08 | J298: =$K$1*B298 -> 450 | K298: =$K$1*C298 -> 10 | L298: =$K$1*D298 -> 10 | M298: =$K$1*E298 -> 230 | N298: =ROUNDDOWN(MIN($J$3/(B298+0.001),$K$3/(C298+0.001),$L$3/(D298+0.001),$M$3/(E298+0.001)),0) -> 0

Sheet API Raw
B2: Keep B3 at 0 when not in use to avoid unnecessary API queries.
B3: =UserBuildings!C2 -> 0 | C3: API Key: | D3: =UserBuildings!G2 -> d2f7070074a24ff4c55a55a0c0ab3faa699c437a4d87b | H3: Number of Days:
C5: Query ID: | E5: Output Type ID: | G5: Language ID: | H5: en
B6: =HYPERLINK("https://www.resources","https://www.resources") -> https://www.resources | C6: =HYPERLINK("http://-game.ch/","-game.ch/") -> -game.ch/ | D6: resapi/?q= | E6: [Query ID] | F6: &f= | G6: 0 | H6: &k= | I6: [API Key] | J6: &l= | K6: [Language ID] | L6: &d= | M6: [Number of Days]
B8: API Credits | D8: Factories | I8: Warehouses | O8: Special Buildings | S8: HQ
B9: =_xludf.textjoin("",TRUE,B6,C6,D6,0,F6,0,H6,D3,J6,$H$5,L6,10,"?") -> #NAME? | D9: =_xludf.textjoin("",TRUE,B6,C6,D6,1,F6,0,H6,D3,J6,$H$5,L6,10,"?") -> #NAME? | I9: =_xludf.textjoin("",TRUE,B6,C6,D6,2,F6,0,H6,D3,J6,$H$5,L6,10,"?") -> #NAME? | O9: =_xludf.textjoin("",TRUE,B6,C6,D6,3,F6,0,H6,D3,J6,$H$5,L6,10,"?") -> #NAME? | S9: =_xludf.textjoin("",TRUE,B6,C6,D6,4,F6,0,H6,D3,J6,$H$5,L6,10,"?") -> #NAME?
B10: =IFERROR(__xludf.DUMMYFUNCTION("if($B$3=1,importdata(B9),0)"),0) -> 0 | D10: =IFERROR(__xludf.DUMMYFUNCTION("if($B$3=1,importdata(D9),0)"),0) -> 0 | I10: =IFERROR(__xludf.DUMMYFUNCTION("if($B$3=1,importdata(I9),0)"),0) -> 0 | O10: =IFERROR(__xludf.DUMMYFUNCTION("if($B$3=1,importdata(O9),0)"),0) -> 0 | S10: =IFERROR(__xludf.DUMMYFUNCTION("if($B$3=1,importdata(S9),0)"),0) -> 0
O27: Mines
O28: =_xludf.textjoin("",TRUE,B6,C6,D6,51,F6,0,H6,D3,J6,$H$5,L6,10,"?") -> #NAME?
O29: =IFERROR(__xludf.DUMMYFUNCTION("if($B$3=0,0,importdata(O28))"),0) -> 0
N30: =Q30 -> 0
N31: =Q31 -> 0
N32: =Q32 -> 0
N33: =Q33 -> 0
N34: =Q34 -> 0
N35: =Q35 -> 0
N36: =Q36 -> 0
N37: =Q37 -> 0
N38: =Q38 -> 0
N39: =Q39 -> 0
N40: =Q40 -> 0
N41: =Q41 -> 0
... N49: =Q49 -> 0

Sheet Factory ROI
B2: Factory ROI | C2: Days to ROI | D2: ROI w/ TC | E2: Total Credit TC | F2: Daily Increase | G2: Produce Increase | H2: Total Credit Upgrade | I2: Resource 1 | J2: WH | K2: WH | L2: Cash | M2: Resource 2 | N2: WH | O2: WH | P2: Cash | Q2: Resource 3 | R2: WH | S2: WH | T2: Cash | U2: Cash
B3: Brick Factory | C3: =IF(H3/G3<=0,"NO",H3/G3/24) -> #N/A | D3: =IF(E3/G3<=0,"NO",E3/G3/24) -> #N/A | E3: =H3*(1.15-UserBuildings!$T$16*0.01) -> 7.6278226e+10 | F3: =G3*24 -> #N/A | G3: =Static!E4*'Supply Chain'!N33 -> #N/A | H3: =(I3*'Supply Chain'!E33)+U3+L3 -> 72645930000 | I3: =((UserBuildings!$M5+1)^2)*Static!$O4 -> 25489800 | J3: =ROUNDUP(SQRT(I3/5000),0) -> 72 | K3: =VLOOKUP("Clay",TblUserWarehouse,2,FALSE) -> 126 | L3: =IF(K3=0,0,IF((J3-K3)<0,0,((416666+2/3)*J3^3-625000*J3^2+(208333+1/3)*J3)-((416666+2/3)*K3^3-625000*K3^2+(208333+1/3)*K3))) -> 0 | M3: - | N3: - | O3: - | P3: - | Q3: - | R3: - | S3: - | T3: - | U3: =((UserBuildings!$M5+1)^2)*Static!$O5 -> 63724500000
B4: Concrete Factory | C4: =IF(H4/G4<=0,"NO",H4/G4/24) -> #N/A | D4: =IF(E4/G4<=0,"NO",E4/G4/24) -> #N/A | E4: =H4*(1.15-UserBuildings!$T$16*0.01) -> #N/A | F4: =G4*24 -> 251928000 | G4: =Static!E5*'Supply Chain'!N34 -> 10497000 | H4: =(I4*'Supply Chain'!L33)+(M4*'Supply Chain'!E33)+(Q4*'Supply Chain'!E34)+U4+SUM(L4,P4,T4) -> #N/A | I4: =((UserBuildings!$M6+1)^2)*Static!$O6 -> 24649000 | J4: =ROUNDUP(SQRT(I4/5000),0) -> 71 | K4: =VLOOKUP("Bricks",TblUserWarehouse,2,FALSE) -> 190 | L4: =IF(K4=0,0,IF((J4-K4)<0,0,((416666+2/3)*J4^3-625000*J4^2+(208333+1/3)*J4)-((416666+2/3)*K4^3-625000*K4^2+(208333+1/3)*K4))) -> 0 | M4: =((UserBuildings!$M6+1)^2)*Static!$O7 -> 24649000 | N4: =ROUNDUP(SQRT(M4/5000),0) -> 71 | O4: =VLOOKUP("Clay",TblUserWarehouse,2,FALSE) -> 126 | P4: =IF(O4=0,0,IF((N4-O4)<0,0,((416666+2/3)*N4^3-625000*N4^2+(208333+1/3)*N4)-((416666+2/3)*O4^3-625000*O4^2+(208333+1/3)*O4))) -> 0 | Q4: =((UserBuildings!$M6+1)^2)*Static!$O8 -> 12324500 | R4: =ROUNDUP(SQRT(Q4/5000),0) -> 50 | S4: =VLOOKUP("Limestone",TblUserWarehouse,2,FALSE) -> 64 | T4: =IF(S4=0,0,IF((R4-S4)<0,0,((416666+2/3)*R4^3-625000*R4^2+(208333+1/3)*R4)-((416666+2/3)*S4^3-625000*S4^2+(208333+1/3)*S4))) -> 0 | U4: =((UserBuildings!$M6+1)^2)*Static!$O9 -> 49298000000
B5: Fertilizer Factory | C5: =IF(H5/G5<=0,"NO",H5/G5/24) -> #N/A | D5: =IF(E5/G5<=0,"NO",E5/G5/24) -> #N/A | E5: =H5*(1.15-UserBuildings!$T$16*0.01) -> #N/A | F5: =G5*24 -> 51994800 | G5: =Static!E6*'Supply Chain'!N35 -> 2166450 | H5: =(I5*'Supply Chain'!L33)+(M5*'Supply Chain'!L34)+(Q5*'Supply Chain'!E34)+U5+SUM(L5,P5,T5) -> #N/A | I5: =((UserBuildings!$M7+1)^2)*Static!$O10 -> 10562500 | J5: =ROUNDUP(SQRT(I5/5000),0) -> 46 | K5: =VLOOKUP("Bricks",TblUserWarehouse,2,FALSE) -> 190 | L5: =IF(K5=0,0,IF((J5-K5)<0,0,((416666+2/3)*J5^3-625000*J5^2+(208333+1/3)*J5)-((416666+2/3)*K5^3-625000*K5^2+(208333+1/3)*K5))) -> 0 | M5: =((UserBuildings!$M7+1)^2)*Static!$O11 -> 21125000 | N5: =ROUNDUP(SQRT(M5/5000),0) -> 65 | O5: =VLOOKUP("Concrete",TblUserWarehouse,2,FALSE) -> 156 | P5: =IF(O5=0,0,IF((N5-O5)<0,0,((416666+2/3)*N5^3-625000*N5^2+(208333+1/3)*N5)-((416666+2/3)*O5^3-625000*O5^2+(208333+1/3)*O5))) -> 0 | Q5: =((UserBuildings!$M7+1)^2)*Static!$O12 -> 2112500 | R5: =ROUNDUP(SQRT(Q5/5000),0) -> 21 | S5: =VLOOKUP("Limestone",TblUserWarehouse,2,FALSE) -> 64 | T5: =IF(S5=0,0,IF((R5-S5)<0,0,((416666+2/3)*R5^3-625000*R5^2+(208333+1/3)*R5)-((416666+2/3)*S5^3-625000*S5^2+(208333+1/3)*S5))) -> 0 | U5: =((UserBuildings!$M7+1)^2)*Static!$O13 -> 16900000000
B6: Ironworks | C6: =IF(H6/G6<=0,"NO",H6/G6/24) -> #N/A | D6: =IF(E6/G6<=0,"NO",E6/G6/24) -> #N/A | E6: =H6*(1.15-UserBuildings!$T$16*0.01) -> #N/A | F6: =G6*24 -> 165002400 | G6: =Static!E7*'Supply Chain'!N36 -> 6875100 | H6: =(I6*'Supply Chain'!L33)+(M6*'Supply Chain'!L34)+(Q6*'Supply Chain'!E34)+U6+SUM(L6,P6,T6) -> #N/A | I6: =((UserBuildings!$M8+1)^2)*Static!$O14 -> 2178000 | J6: =ROUNDUP(SQRT(I6/5000),0) -> 21 | K6: =VLOOKUP("Bricks",TblUserWarehouse,2,FALSE) -> 190 | L6: =IF(K6=0,0,IF((J6-K6)<0,0,((416666+2/3)*J6^3-625000*J6^2+(208333+1/3)*J6)-((416666+2/3)*K6^3-625000*K6^2+(208333+1/3)*K6))) -> 0 | M6: =((UserBuildings!$M8+1)^2)*Static!$O15 -> 39204000 | N6: =ROUNDUP(SQRT(M6/5000),0) -> 89 | O6: =VLOOKUP("Concrete",TblUserWarehouse,2,FALSE) -> 156 | P6: =IF(O6=0,0,IF((N6-O6)<0,0,((416666+2/3)*N6^3-625000*N6^2+(208333+1/3)*N6)-((416666+2/3)*O6^3-625000*O6^2+(208333+1/3)*O6))) -> 0 | Q6: =((UserBuildings!$M8+1)^2)*Static!$O16 -> 13068000 | R6: =ROUNDUP(SQRT(Q6/5000),0) -> 52 | S6: =VLOOKUP("Limestone",TblUserWarehouse,2,FALSE) -> 64 | T6: =IF(S6=0,0,IF((R6-S6)<0,0,((416666+2/3)*R6^3-625000*R6^2+(208333+1/3)*R6)-((416666+2/3)*S6^3-625000*S6^2+(208333+1/3)*S6))) -> 0 | U6: =((UserBuildings!$M8+1)^2)*Static!$O17 -> 43560000000
B7: Oil Refinery | C7: =IF(H7/G7<=0,"NO",H7/G7/24) -> 1154.2622 | D7: =IF(E7/G7<=0,"NO",E7/G7/24) -> 1211.9753 | E7: =H7*(1.15-UserBuildings!$T$16*0.01) -> 5.4949601e+11 | F7: =G7*24 -> 453388800 | G7: =Static!E8*'Supply Chain'!N37 -> 18891200 | H7: =(I7*'Supply Chain'!L36)+(M7*'Supply Chain'!L34)+(Q7*'Supply Chain'!E35)+U7+SUM(L7,P7,T7) -> 523329536000 | I7: =((UserBuildings!$M9+1)^2)*Static!$O18 -> 2048000 | J7: =ROUNDUP(SQRT(I7/5000),0) -> 21 | K7: =VLOOKUP("Steel",TblUserWarehouse,2,FALSE) -> 64 | L7: =IF(K7=0,0,IF((J7-K7)<0,0,((416666+2/3)*J7^3-625000*J7^2+(208333+1/3)*J7)-((416666+2/3)*K7^3-625000*K7^2+(208333+1/3)*K7))) -> 0 | M7: =((UserBuildings!$M9+1)^2)*Static!$O19 -> 65536000 | N7: =ROUNDUP(SQRT(M7/5000),0) -> 115 | O7: =VLOOKUP("Concrete",TblUserWarehouse,2,FALSE) -> 156 | P7: =IF(O7=0,0,IF((N7-O7)<0,0,((416666+2/3)*N7^3-625000*N7^2+(208333+1/3)*N7)-((416666+2/3)*O7^3-625000*O7^2+(208333+1/3)*O7))) -> 0 | Q7: =((UserBuildings!$M9+1)^2)*Static!$O20 -> 2048000 | R7: =ROUNDUP(SQRT(Q7/5000),0) -> 21 | S7: =VLOOKUP("Gravel",TblUserWarehouse,2,FALSE) -> 60 | T7: =IF(S7=0,0,IF((R7-S7)<0,0,((416666+2/3)*R7^3-625000*R7^2+(208333+1/3)*R7)-((416666+2/3)*S7^3-625000*S7^2+(208333+1/3)*S7))) -> 0 | U7: =((UserBuildings!$M9+1)^2)*Static!$O21 -> 81920000000
B8: Glazier's Worshop | C8: =IF(H8/G8<=0,"NO",H8/G8/24) -> #N/A | D8: =IF(E8/G8<=0,"NO",E8/G8/24) -> #N/A | E8: =H8*(1.15-UserBuildings!$T$16*0.01) -> #N/A | F8: =G8*24 -> 263842560 | G8: =Static!E9*'Supply Chain'!N38 -> 10993440 | H8: =(I8*'Supply Chain'!L33)+(M8*'Supply Chain'!L34)+(Q8*'Supply Chain'!E34)+U8+SUM(L8,P8,T8) -> #N/A | I8: =((UserBuildings!$M10+1)^2)*Static!$O22 -> 6912000 | J8: =ROUNDUP(SQRT(I8/5000),0) -> 38 | K8: =VLOOKUP("Bricks",TblUserWarehouse,2,FALSE) -> 190 | L8: =IF(K8=0,0,IF((J8-K8)<0,0,((416666+2/3)*J8^3-625000*J8^2+(208333+1/3)*J8)-((416666+2/3)*K8^3-625000*K8^2+(208333+1/3)*K8))) -> 0 | M8: =((UserBuildings!$M10+1)^2)*Static!$O23 -> 57600000 | N8: =ROUNDUP(SQRT(M8/5000),0) -> 108 | O8: =VLOOKUP("Concrete",TblUserWarehouse,2,FALSE) -> 156 | P8: =IF(O8=0,0,IF((N8-O8)<0,0,((416666+2/3)*N8^3-625000*N8^2+(208333+1/3)*N8)-((416666+2/3)*O8^3-625000*O8^2+(208333+1/3)*O8))) -> 0 | Q8: =((UserBuildings!$M10+1)^2)*Static!$O24 -> 345600 | R8: =ROUNDUP(SQRT(Q8/5000),0) -> 9 | S8: =VLOOKUP("Limestone",TblUserWarehouse,2,FALSE) -> 64 | T8: =IF(S8=0,0,IF((R8-S8)<0,0,((416666+2/3)*R8^3-625000*R8^2+(208333+1/3)*R8)-((416666+2/3)*S8^3-625000*S8^2+(208333+1/3)*S8))) -> 0 | U8: =((UserBuildings!$M10+1)^2)*Static!$O25 -> 46080000000
B9: Copper Refinery | C9: =IF(H9/G9<=0,"NO",H9/G9/24) -> 844.36168 | D9: =IF(E9/G9<=0,"NO",E9/G9/24) -> 886.57977 | E9: =H9*(1.15-UserBuildings!$T$16*0.01) -> 4.7356722e+11 | F9: =G9*24 -> 534150720 | G9: =Static!E10*'Supply Chain'!N39 -> 22256280 | H9: =(I9*'Supply Chain'!L36)+(M9*'Supply Chain'!L34)+(Q9*'Supply Chain'!L38)+U9+SUM(L9,P9,T9) -> 451016400500 | I9: =((UserBuildings!$M11+1)^2)*Static!$O26 -> 1849000 | J9: =ROUNDUP(SQRT(I9/5000),0) -> 20 | K9: =VLOOKUP("Steel",TblUserWarehouse,2,FALSE) -> 64 | L9: =IF(K9=0,0,IF((J9-K9)<0,0,((416666+2/3)*J9^3-625000*J9^2+(208333+1/3)*J9)-((416666+2/3)*K9^3-625000*K9^2+(208333+1/3)*K9))) -> 0 | M9: =((UserBuildings!$M11+1)^2)*Static!$O27 -> 46225000 | N9: =ROUNDUP(SQRT(M9/5000),0) -> 97 | O9: =VLOOKUP("Concrete",TblUserWarehouse,2,FALSE) -> 156 | P9: =IF(O9=0,0,IF((N9-O9)<0,0,((416666+2/3)*N9^3-625000*N9^2+(208333+1/3)*N9)-((416666+2/3)*O9^3-625000*O9^2+(208333+1/3)*O9))) -> 0 | Q9: =((UserBuildings!$M11+1)^2)*Static!$O28 -> 924500 | R9: =ROUNDUP(SQRT(Q9/5000),0) -> 14 | S9: =VLOOKUP("Glass",TblUserWarehouse,2,FALSE) -> 84 | T9: =IF(S9=0,0,IF((R9-S9)<0,0,((416666+2/3)*R9^3-625000*R9^2+(208333+1/3)*R9)-((416666+2/3)*S9^3-625000*S9^2+(208333+1/3)*S9))) -> 0 | U9: =((UserBuildings!$M11+1)^2)*Static!$O29 -> 73960000000
B10: Insecticide Factory | C10: =IF(H10/G10<=0,"NO",H10/G10/24) -> 3116.2377 | D10: =IF(E10/G10<=0,"NO",E10/G10/24) -> 3272.0496 | E10: =H10*(1.15-UserBuildings!$T$16*0.01) -> 4.8216137e+11 | F10: =G10*24 -> 147357600 | G10: =Static!E11*'Supply Chain'!N40 -> 6139900 | H10: =(I10*'Supply Chain'!L36)+(M10*'Supply Chain'!L34)+(Q10*'Supply Chain'!L39)+U10+SUM(L10,P10,T10) -> 459201307500 | I10: =((UserBuildings!$M12+1)^2)*Static!$O30 -> 3042000 | J10: =ROUNDUP(SQRT(I10/5000),0) -> 25 | K10: =VLOOKUP("Steel",TblUserWarehouse,2,FALSE) -> 64 | L10: =IF(K10=0,0,IF((J10-K10)<0,0,((416666+2/3)*J10^3-625000*J10^2+(208333+1/3)*J10)-((416666+2/3)*K10^3-625000*K10^2+(208333+1/3)*K10))) -> 0 | M10: =((UserBuildings!$M12+1)^2)*Static!$O31 -> 38025000 | N10: =ROUNDUP(SQRT(M10/5000),0) -> 88 | O10: =VLOOKUP("Concrete",TblUserWarehouse,2,FALSE) -> 156 | P10: =IF(O10=0,0,IF((N10-O10)<0,0,((416666+2/3)*N10^3-625000*N10^2+(208333+1/3)*N10)-((416666+2/3)*O10^3-625000*O10^2+(208333+1/3)*O10))) -> 0 | Q10: =((UserBuildings!$M12+1)^2)*Static!$O32 -> 760500 | R10: =ROUNDUP(SQRT(Q10/5000),0) -> 13 | S10: =VLOOKUP("Copper",TblUserWarehouse,2,FALSE) -> 35 | T10: =IF(S10=0,0,IF((R10-S10)<0,0,((416666+2/3)*R10^3-625000*R10^2+(208333+1/3)*R10)-((416666+2/3)*S10^3-625000*S10^2+(208333+1/3)*S10))) -> 0 | U10: =((UserBuildings!$M12+1)^2)*Static!$O33 -> 45630000000
B11: Aluminium Factory | C11: =IF(H11/G11<=0,"NO",H11/G11/24) -> 1278.4535 | D11: =IF(E11/G11<=0,"NO",E11/G11/24) -> 1342.3762 | E11: =H11*(1.15-UserBuildings!$T$16*0.01) -> 8.5416878e+11 | F11: =G11*24 -> 636311040 | G11: =Static!E12*'Supply Chain'!N41 -> 26512960 | H11: =(I11*'Supply Chain'!L36)+(M11*'Supply Chain'!L34)+(Q11*'Supply Chain'!L38)+U11+SUM(L11,P11,T11) -> 813494071500 | I11: =((UserBuildings!$M13+1)^2)*Static!$O34 -> 5522500 | J11: =ROUNDUP(SQRT(I11/5000),0) -> 34 | K11: =VLOOKUP("Steel",TblUserWarehouse,2,FALSE) -> 64 | L11: =IF(K11=0,0,IF((J11-K11)<0,0,((416666+2/3)*J11^3-625000*J11^2+(208333+1/3)*J11)-((416666+2/3)*K11^3-625000*K11^2+(208333+1/3)*K11))) -> 0 | M11: =((UserBuildings!$M13+1)^2)*Static!$O35 -> 55225000 | N11: =ROUNDUP(SQRT(M11/5000),0) -> 106 | O11: =VLOOKUP("Concrete",TblUserWarehouse,2,FALSE) -> 156 | P11: =IF(O11=0,0,IF((N11-O11)<0,0,((416666+2/3)*N11^3-625000*N11^2+(208333+1/3)*N11)-((416666+2/3)*O11^3-625000*O11^2+(208333+1/3)*O11))) -> 0 | Q11: =((UserBuildings!$M13+1)^2)*Static!$O36 -> 3313500 | R11: =ROUNDUP(SQRT(Q11/5000),0) -> 26 | S11: =VLOOKUP("Glass",TblUserWarehouse,2,FALSE) -> 84 | T11: =IF(S11=0,0,IF((R11-S11)<0,0,((416666+2/3)*R11^3-625000*R11^2+(208333+1/3)*R11)-((416666+2/3)*S11^3-625000*S11^2+(208333+1/3)*S11))) -> 0 | U11: =((UserBuildings!$M13+1)^2)*Static!$O37 -> 88360000000
B12: Plastic Factory | C12: =IF(H12/G12<=0,"NO",H12/G12/24) -> 2089.0572 | D12: =IF(E12/G12<=0,"NO",E12/G12/24) -> 2193.51 | E12: =H12*(1.15-UserBuildings!$T$16*0.01) -> 4.2681634e+11 | F12: =G12*24 -> 194581440 | G12: =Static!E13*'Supply Chain'!N42 -> 8107560 | H12: =(I12*'Supply Chain'!L36)+(M12*'Supply Chain'!L34)+(Q12*'Supply Chain'!L41)+U12+SUM(L12,P12,T12) -> 406491750000 | I12: =((UserBuildings!$M14+1)^2)*Static!$O38 -> 1764000 | J12: =ROUNDUP(SQRT(I12/5000),0) -> 19 | K12: =VLOOKUP("Steel",TblUserWarehouse,2,FALSE) -> 64 | L12: =IF(K12=0,0,IF((J12-K12)<0,0,((416666+2/3)*J12^3-625000*J12^2+(208333+1/3)*J12)-((416666+2/3)*K12^3-625000*K12^2+(208333+1/3)*K12))) -> 0 | M12: =((UserBuildings!$M14+1)^2)*Static!$O39 -> 28224000 | N12: =ROUNDUP(SQRT(M12/5000),0) -> 76 | O12: =VLOOKUP("Concrete",TblUserWarehouse,2,FALSE) -> 156 | P12: =IF(O12=0,0,IF((N12-O12)<0,0,((416666+2/3)*N12^3-625000*N12^2+(208333+1/3)*N12)-((416666+2/3)*O12^3-625000*O12^2+(208333+1/3)*O12))) -> 0 | Q12: =((UserBuildings!$M14+1)^2)*Static!$O40 -> 882000 | R12: =ROUNDUP(SQRT(Q12/5000),0) -> 14 | S12: =VLOOKUP("Aluminium",TblUserWarehouse,2,FALSE) -> 69 | T12: =IF(S12=0,0,IF((R12-S12)<0,0,((416666+2/3)*R12^3-625000*R12^2+(208333+1/3)*R12)-((416666+2/3)*S12^3-625000*S12^2+(208333+1/3)*S12))) -> 0 | U12: =((UserBuildings!$M14+1)^2)*Static!$O41 -> 88200000000
B13: Lithium Refinery | C13: =IF(H13/G13<=0,"NO",H13/G13/24) -> 3051.5748 | D13: =IF(E13/G13<=0,"NO",E13/G13/24) -> 3204.1535 | E13: =H13*(1.15-UserBuildings!$T$16*0.01) -> 1.0548137e+12 | F13: =G13*24 -> 329202000 | G13: =Static!E14*'Supply Chain'!N43 -> 13716750 | H13: =(I13*'Supply Chain'!L36)+(M13*'Supply Chain'!L34)+(Q13*'Supply Chain'!L38)+U13+SUM(L13,P13,T13) -> 1004584521000 | I13: =((UserBuildings!$M15+1)^2)*Static!$O42 -> 13690000 | J13: =ROUNDUP(SQRT(I13/5000),0) -> 53 | K13: =VLOOKUP("Steel",TblUserWarehouse,2,FALSE) -> 64 | L13: =IF(K13=0,0,IF((J13-K13)<0,0,((416666+2/3)*J13^3-625000*J13^2+(208333+1/3)*J13)-((416666+2/3)*K13^3-625000*K13^2+(208333+1/3)*K13))) -> 0 | M13: =((UserBuildings!$M15+1)^2)*Static!$O43 -> 34225000 | N13: =ROUNDUP(SQRT(M13/5000),0) -> 83 | O13: =VLOOKUP("Concrete",TblUserWarehouse,2,FALSE) -> 156 | P13: =IF(O13=0,0,IF((N13-O13)<0,0,((416666+2/3)*N13^3-625000*N13^2+(208333+1/3)*N13)-((416666+2/3)*O13^3-625000*O13^2+(208333+1/3)*O13))) -> 0 | Q13: =((UserBuildings!$M15+1)^2)*Static!$O44 -> 1369000 | R13: =ROUNDUP(SQRT(Q13/5000),0) -> 17 | S13: =VLOOKUP("Glass",TblUserWarehouse,2,FALSE) -> 84 | T13: =IF(S13=0,0,IF((R13-S13)<0,0,((416666+2/3)*R13^3-625000*R13^2+(208333+1/3)*R13)-((416666+2/3)*S13^3-625000*S13^2+(208333+1/3)*S13))) -> 0 | U13: =((UserBuildings!$M15+1)^2)*Static!$O45 -> 82140000000
B14: Battery Factory | C14: =IF(H14/G14<=0,"NO",H14/G14/24) -> 1468.6735 | D14: =IF(E14/G14<=0,"NO",E14/G14/24) -> 1542.1071 | E14: =H14*(1.15-UserBuildings!$T$16*0.01) -> 4.9968712e+11 | F14: =G14*24 -> 324028800 | G14: =Static!E15*'Supply Chain'!N44 -> 13501200 | H14: =(I14*'Supply Chain'!L41)+(M14*'Supply Chain'!L34)+(Q14*'Supply Chain'!L38)+U14+SUM(L14,P14,T14) -> 475892496000 | I14: =((UserBuildings!$M16+1)^2)*Static!$O46 -> 3240000 | J14: =ROUNDUP(SQRT(I14/5000),0) -> 26 | K14: =VLOOKUP("Aluminium",TblUserWarehouse,2,FALSE) -> 69 | L14: =IF(K14=0,0,IF((J14-K14)<0,0,((416666+2/3)*J14^3-625000*J14^2+(208333+1/3)*J14)-((416666+2/3)*K14^3-625000*K14^2+(208333+1/3)*K14))) -> 0 | M14: =((UserBuildings!$M16+1)^2)*Static!$O47 -> 6480000 | N14: =ROUNDUP(SQRT(M14/5000),0) -> 36 | O14: =VLOOKUP("Concrete",TblUserWarehouse,2,FALSE) -> 156 | P14: =IF(O14=0,0,IF((N14-O14)<0,0,((416666+2/3)*N14^3-625000*N14^2+(208333+1/3)*N14)-((416666+2/3)*O14^3-625000*O14^2+(208333+1/3)*O14))) -> 0 | Q14: =((UserBuildings!$M16+1)^2)*Static!$O48 -> 1944000 | R14: =ROUNDUP(SQRT(Q14/5000),0) -> 20 | S14: =VLOOKUP("Glass",TblUserWarehouse,2,FALSE) -> 84 | T14: =IF(S14=0,0,IF((R14-S14)<0,0,((416666+2/3)*R14^3-625000*R14^2+(208333+1/3)*R14)-((416666+2/3)*S14^3-625000*S14^2+(208333+1/3)*S14))) -> 0 | U14: =((UserBuildings!$M16+1)^2)*Static!$O49 -> 32400000000
B15: Arms Factory | C15: =IF(H15/G15<=0,"NO",H15/G15/24) -> #N/A | D15: =IF(E15/G15<=0,"NO",E15/G15/24) -> #N/A | E15: =H15*(1.15-UserBuildings!$T$16*0.01) -> #N/A | F15: =G15*24 -> #N/A | G15: =Static!E16*'Supply Chain'!N45 -> #N/A | H15: =(I15*'Supply Chain'!L33)+(M15*'Supply Chain'!L34)+(Q15*'Supply Chain'!L38)+U15+SUM(L15,P15,T15) -> #N/A | I15: =((UserBuildings!$M17+1)^2)*Static!$O50 -> 220500000 | J15: =ROUNDUP(SQRT(I15/5000),0) -> 210 | K15: =VLOOKUP("Bricks",TblUserWarehouse,2,FALSE) -> 190 | L15: =IF(K15=0,0,IF((J15-K15)<0,0,((416666+2/3)*J15^3-625000*J15^2+(208333+1/3)*J15)-((416666+2/3)*K15^3-625000*K15^2+(208333+1/3)*K15))) -> 9.958375e+11 | M15: =((UserBuildings!$M17+1)^2)*Static!$O51 -> 22050000 | N15: =ROUNDUP(SQRT(M15/5000),0) -> 67 | O15: =VLOOKUP("Concrete",TblUserWarehouse,2,FALSE) -> 156 | P15: =IF(O15=0,0,IF((N15-O15)<0,0,((416666+2/3)*N15^3-625000*N15^2+(208333+1/3)*N15)-((416666+2/3)*O15^3-625000*O15^2+(208333+1/3)*O15))) -> 0 | Q15: =((UserBuildings!$M17+1)^2)*Static!$O52 -> 4410000 | R15: =ROUNDUP(SQRT(Q15/5000),0) -> 30 | S15: =VLOOKUP("Glass",TblUserWarehouse,2,FALSE) -> 84 | T15: =IF(S15=0,0,IF((R15-S15)<0,0,((416666+2/3)*R15^3-625000*R15^2+(208333+1/3)*R15)-((416666+2/3)*S15^3-625000*S15^2+(208333+1/3)*S15))) -> 0 | U15: =((UserBuildings!$M17+1)^2)*Static!$O53 -> 88200000000
B16: Silicon Refinery | C16: =IF(H16/G16<=0,"NO",H16/G16/24) -> 472.13148 | D16: =IF(E16/G16<=0,"NO",E16/G16/24) -> 495.73805 | E16: =H16*(1.15-UserBuildings!$T$16*0.01) -> 1.7317597e+10 | F16: =G16*24 -> 34932960 | G16: =Static!E17*'Supply Chain'!N46 -> 1455540 | H16: =(I16*'Supply Chain'!L36)+(M16*'Supply Chain'!L34)+(Q16*'Supply Chain'!L38)+U16+SUM(L16,P16,T16) -> 16492950000 | I16: =((UserBuildings!$M18+1)^2)*Static!$O54 -> 43200 | J16: =ROUNDUP(SQRT(I16/5000),0) -> 3 | K16: =VLOOKUP("Steel",TblUserWarehouse,2,FALSE) -> 64 | L16: =IF(K16=0,0,IF((J16-K16)<0,0,((416666+2/3)*J16^3-625000*J16^2+(208333+1/3)*J16)-((416666+2/3)*K16^3-625000*K16^2+(208333+1/3)*K16))) -> 0 | M16: =((UserBuildings!$M18+1)^2)*Static!$O55 -> 720000 | N16: =ROUNDUP(SQRT(M16/5000),0) -> 12 | O16: =VLOOKUP("Concrete",TblUserWarehouse,2,FALSE) -> 156 | P16: =IF(O16=0,0,IF((N16-O16)<0,0,((416666+2/3)*N16^3-625000*N16^2+(208333+1/3)*N16)-((416666+2/3)*O16^3-625000*O16^2+(208333+1/3)*O16))) -> 0 | Q16: =((UserBuildings!$M18+1)^2)*Static!$O56 -> 54000 | R16: =ROUNDUP(SQRT(Q16/5000),0) -> 4 | S16: =VLOOKUP("Glass",TblUserWarehouse,2,FALSE) -> 84 | T16: =IF(S16=0,0,IF((R16-S16)<0,0,((416666+2/3)*R16^3-625000*R16^2+(208333+1/3)*R16)-((416666+2/3)*S16^3-625000*S16^2+(208333+1/3)*S16))) -> 0 | U16: =((UserBuildings!$M18+1)^2)*Static!$O57 -> 7920000000
B17: Electronics Factory | C17: =IF(H17/G17<=0,"NO",H17/G17/24) -> 8422.0072 | D17: =IF(E17/G17<=0,"NO",E17/G17/24) -> 8843.1075 | E17: =H17*(1.15-UserBuildings!$T$16*0.01) -> 1.2959977e+12 | F17: =G17*24 -> 146554560 | G17: =Static!E18*'Supply Chain'!N47 -> 6106440 | H17: =(I17*'Supply Chain'!L41)+(M17*'Supply Chain'!L34)+(Q17*'Supply Chain'!L38)+U17+SUM(L17,P17,T17) -> 1234283555000 | I17: =((UserBuildings!$M19+1)^2)*Static!$O58 -> 1369000 | J17: =ROUNDUP(SQRT(I17/5000),0) -> 17 | K17: =VLOOKUP("Aluminium",TblUserWarehouse,2,FALSE) -> 69 | L17: =IF(K17=0,0,IF((J17-K17)<0,0,((416666+2/3)*J17^3-625000*J17^2+(208333+1/3)*J17)-((416666+2/3)*K17^3-625000*K17^2+(208333+1/3)*K17))) -> 0 | M17: =((UserBuildings!$M19+1)^2)*Static!$O59 -> 27380000 | N17: =ROUNDUP(SQRT(M17/5000),0) -> 74 | O17: =VLOOKUP("Concrete",TblUserWarehouse,2,FALSE) -> 156 | P17: =IF(O17=0,0,IF((N17-O17)<0,0,((416666+2/3)*N17^3-625000*N17^2+(208333+1/3)*N17)-((416666+2/3)*O17^3-625000*O17^2+(208333+1/3)*O17))) -> 0 | Q17: =((UserBuildings!$M19+1)^2)*Static!$O60 -> 10952000 | R17: =ROUNDUP(SQRT(Q17/5000),0) -> 47 | S17: =VLOOKUP("Glass",TblUserWarehouse,2,FALSE) -> 84 | T17: =IF(S17=0,0,IF((R17-S17)<0,0,((416666+2/3)*R17^3-625000*R17^2+(208333+1/3)*R17)-((416666+2/3)*S17^3-625000*S17^2+(208333+1/3)*S17))) -> 0 | U17: =((UserBuildings!$M19+1)^2)*Static!$O61 -> 410700000000
B18: Titanium Refinery | C18: =IF(H18/G18<=0,"NO",H18/G18/24) -> 2125.1939 | D18: =IF(E18/G18<=0,"NO",E18/G18/24) -> 2231.4536 | E18: =H18*(1.15-UserBuildings!$T$16*0.01) -> 5.7172627e+11 | F18: =G18*24 -> 256212480 | G18: =Static!E19*'Supply Chain'!N48 -> 10675520 | H18: =(I18*'Supply Chain'!L36)+(M18*'Supply Chain'!L34)+(Q18*'Supply Chain'!L38)+U18+SUM(L18,P18,T18) -> 544501210000 | I18: =((UserBuildings!$M20+1)^2)*Static!$O62 -> 4840000 | J18: =ROUNDUP(SQRT(I18/5000),0) -> 32 | K18: =VLOOKUP("Steel",TblUserWarehouse,2,FALSE) -> 64 | L18: =IF(K18=0,0,IF((J18-K18)<0,0,((416666+2/3)*J18^3-625000*J18^2+(208333+1/3)*J18)-((416666+2/3)*K18^3-625000*K18^2+(208333+1/3)*K18))) -> 0 | M18: =((UserBuildings!$M20+1)^2)*Static!$O63 -> 14520000 | N18: =ROUNDUP(SQRT(M18/5000),0) -> 54 | O18: =VLOOKUP("Concrete",TblUserWarehouse,2,FALSE) -> 156 | P18: =IF(O18=0,0,IF((N18-O18)<0,0,((416666+2/3)*N18^3-625000*N18^2+(208333+1/3)*N18)-((416666+2/3)*O18^3-625000*O18^2+(208333+1/3)*O18))) -> 0 | Q18: =((UserBuildings!$M20+1)^2)*Static!$O64 -> 1210000 | R18: =ROUNDUP(SQRT(Q18/5000),0) -> 16 | S18: =VLOOKUP("Glass",TblUserWarehouse,2,FALSE) -> 84 | T18: =IF(S18=0,0,IF((R18-S18)<0,0,((416666+2/3)*R18^3-625000*R18^2+(208333+1/3)*R18)-((416666+2/3)*S18^3-625000*S18^2+(208333+1/3)*S18))) -> 0 | U18: =((UserBuildings!$M20+1)^2)*Static!$O65 -> 169400000000
B19: Medical Tech | C19: =IF(H19/G19<=0,"NO",H19/G19/24) -> 827.75419 | D19: =IF(E19/G19<=0,"NO",E19/G19/24) -> 869.1419 | E19: =H19*(1.15-UserBuildings!$T$16*0.01) -> 1.1844271e+12 | F19: =G19*24 -> 1362754560 | G19: =Static!E20*'Supply Chain'!N49 -> 56781440 | H19: =(I19*'Supply Chain'!L36)+(M19*'Supply Chain'!L34)+(Q19*'Supply Chain'!L42)+U19+SUM(L19,P19,T19) -> 1128025800000 | I19: =((UserBuildings!$M21+1)^2)*Static!$O66 -> 8550000 | J19: =ROUNDUP(SQRT(I19/5000),0) -> 42 | K19: =VLOOKUP("Steel",TblUserWarehouse,2,FALSE) -> 64 | L19: =IF(K19=0,0,IF((J19-K19)<0,0,((416666+2/3)*J19^3-625000*J19^2+(208333+1/3)*J19)-((416666+2/3)*K19^3-625000*K19^2+(208333+1/3)*K19))) -> 0 | M19: =((UserBuildings!$M21+1)^2)*Static!$O67 -> 36000000 | N19: =ROUNDUP(SQRT(M19/5000),0) -> 85 | O19: =VLOOKUP("Concrete",TblUserWarehouse,2,FALSE) -> 156 | P19: =IF(O19=0,0,IF((N19-O19)<0,0,((416666+2/3)*N19^3-625000*N19^2+(208333+1/3)*N19)-((416666+2/3)*O19^3-625000*O19^2+(208333+1/3)*O19))) -> 0 | Q19: =((UserBuildings!$M21+1)^2)*Static!$O68 -> 14400000 | R19: =ROUNDUP(SQRT(Q19/5000),0) -> 54 | S19: =VLOOKUP("Plastics",TblUserWarehouse,2,FALSE) -> 59 | T19: =IF(S19=0,0,IF((R19-S19)<0,0,((416666+2/3)*R19^3-625000*R19^2+(208333+1/3)*R19)-((416666+2/3)*S19^3-625000*S19^2+(208333+1/3)*S19))) -> 0 | U19: =((UserBuildings!$M21+1)^2)*Static!$O69 -> 450000000000
B20: Silver Refinery | C20: =IF(H20/G20<=0,"NO",H20/G20/24) -> 3464.1735 | D20: =IF(E20/G20<=0,"NO",E20/G20/24) -> 3637.3822 | E20: =H20*(1.15-UserBuildings!$T$16*0.01) -> 3.1014241e+11 | F20: =G20*24 -> 85265280 | G20: =Static!E21*'Supply Chain'!N50 -> 3552720 | H20: =(I20*'Supply Chain'!L36)+(M20*'Supply Chain'!L34)+(Q20*'Supply Chain'!L38)+U20+SUM(L20,P20,T20) -> 295373721500 | I20: =((UserBuildings!$M22+1)^2)*Static!$O70 -> 2535000 | J20: =ROUNDUP(SQRT(I20/5000),0) -> 23 | K20: =VLOOKUP("Steel",TblUserWarehouse,2,FALSE) -> 64 | L20: =IF(K20=0,0,IF((J20-K20)<0,0,((416666+2/3)*J20^3-625000*J20^2+(208333+1/3)*J20)-((416666+2/3)*K20^3-625000*K20^2+(208333+1/3)*K20))) -> 0 | M20: =((UserBuildings!$M22+1)^2)*Static!$O71 -> 5915000 | N20: =ROUNDUP(SQRT(M20/5000),0) -> 35 | O20: =VLOOKUP("Concrete",TblUserWarehouse,2,FALSE) -> 156 | P20: =IF(O20=0,0,IF((N20-O20)<0,0,((416666+2/3)*N20^3-625000*N20^2+(208333+1/3)*N20)-((416666+2/3)*O20^3-625000*O20^2+(208333+1/3)*O20))) -> 0 | Q20: =((UserBuildings!$M22+1)^2)*Static!$O72 -> 253500 | R20: =ROUNDUP(SQRT(Q20/5000),0) -> 8 | S20: =VLOOKUP("Glass",TblUserWarehouse,2,FALSE) -> 84 | T20: =IF(S20=0,0,IF((R20-S20)<0,0,((416666+2/3)*R20^3-625000*R20^2+(208333+1/3)*R20)-((416666+2/3)*S20^3-625000*S20^2+(208333+1/3)*S20))) -> 0 | U20: =((UserBuildings!$M22+1)^2)*Static!$O73 -> 126750000000
B21: Gold Refinery | C21: =IF(H21/G21<=0,"NO",H21/G21/24) -> 5262.8842 | D21: =IF(E21/G21<=0,"NO",E21/G21/24) -> 5526.0285 | E21: =H21*(1.15-UserBuildings!$T$16*0.01) -> 1.573438e+12 | F21: =G21*24 -> 284732160 | G21: =Static!E22*'Supply Chain'!N51 -> 11863840 | H21: =(I21*'Supply Chain'!L36)+(M21*'Supply Chain'!L34)+(Q21*'Supply Chain'!L38)+U21+SUM(L21,P21,T21) -> 1498512400000 | I21: =((UserBuildings!$M23+1)^2)*Static!$O74 -> 9680000 | J21: =ROUNDUP(SQRT(I21/5000),0) -> 44 | K21: =VLOOKUP("Steel",TblUserWarehouse,2,FALSE) -> 64 | L21: =IF(K21=0,0,IF((J21-K21)<0,0,((416666+2/3)*J21^3-625000*J21^2+(208333+1/3)*J21)-((416666+2/3)*K21^3-625000*K21^2+(208333+1/3)*K21))) -> 0 | M21: =((UserBuildings!$M23+1)^2)*Static!$O75 -> 9680000 | N21: =ROUNDUP(SQRT(M21/5000),0) -> 44 | O21: =VLOOKUP("Concrete",TblUserWarehouse,2,FALSE) -> 156 | P21: =IF(O21=0,0,IF((N21-O21)<0,0,((416666+2/3)*N21^3-625000*N21^2+(208333+1/3)*N21)-((416666+2/3)*O21^3-625000*O21^2+(208333+1/3)*O21))) -> 0 | Q21: =((UserBuildings!$M23+1)^2)*Static!$O76 -> 9680000 | R21: =ROUNDUP(SQRT(Q21/5000),0) -> 44 | S21: =VLOOKUP("Glass",TblUserWarehouse,2,FALSE) -> 84 | T21: =IF(S21=0,0,IF((R21-S21)<0,0,((416666+2/3)*R21^3-625000*R21^2+(208333+1/3)*R21)-((416666+2/3)*S21^3-625000*S21^2+(208333+1/3)*S21))) -> 0 | U21: =((UserBuildings!$M23+1)^2)*Static!$O77 -> 484000000000
B22: Goldsmith | C22: =IF(H22/G22<=0,"NO",H22/G22/24) -> #N/A | D22: =IF(E22/G22<=0,"NO",E22/G22/24) -> #N/A | E22: =H22*(1.15-UserBuildings!$T$16*0.01) -> #N/A | F22: =G22*24 -> 732945600 | G22: =Static!E23*'Supply Chain'!N52 -> 30539400 | H22: =(I22*'Supply Chain'!L33)+(M22*'Supply Chain'!L34)+(Q22*'Supply Chain'!L38)+U22+SUM(L22,P22,T22) -> #N/A | I22: =((UserBuildings!$M24+1)^2)*Static!$O78 -> 216090000 | J22: =ROUNDUP(SQRT(I22/5000),0) -> 208 | K22: =VLOOKUP("Bricks",TblUserWarehouse,2,FALSE) -> 190 | L22: =IF(K22=0,0,IF((J22-K22)<0,0,((416666+2/3)*J22^3-625000*J22^2+(208333+1/3)*J22)-((416666+2/3)*K22^3-625000*K22^2+(208333+1/3)*K22))) -> 887156250000 | M22: =((UserBuildings!$M24+1)^2)*Static!$O79 -> 48020000 | N22: =ROUNDUP(SQRT(M22/5000),0) -> 98 | O22: =VLOOKUP("Concrete",TblUserWarehouse,2,FALSE) -> 156 | P22: =IF(O22=0,0,IF((N22-O22)<0,0,((416666+2/3)*N22^3-625000*N22^2+(208333+1/3)*N22)-((416666+2/3)*O22^3-625000*O22^2+(208333+1/3)*O22))) -> 0 | Q22: =((UserBuildings!$M24+1)^2)*Static!$O80 -> 48020000 | R22: =ROUNDUP(SQRT(Q22/5000),0) -> 98 | S22: =VLOOKUP("Glass",TblUserWarehouse,2,FALSE) -> 84 | T22: =IF(S22=0,0,IF((R22-S22)<0,0,((416666+2/3)*R22^3-625000*R22^2+(208333+1/3)*R22)-((416666+2/3)*S22^3-625000*S22^2+(208333+1/3)*S22))) -> 1.4361375e+11 | U22: =((UserBuildings!$M24+1)^2)*Static!$O81 -> 1200500000000
B23: Drone Shipyard | C23: =IF(H23/G23<=0,"NO",H23/G23/24) -> #N/A | D23: =IF(E23/G23<=0,"NO",E23/G23/24) -> #N/A | E23: =H23*(1.15-UserBuildings!$T$16*0.01) -> #N/A | F23: =G23*24 -> 395887008 | G23: =Static!E24*'Supply Chain'!N53 -> 16495292 | H23: =(I23*'Supply Chain'!L33)+(M23*'Supply Chain'!L34)+(Q23*'Supply Chain'!L42)+U23+SUM(L23,P23,T23) -> #N/A | I23: =((UserBuildings!$M25+1)^2)*Static!$O82 -> 120000 | J23: =ROUNDUP(SQRT(I23/5000),0) -> 5 | K23: =VLOOKUP("Plastics",TblUserWarehouse,2,FALSE) -> 59 | L23: =IF(K23=0,0,IF((J23-K23)<0,0,((416666+2/3)*J23^3-625000*J23^2+(208333+1/3)*J23)-((416666+2/3)*K23^3-625000*K23^2+(208333+1/3)*K23))) -> 0 | M23: =((UserBuildings!$M25+1)^2)*Static!$O83 -> 80000 | N23: =ROUNDUP(SQRT(M23/5000),0) -> 4 | O23: =VLOOKUP("Concrete",TblUserWarehouse,2,FALSE) -> 156 | P23: =IF(O23=0,0,IF((N23-O23)<0,0,((416666+2/3)*N23^3-625000*N23^2+(208333+1/3)*N23)-((416666+2/3)*O23^3-625000*O23^2+(208333+1/3)*O23))) -> 0 | Q23: =((UserBuildings!$M25+1)^2)*Static!$O84 -> 40000 | R23: =ROUNDUP(SQRT(Q23/5000),0) -> 3 | S23: =VLOOKUP("Glass",TblUserWarehouse,2,FALSE) -> 84 | T23: =IF(S23=0,0,IF((R23-S23)<0,0,((416666+2/3)*R23^3-625000*R23^2+(208333+1/3)*R23)-((416666+2/3)*S23^3-625000*S23^2+(208333+1/3)*S23))) -> 0 | U23: =((UserBuildings!$M25+1)^2)*Static!$O85 -> 2000000000
B24: Truck plant | C24: =IF(H24/G24<=0,"NO",H24/G24/24) -> #N/A | D24: =IF(E24/G24<=0,"NO",E24/G24/24) -> #N/A | E24: =H24*(1.15-UserBuildings!$T$16*0.01) -> #N/A | F24: =G24*24 -> 109225200 | G24: =Static!E25*'Supply Chain'!N54 -> 4551050 | H24: =(I24*'Supply Chain'!L33)+(M24*'Supply Chain'!L50)+(Q24*'Supply Chain'!L47)+U24+SUM(L24,P24,T24) -> #N/A | I24: =((UserBuildings!$M26+1)^2)*Static!$O86 -> 60500000 | J24: =ROUNDUP(SQRT(I24/5000),0) -> 110 | K24: =VLOOKUP("Bricks",TblUserWarehouse,2,FALSE) -> 190 | L24: =IF(K24=0,0,IF((J24-K24)<0,0,((416666+2/3)*J24^3-625000*J24^2+(208333+1/3)*J24)-((416666+2/3)*K24^3-625000*K24^2+(208333+1/3)*K24))) -> 0 | M24: =((UserBuildings!$M26+1)^2)*Static!$O87 -> 6050000 | N24: =ROUNDUP(SQRT(M24/5000),0) -> 35 | O24: =VLOOKUP("Silver",TblUserWarehouse,2,FALSE) -> 201 | P24: =IF(O24=0,0,IF((N24-O24)<0,0,((416666+2/3)*N24^3-625000*N24^2+(208333+1/3)*N24)-((416666+2/3)*O24^3-625000*O24^2+(208333+1/3)*O24))) -> 0 | Q24: =((UserBuildings!$M26+1)^2)*Static!$O88 -> 10890000 | R24: =ROUNDUP(SQRT(Q24/5000),0) -> 47 | S24: =VLOOKUP("Electronics",TblUserWarehouse,2,FALSE) -> 50 | T24: =IF(S24=0,0,IF((R24-S24)<0,0,((416666+2/3)*R24^3-625000*R24^2+(208333+1/3)*R24)-((416666+2/3)*S24^3-625000*S24^2+(208333+1/3)*S24))) -> 0 | U24: =((UserBuildings!$M26+1)^2)*Static!$O89 -> 242000000000
B25: Haulage firm | C25: =SpecialBuildings!E2 -> #N/A | D25: =SpecialBuildings!C2 -> #N/A | F25: Approximately 1% of daily profit. | H25: See specialbuildings tab for details. See readme for explanation.
B27: Profit over time | C27: 100 | D27: 150 | E27: 200
B28: Brick Factory | C28: =$G3*24*C$27-$H3 -> #N/A | D28: =$G3*24*D$27-$H3 -> #N/A | E28: =$G3*24*E$27-$H3 -> #N/A
B29: Concrete Factory | C29: =$G4*24*C$27-$H4 -> #N/A | D29: =$G4*24*D$27-$H4 -> #N/A | E29: =$G4*24*E$27-$H4 -> #N/A
B30: Fertilizer Factory | C30: =$G5*24*C$27-$H5 -> #N/A | D30: =$G5*24*D$27-$H5 -> #N/A | E30: =$G5*24*E$27-$H5 -> #N/A
B31: Ironworks | C31: =$G6*24*C$27-$H6 -> #N/A | D31: =$G6*24*D$27-$H6 -> #N/A | E31: =$G6*24*E$27-$H6 -> #N/A
B32: Oil Refinery | C32: =$G7*24*C$27-$H7 -> -477990656000 | D32: =$G7*24*D$27-$H7 -> -455321216000 | E32: =$G7*24*E$27-$H7 -> -432651776000
B33: Glazier's Worshop | C33: =$G8*24*C$27-$H8 -> #N/A | D33: =$G8*24*D$27-$H8 -> #N/A | E33: =$G8*24*E$27-$H8 -> #N/A
B34: Copper Refinery | C34: =$G9*24*C$27-$H9 -> -397601328500 | D34: =$G9*24*D$27-$H9 -> -370893792500 | E34: =$G9*24*E$27-$H9 -> -344186256500
B35: Insecticide Factory | C35: =$G10*24*C$27-$H10 -> -444465547500 | D35: =$G10*24*D$27-$H10 -> -437097667500 | E35: =$G10*24*E$27-$H10 -> -429729787500
B36: Aluminium Factory | C36: =$G11*24*C$27-$H11 -> -749862967500 | D36: =$G11*24*D$27-$H11 -> -718047415500 | E36: =$G11*24*E$27-$H11 -> -686231863500
B37: Plastic Factory | C37: =$G12*24*C$27-$H12 -> -387033606000 | D37: =$G12*24*D$27-$H12 -> -377304534000 | E37: =$G12*24*E$27-$H12 -> -367575462000
B38: Lithium Refinery | C38: =$G13*24*C$27-$H13 -> -971664321000 | D38: =$G13*24*D$27-$H13 -> -955204221000 | E38: =$G13*24*E$27-$H13 -> -938744121000
B39: Battery Factory | C39: =$G14*24*C$27-$H14 -> -443489616000 | D39: =$G14*24*D$27-$H14 -> -427288176000 | E39: =$G14*24*E$27-$H14 -> -411086736000
... B49: Truck plant | C49: =$G24*24*C$27-$H24 -> #N/A | D49: =$G24*24*D$27-$H24 -> #N/A | E49: =$G24*24*E$27-$H24 -> #N/A

Sheet API Mine Detail
O1: =IFERROR(__xludf.DUMMYFUNCTION("if(AND($C$8=""ON"",UserBuildings!$C$2=1 ),importdata(B9),0)"),0) -> 0
B2: Keep B3 at 0 when not in use to avoid unnecessary API queries.
B3: =UserBuildings!C2 -> 0 | C3: API Key: | D3: =UserBuildings!G2 -> d2f7070074a24ff4c55a55a0c0ab3faa699c437a4d87b | H3: Number of Days:
C5: Query ID: | E5: Output Type ID: | G5: Language ID: | H5: en
B6: =HYPERLINK("https://www.resources","https://www.resources") -> https://www.resources | C6: =HYPERLINK("http://-game.ch/","-game.ch/") -> -game.ch/ | D6: resapi/?q= | E6: [Query ID] | F6: &f= | G6: 0 | H6: &k= | I6: [API Key] | J6: &l= | K6: [Language ID] | L6: &d= | M6: [Number of Days]
B8: Mine Detail | C8: ON
B9: =_xludf.textjoin("",TRUE,B6,C6,D6,5,F6,0,H6,D3,J6,$H$5,L6,10,"?") -> #NAME?

Sheet Headquarters
B1: =UserBuildings!W5 -> 9
B2: HQ Level | C2: Total Cost w/TC | D2: Total Cost | E2: Amount | F2: Resource 1 | G2: Cost | H2: Resource 2 | I2: Cost | J2: Resource 3 | K2: Cost | L2: Resource 4 | M2: Cost
B3: 2 | C3: =(G3+I3+K3+M3)*(1.15-(UserBuildings!T$16*0.01)) -> 2.959425e+09 | D3: =(G3+I3+K3+M3) -> 2818500000 | E3: 750000 | F3: Clay | G3: =IF(VLOOKUP(F3,TblMarket,3,FALSE)=0,(VLOOKUP(F3,TblMarket,2,FALSE)*$E3), (VLOOKUP(F3,TblMarket,3,FALSE)*$E3)) -> 262500000 | H3: Gravel | I3: =IF(VLOOKUP(H3,TblMarket,3,FALSE)=0,(VLOOKUP(H3,TblMarket,2,FALSE)*$E3), (VLOOKUP(H3,TblMarket,3,FALSE)*$E3)) -> 360000000 | J3: Limestone | K3: =IF(VLOOKUP(J3,TblMarket,3,FALSE)=0,(VLOOKUP(J3,TblMarket,2,FALSE)*$E3), (VLOOKUP(J3,TblMarket,3,FALSE)*$E3)) -> 384000000 | L3: Coal | M3: =IF(VLOOKUP(L3,TblMarket,3,FALSE)=0,(VLOOKUP(L3,TblMarket,2,FALSE)*$E3), (VLOOKUP(L3,TblMarket,3,FALSE)*$E3)) -> 1812000000
B4: 3 | C4: =(G4+I4+K4+M4)*(1.15-(UserBuildings!T$16*0.01)) -> #N/A | D4: =G4+I4+K4+M4 -> #N/A | E4: 1500000 | F4: Concrete | G4: =IF(VLOOKUP(F4,TblMarket,3,FALSE)=0,(VLOOKUP(F4,TblMarket,2,FALSE)*$E4), (VLOOKUP(F4,TblMarket,3,FALSE)*$E4)) -> 7764000000 | H4: Bricks | I4: =IF(VLOOKUP(H4,TblMarket,3,FALSE)=0,(VLOOKUP(H4,TblMarket,2,FALSE)*$E4), (VLOOKUP(H4,TblMarket,3,FALSE)*$E4)) -> #N/A | J4: Fertilizer | K4: =IF(VLOOKUP(J4,TblMarket,3,FALSE)=0,(VLOOKUP(J4,TblMarket,2,FALSE)*$E4), (VLOOKUP(J4,TblMarket,3,FALSE)*$E4)) -> 3256500000 | L4: Iron Ore | M4: =IF(VLOOKUP(L4,TblMarket,3,FALSE)=0,(VLOOKUP(L4,TblMarket,2,FALSE)*$E4), (VLOOKUP(L4,TblMarket,3,FALSE)*$E4)) -> 2064000000
B5: 4 | C5: =(G5+I5+K5+M5)*(1.15-(UserBuildings!T$16*0.01)) -> 1.33182e+10 | D5: =G5+I5+K5+M5 -> 12684000000 | E5: 2000000 | F5: Crude Oil | G5: =IF(VLOOKUP(F5,TblMarket,3,FALSE)=0,(VLOOKUP(F5,TblMarket,2,FALSE)*$E5), (VLOOKUP(F5,TblMarket,3,FALSE)*$E5)) -> 5156000000 | H5: Quartz Sand | I5: =IF(VLOOKUP(H5,TblMarket,3,FALSE)=0,(VLOOKUP(H5,TblMarket,2,FALSE)*$E5), (VLOOKUP(H5,TblMarket,3,FALSE)*$E5)) -> 714000000 | J5: Chalcopyrite | K5: =IF(VLOOKUP(J5,TblMarket,3,FALSE)=0,(VLOOKUP(J5,TblMarket,2,FALSE)*$E5), (VLOOKUP(J5,TblMarket,3,FALSE)*$E5)) -> 2714000000 | L5: Bauxite | M5: =IF(VLOOKUP(L5,TblMarket,3,FALSE)=0,(VLOOKUP(L5,TblMarket,2,FALSE)*$E5), (VLOOKUP(L5,TblMarket,3,FALSE)*$E5)) -> 4100000000
B6: 5 | C6: =(G6+I6+K6+M6)*(1.15-(UserBuildings!T$16*0.01)) -> 5.457375e+11 | D6: =G6+I6+K6+M6 -> 519750000000 | E6: 3000000 | F6: Fossil Fuel | G6: =IF(VLOOKUP(F6,TblMarket,3,FALSE)=0,(VLOOKUP(F6,TblMarket,2,FALSE)*$E6), (VLOOKUP(F6,TblMarket,3,FALSE)*$E6)) -> 96399000000 | H6: Copper | I6: =IF(VLOOKUP(H6,TblMarket,3,FALSE)=0,(VLOOKUP(H6,TblMarket,2,FALSE)*$E6), (VLOOKUP(H6,TblMarket,3,FALSE)*$E6)) -> 262005000000 | J6: Steel | K6: =IF(VLOOKUP(J6,TblMarket,3,FALSE)=0,(VLOOKUP(J6,TblMarket,2,FALSE)*$E6), (VLOOKUP(J6,TblMarket,3,FALSE)*$E6)) -> 148260000000 | L6: Insecticides | M6: =IF(VLOOKUP(L6,TblMarket,3,FALSE)=0,(VLOOKUP(L6,TblMarket,2,FALSE)*$E6), (VLOOKUP(L6,TblMarket,3,FALSE)*$E6)) -> 13086000000
B7: 6 | C7: =(G7+I7+K7+M7)*(1.15-(UserBuildings!T$16*0.01)) -> 5.36256e+11 | D7: =G7+I7+K7+M7 -> 510720000000 | E7: 4000000 | F7: Aluminium | G7: =IF(VLOOKUP(F7,TblMarket,3,FALSE)=0,(VLOOKUP(F7,TblMarket,2,FALSE)*$E7), (VLOOKUP(F7,TblMarket,3,FALSE)*$E7)) -> 385612000000 | H7: Lithium | I7: =IF(VLOOKUP(H7,TblMarket,3,FALSE)=0,(VLOOKUP(H7,TblMarket,2,FALSE)*$E7), (VLOOKUP(H7,TblMarket,3,FALSE)*$E7)) -> 121960000000 | J7: Lithium Ore | K7: =IF(VLOOKUP(J7,TblMarket,3,FALSE)=0,(VLOOKUP(J7,TblMarket,2,FALSE)*$E7), (VLOOKUP(J7,TblMarket,3,FALSE)*$E7)) -> 1948000000 | L7: Ilmenite | M7: =IF(VLOOKUP(L7,TblMarket,3,FALSE)=0,(VLOOKUP(L7,TblMarket,2,FALSE)*$E7), (VLOOKUP(L7,TblMarket,3,FALSE)*$E7)) -> 1200000000
B8: 7 | C8: =(G8+I8+K8+M8)*(1.15-(UserBuildings!T$16*0.01)) -> 2.0084452e+12 | D8: =G8+I8+K8+M8 -> 1912805000000 | E8: 5000000 | F8: Glass | G8: =IF(VLOOKUP(F8,TblMarket,3,FALSE)=0,(VLOOKUP(F8,TblMarket,2,FALSE)*$E8), (VLOOKUP(F8,TblMarket,3,FALSE)*$E8)) -> 251045000000 | H8: Batteries | I8: =IF(VLOOKUP(H8,TblMarket,3,FALSE)=0,(VLOOKUP(H8,TblMarket,2,FALSE)*$E8), (VLOOKUP(H8,TblMarket,3,FALSE)*$E8)) -> 1032965000000 | J8: Silicon | K8: =IF(VLOOKUP(J8,TblMarket,3,FALSE)=0,(VLOOKUP(J8,TblMarket,2,FALSE)*$E8), (VLOOKUP(J8,TblMarket,3,FALSE)*$E8)) -> 604785000000 | L8: Plastics | M8: =IF(VLOOKUP(L8,TblMarket,3,FALSE)=0,(VLOOKUP(L8,TblMarket,2,FALSE)*$E8), (VLOOKUP(L8,TblMarket,3,FALSE)*$E8)) -> 24010000000
B9: 8 | C9: =(G9+I9+K9+M9)*(1.15-(UserBuildings!T$16*0.01)) -> 4.446435e+11 | D9: =G9+I9+K9+M9 -> 423470000000 | E9: 10000000 | F9: Titanium | G9: =IF(VLOOKUP(F9,TblMarket,3,FALSE)=0,(VLOOKUP(F9,TblMarket,2,FALSE)*$E9), (VLOOKUP(F9,TblMarket,3,FALSE)*$E9)) -> 364610000000 | H9: Silver Ore | I9: =IF(VLOOKUP(H9,TblMarket,3,FALSE)=0,(VLOOKUP(H9,TblMarket,2,FALSE)*$E9), (VLOOKUP(H9,TblMarket,3,FALSE)*$E9)) -> 15110000000 | J9: Rough Diamonds | K9: =IF(VLOOKUP(J9,TblMarket,3,FALSE)=0,(VLOOKUP(J9,TblMarket,2,FALSE)*$E9), (VLOOKUP(J9,TblMarket,3,FALSE)*$E9)) -> 34230000000 | L9: Gold Ore | M9: =IF(VLOOKUP(L9,TblMarket,3,FALSE)=0,(VLOOKUP(L9,TblMarket,2,FALSE)*$E9), (VLOOKUP(L9,TblMarket,3,FALSE)*$E9)) -> 9520000000
B10: 9 | C10: =(G10+I10+K10+M10)*(1.15-(UserBuildings!T$16*0.01)) -> 8.054235e+12 | D10: =G10+I10+K10+M10 -> 7670700000000 | E10: 25000000 | F10: Electronics | G10: =IF(VLOOKUP(F10,TblMarket,3,FALSE)=0,(VLOOKUP(F10,TblMarket,2,FALSE)*$E10), (VLOOKUP(F10,TblMarket,3,FALSE)*$E10)) -> 1590450000000 | H10: Silver | I10: =IF(VLOOKUP(H10,TblMarket,3,FALSE)=0,(VLOOKUP(H10,TblMarket,2,FALSE)*$E10), (VLOOKUP(H10,TblMarket,3,FALSE)*$E10)) -> 40650000000 | J10: Gold | K10: =IF(VLOOKUP(J10,TblMarket,3,FALSE)=0,(VLOOKUP(J10,TblMarket,2,FALSE)*$E10), (VLOOKUP(J10,TblMarket,3,FALSE)*$E10)) -> 1559050000000 | L10: Medical technology | M10: =IF(VLOOKUP(L10,TblMarket,3,FALSE)=0,(VLOOKUP(L10,TblMarket,2,FALSE)*$E10), (VLOOKUP(L10,TblMarket,3,FALSE)*$E10)) -> 4480550000000
B11: 10 | C11: =(G11+I11+K11+M11)*(1.15-(UserBuildings!T$16*0.01)) -> #N/A | D11: =G11+I11+K11+M11 -> #N/A | E11: 50000000 | F11: Weapons | G11: =IF(VLOOKUP(F11,TblMarket,3,FALSE)=0,(VLOOKUP(F11,TblMarket,2,FALSE)*$E11), (VLOOKUP(F11,TblMarket,3,FALSE)*$E11)) -> #N/A | H11: Steel | I11: =IF(VLOOKUP(H11,TblMarket,3,FALSE)=0,(VLOOKUP(H11,TblMarket,2,FALSE)*$E11), (VLOOKUP(H11,TblMarket,3,FALSE)*$E11)) -> 2471000000000 | J11: Glass | K11: =IF(VLOOKUP(J11,TblMarket,3,FALSE)=0,(VLOOKUP(J11,TblMarket,2,FALSE)*$E11), (VLOOKUP(J11,TblMarket,3,FALSE)*$E11)) -> 2510450000000 | L11: Jewellery | M11: =IF(VLOOKUP(L11,TblMarket,3,FALSE)=0,(VLOOKUP(L11,TblMarket,2,FALSE)*$E11), (VLOOKUP(L11,TblMarket,3,FALSE)*$E11)) -> 103696500000000
B14: HQ ROI
B15: HQ ROI Days | C15: Daily Profit Increase | D15: Profit Increase | E15: Total Profit | F15: Total Profit/Day | G15: Total New Profit | H15: Total Mines (Optnl)
B16: =(VLOOKUP(UserBuildings!W5+1,B3:C11,2,FALSE)/C16) -> #N/A | C16: =D16*24 -> 3.0864365e+10 | D16: =G16-E16 -> 1.2860152e+09 | E16: =SUM(F20:F33) -> 1.3003043e+10 | F16: =E16*24 -> 3.1207302e+11 | G16: =SUM(G20:G33) -> 1.4289058e+10 | H16: 154
B17: Averages | C17: =C16/$H$16 -> 2.0041795e+08 | D17: =D16/$H$16 -> 8350748.1 | E17: =E16/$H$16 -> 84435341 | F17: =F16/$H$16 -> 2.0264482e+09 | G17: =G16/$H$16 -> 92786089
B19: Mine Type | C19: API Max Prod | D19: Manual Max Prod | E19: Max Production | F19: Profit/Hr | G19: Upgrade Profit/Hr | H19: Upg Produce | I19: Profit/Day
B20: Clay | C20: =SUMIFS('API Mine Detail'!S:S, 'API Mine Detail'!R:R,">1",'API Mine Detail'!Z:Z,B20) -> 0 | D20: 0 | E20: =IF(C20=0,D20,C20) -> 0 | F20: =VLOOKUP(B20,TblMarket,5,FALSE)*E20 -> 0 | G20: =(F20/(UserBuildings!$W$5*0.9+1))*((UserBuildings!$W$5+1)*0.9+1) -> 0 | H20: =(E20/(UserBuildings!$W$5*0.9+1))*((UserBuildings!$W$5+1)*0.9+1) -> 0 | I20: =F20*24 -> 0
B21: Coal | C21: =SUMIFS('API Mine Detail'!S:S, 'API Mine Detail'!R:R,">1",'API Mine Detail'!Z:Z,B21) -> 0 | D21: 0 | E21: =IF(C21=0,D21,C21) -> 0 | F21: =VLOOKUP(B21,TblMarket,5,FALSE)*E21 -> 0 | G21: =(F21/(UserBuildings!$W$5*0.9+1))*((UserBuildings!$W$5+1)*0.9+1) -> 0 | H21: =(E21/(UserBuildings!$W$5*0.9+1))*((UserBuildings!$W$5+1)*0.9+1) -> 0 | I21: =F21*24 -> 0
B22: Chalcopyrite | C22: =SUMIFS('API Mine Detail'!S:S, 'API Mine Detail'!R:R,">1",'API Mine Detail'!Z:Z,B22) -> 0 | D22: 0 | E22: =IF(C22=0,D22,C22) -> 0 | F22: =VLOOKUP(B22,TblMarket,5,FALSE)*E22 -> 0 | G22: =(F22/(UserBuildings!$W$5*0.9+1))*((UserBuildings!$W$5+1)*0.9+1) -> 0 | H22: =(E22/(UserBuildings!$W$5*0.9+1))*((UserBuildings!$W$5+1)*0.9+1) -> 0 | I22: =F22*24 -> 0
B23: Rough diamonds | C23: =SUMIFS('API Mine Detail'!S:S, 'API Mine Detail'!R:R,">1",'API Mine Detail'!Z:Z,B23) -> 0 | D23: 3547403.5 | E23: =IF(C23=0,D23,C23) -> 3547403.5 | F23: =VLOOKUP(B23,TblMarket,5,FALSE)*E23 -> 1.2142762e+10 | G23: =(F23/(UserBuildings!$W$5*0.9+1))*((UserBuildings!$W$5+1)*0.9+1) -> 1.3343695e+10 | H23: =(E23/(UserBuildings!$W$5*0.9+1))*((UserBuildings!$W$5+1)*0.9+1) -> 3898245.7 | I23: =F23*24 -> 2.914263e+11
B24: Gravel | C24: =SUMIFS('API Mine Detail'!S:S, 'API Mine Detail'!R:R,">1",'API Mine Detail'!Z:Z,B24) -> 0 | D24: 0 | E24: =IF(C24=0,D24,C24) -> 0 | F24: =VLOOKUP(B24,TblMarket,5,FALSE)*E24 -> 0 | G24: =(F24/(UserBuildings!$W$5*0.9+1))*((UserBuildings!$W$5+1)*0.9+1) -> 0 | H24: =(E24/(UserBuildings!$W$5*0.9+1))*((UserBuildings!$W$5+1)*0.9+1) -> 0 | I24: =F24*24 -> 0
B25: Ilmenite | C25: =SUMIFS('API Mine Detail'!S:S, 'API Mine Detail'!R:R,">1",'API Mine Detail'!Z:Z,B25) -> 0 | D25: 0 | E25: =IF(C25=0,D25,C25) -> 0 | F25: =VLOOKUP(B25,TblMarket,5,FALSE)*E25 -> 0 | G25: =(F25/(UserBuildings!$W$5*0.9+1))*((UserBuildings!$W$5+1)*0.9+1) -> 0 | H25: =(E25/(UserBuildings!$W$5*0.9+1))*((UserBuildings!$W$5+1)*0.9+1) -> 0 | I25: =F25*24 -> 0
B26: Iron ore | C26: =SUMIFS('API Mine Detail'!S:S, 'API Mine Detail'!R:R,">1",'API Mine Detail'!Z:Z,B26) -> 0 | D26: 0 | E26: =IF(C26=0,D26,C26) -> 0 | F26: =VLOOKUP(B26,TblMarket,5,FALSE)*E26 -> 0 | G26: =(F26/(UserBuildings!$W$5*0.9+1))*((UserBuildings!$W$5+1)*0.9+1) -> 0 | H26: =(E26/(UserBuildings!$W$5*0.9+1))*((UserBuildings!$W$5+1)*0.9+1) -> 0 | I26: =F26*24 -> 0
B27: Lithium ore | C27: =SUMIFS('API Mine Detail'!S:S, 'API Mine Detail'!R:R,">1",'API Mine Detail'!Z:Z,B27) -> 0 | D27: 1766489.2 | E27: =IF(C27=0,D27,C27) -> 1766489.2 | F27: =VLOOKUP(B27,TblMarket,5,FALSE)*E27 -> 8.6028023e+08 | G27: =(F27/(UserBuildings!$W$5*0.9+1))*((UserBuildings!$W$5+1)*0.9+1) -> 9.453629e+08 | H27: =(E27/(UserBuildings!$W$5*0.9+1))*((UserBuildings!$W$5+1)*0.9+1) -> 1941196.9 | I27: =F27*24 -> 2.0646726e+10
B28: Quartz sand | C28: =SUMIFS('API Mine Detail'!S:S, 'API Mine Detail'!R:R,">1",'API Mine Detail'!Z:Z,B28) -> 0 | D28: 0 | E28: =IF(C28=0,D28,C28) -> 0 | F28: =VLOOKUP(B28,TblMarket,5,FALSE)*E28 -> 0 | G28: =(F28/(UserBuildings!$W$5*0.9+1))*((UserBuildings!$W$5+1)*0.9+1) -> 0 | H28: =(E28/(UserBuildings!$W$5*0.9+1))*((UserBuildings!$W$5+1)*0.9+1) -> 0 | I28: =F28*24 -> 0
B29: Silver ore | C29: =SUMIFS('API Mine Detail'!S:S, 'API Mine Detail'!R:R,">1",'API Mine Detail'!Z:Z,B29) -> 0 | D29: 0 | E29: =IF(C29=0,D29,C29) -> 0 | F29: =VLOOKUP(B29,TblMarket,5,FALSE)*E29 -> 0 | G29: =(F29/(UserBuildings!$W$5*0.9+1))*((UserBuildings!$W$5+1)*0.9+1) -> 0 | H29: =(E29/(UserBuildings!$W$5*0.9+1))*((UserBuildings!$W$5+1)*0.9+1) -> 0 | I29: =F29*24 -> 0
